{"name":"Call for Papers for the 7th AISA International Interdisciplinary Conference, to be held in Nairobi, Kenya on June 28 to 30, 2017 at Multimedia University o","series":"","short":"","website":"http://www.isaafrican.org/index.php/all-for-papers-top-links","content":"Call for Papers for the 7th AISA International Interdisciplinary Conference, to be held in Nairobi, Kenya on June 28 to 30, 2017 at Multimedia University of Kenya General conference theme: “Africa at Development Crossroads” Conference Venue: Multimedia University of Kenya, Nairobi, Kenya Sponsors: African Interdisciplinary Studies Association (AISA), Kenya Scholars and Studies Association (KESSA) and AIDAL Organized and hosted by African Interdisciplinary Studies Association (AISA), this 7th International Interdisciplinary Conference will be held on June 28 to 30, 2017 at Nairobi, Kenya. The conference will bring together scholars from all over the world to make presentations on matters that touch on Africa. Send abstracts of between 250 and 500 words, including full contact details (title, name, address, email-address, and telephone) as well as institutional affiliation by March 30, 2017 to Prof. Maurice N. Amutabi at africanstudiesassociaiton@gmail.com or mauriceamutabi@gmail.com or neddylinnet@gmail.com or Amutabi@yahoo.com or Amutabi@gmail.com The deadline for submission of full papers or PowerPoint presentation is May 30, 2017\\. Most papers presented at the conference will be selected and published in edited volumes and journals affiliated to African Interdisciplinary Studies Association (AISA). The official language of the conference is English. The conference will consist of ten colloquia organized along themes. Colloquium 1: Africa and Sectoral Development Colloquium 2: Economics and Management of Resources in Africa Colloquium 3: Education and Development in Africa Colloquium 4: Judiciary, Constitutionalism and Human Rights Colloquium 5: Engineering, Science and Technology in Africa Colloquium 6: Religion, NGOs and non-State Agencies in Development in Africa Colloquium 7: Security, Peace and Conflict in Africa Colloquium 8: Library, Information and Communication Technology Colloquium 9: Interdisciplinary and Multidisciplinary Research in Africa Colloquium 10: Roundtables, independent panels and association meetings Registration Fees: https://kenyasocialscienceforum.wordpress.com/2016/06/13/call-for-papers-for-the-7th-international-interdisciplinary-conference-to-be-held-in-nairobi-kenya-on-june-28-to-30-2017-at-multimedia-university-of-kenya-hotel-2/ 1\\. Staff from East African Universities and Organizations US$ 60 (KES 6,000) 2\\. Rest of Africa US$ 150 3\\. Rest of the World – Europe, North America, Asia, etc US$ 200 4\\. Exhibition and advertising stand - US$ 200 Registration fee payments to: African Interdisciplinary Studies Association (AISA), Nairobi, Kenya ALL GENERAL ENQUIRIES TO BE ADDRESSED TO: Prof. Maurice N. Amutabi, Convenor and Chair African Interdisciplinary Studies Association (AISA), Nairobi, Kenya P.O. Box 13447-00400, Nairobi, Kenya E-mail: africanstudiesassociaiton@gmail.com or mauriceamutabi@gmail.com or neddylinnet@gmail.com or Amutabi@yahoo.com or Amutabi@gmail.com","date_start":"2017-06-27","date_end":"2017-06-30","important_dates":{"abstract":"","full":"2017-03-30","notification":"","final":""},"topics":["Education / Legal / Other","Education","interdisciplinary"],"location":{"virtual":"","full":["Nairobi","Kenya"],"name":"","street":"","city":"Nairobi","state":"","ZIP":"","country":"Kenya"},"organizers":["African Interdisciplinary Studies Association (AISA)"],"societies":[],"indexes":[],"emails":["africanstudiesassociaiton@gmail.com","mauriceamutabi@gmail.com","neddylinnet@gmail.com","amutabi@yahoo.com","amutabi@gmail.com"]}