{"name":"2019 3rd International Conference on Sustainable Development and Green Buildings","series":"","short":"ICSDGB 2019","website":"http://www.icsdgb.org/ ","content":"EI/Scopus-ICSDGB: 2019 3rd International Conference on Sustainable Development and Green Buildings (ICSDGB 2019) Call For Papers 2019 3rd International Conference on Sustainable Development and Green Buildings (ICSDGB 2019) Apr. 25-27, 2019| Qingdao, China Web: http://www.icsdgb.org/ 2019 3rd International Conference on Sustainable Development and Green Buildings (ICSDGB 2019) will be held in Qingdao, China during Apr.25-27, 2019, in conjunction with 2019 3rd International Conference on Environmental and Energy Engineering (IC3E 2019). ICSDGB 2019 is co-organized by Shandong University, International Society for Environmental Information Sciences (ISEIS) and APISE, sponsored by Xiamen University of Technology. ICSDGB 2017 & 2018 was successfully held in Suzhou and Xiamen, respectively. We believe that ICSDGB 2019 will be more attractive and meaningful. This conference is a platform for researchers, engineers, academicians as well as industrial professionals from all over the world to present their research results and development activities in Sustainable Development and Green Buildings. This conference provides opportunities for the delegates to exchange new ideas and application experiences face to face, to establish business or research relations and to find global partners for future collaboration. We sincerely invite all the researchers, scholars, engineers, students and people are in interested in these areas to take part in ICSDGB 2019\\. ●Publication and Indexing All the registered and presented will be included in the conference proceeding, which will be published in the volume of conference proceedings , which will be indexed by Ei Compendex, SCOPUS, Inspec, Conference Proceedings Citation Index – Science (CPCI-S)(Thomson Reuters, Web of Science), NASA Astrophysics Data System, and other databases. ●Topics(for more topics: http://www.icsdgb.org/CFP.html) Sustainable Development Green Building Air emission trading Building Technology Economic instruments Building Materials Material Quality and Control Carbon capture and storage Monitoring and Control of Structures Environmental Protection Technologies Environmental Science and Technology Environmental dynamics Structural Engineering and Disaster Reduction Clean technologies Environmental sustainability Water treatment and reclamation Renewable sources of energy-energy savings Suspended and fixed film biological processes ●Paper Submission Submission Email:icsdgb@apise.org Electronic submission system: https://cmt3.research.microsoft.com/ICSDGB2019 ●Call for participants 1, Presenter: If you are interested in giving presentation on conference, without publishing your paper in the proceeding, you need to submit the abstract and title of your presentation to us:cceai@apise.org 2, Listener: You are welcome to attend this great event. You need to complete the registration as Listener before the registration deadline. 3, Invited Speakers: If you are interested in being an invited speaker, to share your ideas in the felid of Control Engineering and Artificial Intelligence, you are welcome to join us! Please send your CV to us. 4, Reviewer: We sincerely welcome professors, associate professors, teachers and other experts in the areas of Machine Vision and Information Technology join the conference as a reviewer. ●Contact Us Ms. Linda Lee E-mail: icsdgb@apise.org Tel:+852-30506939( Hong Kong) Web: http://www.icsdgb.org/","date_start":"2019-04-25","date_end":"2019-04-27","important_dates":{"abstract":"","full":"2018-08-10","notification":"","final":""},"topics":["Engineering & Technology","Architectural/Environmental"],"location":{"virtual":"","full":["Qingdao","China"],"name":"","street":"","city":"Qingdao","state":"","ZIP":"","country":"China"},"organizers":["APISE"],"societies":[],"indexes":[],"emails":["icsdgb@apise.org","cceai@apise.org"]}