{"name":"The 5th Int'l Conference on Acoustics, Vibration and Noise Control","series":"","short":"CAVNC 2022","website":"https://www.wsaugust.org/conference/CAVNC2022","content":"The 5th Int'l Conference on Acoustics, Vibration and Noise Control (CAVNC 2022) Conference Date: August 13-15, 2022 Conference Venue: Xiamen, China Website: https://www.wsaugust.org/conference/CAVNC2022/ Online Registration System: https://www.wsaugust.org/RegistrationSubmission/default.aspx?ConferenceID=1498 Email: wsaugust@126.com The 5th Int'l Conference on Acoustics, Vibration and Noise Control (CAVNC 2022) will be held from August 13-15, 2022 in Xiamen, China. This Conference will cover issues on Acoustics, Acoustical Engineering, Vibration and Noise Control, Noise Impacts, Noise Control Engineering, etc. It dedicates to creating a stage for exchanging the latest research results and sharing the advanced research methods. If you wish to serve the conference as an invited speaker, please send email to us with your CV. We'll contact with you asap. Publication and Presentation Publication: Open Access Journalï¼Œplease contact us for detailed information Index: CNKI and Google Scholar Note: If you want to present your research results but do NOT wish to publish a paper, you may simply submit an Abstract to our Registration System. Contact Us Email: wsaugust@126.com (Editor.RolinZhang@gmail.com) Tel: +86 18627814037 QQ: 1349406763 Wechat: 3025797047 Official Account: Academic Communications Attendance Methods 1.Submit full paper (Regular Attendance+Paper Publication+Presentation) You are welcome to submit full paper, all the accepted papers will be published by Open access journal. 2\\. Submit abstract (Regular Attendance+Abstract+Presentation) 3\\. Regular Attendance (No Submission Required) Conference Topics Acoustics Airborne Acoustics Architectural Acoustics Bioacoustics Building and Room Acoustics Architectural Acoustics Communication Acoustics Computational Acoustics Electro-acoustic and Audio Engineering Environmental Acoustics Forensic Acoustics Aerodynamic and Acoustic Flight Tests Medical Acoustics Musical Acoustics Physical Acoustics Underwater Acoustics Acoustical Engineering Vibration Acoustics Ultrasonics Structural Acoustic Aeroacoustics Applied Acoustics Audio Engineering Electroacoustics Acoustic Levitation Acoustical Oceanography Acoustics for Navigation Acoustics of Bubbles Acoustic Tomography Vibration and Noise Control Advanced Vibration Construction Vibration Vibration Isolation of Buildings Vibration Modal and Fatigue Analysis Machinery and Equipment Vibration Isolation Insulation of building elements Vibration control Environmental Noise Assessments Noise Contour Maps Noise Impacts Noise Risk Assessments Noise Studies for Land-use Planning Noise Sources and control Noise Exposure Stationary Noise Source Measurements HVAC Noise Control Industrial Noise Control Traffic Noise and Vibration Wind Turbine Noise Noise Control Engineering Ambient Noise Sound insulation","date_start":"2022-08-13","date_end":"2022-08-15","important_dates":{"abstract":"","full":"2022-07-13","notification":"","final":""},"topics":["Physical Science & Math","Physics","Acoustics"],"location":{"virtual":"","full":["Xiamen","China"],"name":"","street":"","city":"Xiamen","state":"","ZIP":"","country":"China"},"organizers":["Academic Communications"],"societies":[],"indexes":[],"emails":["wsaugust@126.com","editor.rolinzhang@gmail.com"]}