{"name":"2022 Int'l Conference on Industrial and Mechanical Engineering","series":"","short":"CIME 2022","website":"https://www.eventcet.org/conference/CET2022","content":"2022 Int'l Conference on Industrial and Mechanical Engineering (CIME 2022) Website：https://www.eventcet.org/conference/CET2022/ Date：Oct. 31-Nov. 2, 2022 Venue：Kunming, China Online Registration Entrance：https://www.eventcet.org/RegistrationSubmission/default.aspx?ConferenceID=1514 2022 Int’l Conference on Industrial and Mechanical Engineering (CIME 2022), which will be held from October 31 to November 2, 2022, in Kunming, China, is one of the special tracks within The 9th World Congress on Engineering and Technology (CET 2022). The main objective of CIME 2022 is to provide a platform for researchers, engineers and academicians from all over the world to present their research results and development activities in Industrial and Mechanical Engineering. This symposium provides opportunities for the delegates to exchange new ideas and application experiences face to face, to establish business or research relations and to find global partners for future collaboration. Attendance Methods 1\\. Full Paper submission Submit full paper ( Regular Attendance + Paper Publication + Presentation ) You are invited to submit papers and participate in our academic exchange. One author will be invited to make an oral presentation and the paper will be published by peer-reviewed open access journal and submitted to CNKI and Google Scholar for indexing. 2.Abstract submission Submit abstract ( Regular Attendance + Abstract + Presentation ) You are welcome to submit abstract for oral presentation or poster presentation. 3.Regular Attendance ( No Submission Required ) You're also welcome to attend our conference (without submitting full paper or abstract) Publication and Presentation Publication: All the accepted papers will be published by a peer-reviewed open access journal that can ensure the widest dissemination of your published work Index: CNKI and Google Scholar Note: 1\\. If you want to present your research results but do NOT wish to publish a paper, you may simply submit an Abstract. 2\\. The simple Abstract submission should include the title, contents, keywords, authors names, affiliations and emails. The length is suggested to be controlled within 1 page and no more than 2 pages. 3\\. You will receive the review results within 3-5 working days after submission. If you do not get any notification within the time limit, please contact us as soon as possible. Contact Us Email: editor\\_cfp@163.com (workshop\\_editor@hotmail.com) Tel: +86 13296503784 (Monday to Friday) QQ: 1349406763 WeChat: 3025797047 Official Account: Academic Communications","date_start":"2022-10-31","date_end":"2022-11-02","important_dates":{"abstract":"","full":"2022-10-25","notification":"","final":""},"topics":["Engineering & Technology","Mechanical/Industrial"],"location":{"virtual":"","full":["Kunming","China"],"name":"","street":"","city":"Kunming","state":"","ZIP":"","country":"China"},"organizers":["Academic Communications"],"societies":[],"indexes":[],"emails":["_cfp@163.com","_editor@hotmail.com"]}