{"name":"2022 Int'l Conference on Preschool Education and Child Development","series":"","short":"PECD 2022","website":"https://www.sepconf.org/conference/PECD2022","content":"2022 Int'l Conference on Preschool Education and Child Development (PECD 2022) Website：https://www.sepconf.org/conference/PECD2022/ Date：October 28-30, 2022 Venue：Kunming, China Online Registration Entrance：http://www.sepconf.org/RegistrationSubmission/default.aspx?ConferenceID=1509 2022 Int'l Conference on Preschool Education and Child Development (PECD 2022) will be held from October 28 to 30, 2022 in Kunming, China. This Conference will cover issues on Preschool Education and Child Development. The aim of PECD 2022 is to provide a stage for researchers, engineers, academicians as well as industrial professionals from all over the world to present their latest research results and advanced research methods. Attendance Methods 1\\. Full Paper submission Submit full paper ( Regular Attendance + Paper Publication + Presentation ) You are invited to submit papers and participate in our academic exchange. One author will be invited to make an oral presentation and the paper will be published by peer-reviewed open access journal and submitted to CNKI and Google Scholar for indexing. 2.Abstract submission Submit abstract ( Regular Attendance + Abstract + Presentation ) You are welcome to submit abstract for oral presentation or poster presentation. 3.Regular Attendance ( No Submission Required ) You're also welcome to attend our conference (without submitting full paper or abstract) Publication and Presentation Publication: All the accepted papers will be published by a peer-reviewed open access journal that can ensure the widest dissemination of your published work Index: CNKI and Google Scholar Note: 1\\. If you want to present your research results but do NOT wish to publish a paper, you may simply submit an Abstract. 2\\. The simple Abstract submission should include the title, contents, keywords, authors names, affiliations and emails. The length is suggested to be controlled within 1 page and no more than 2 pages. 3\\. You will receive the review results within 3-5 working days after submission. If you do not get any notification within the time limit, please contact us as soon as possible. Contact Us Email: workshop9@126.com (workshop\\_editor@hotmail.com) Tel: +86 18672346485 (Monday to Friday) QQ: 1349406763 WeChat: 3025797047 Official Account: Academic Communications","date_start":"2022-10-28","date_end":"2022-10-30","important_dates":{"abstract":"","full":"2022-10-18","notification":"","final":""},"topics":["Education / Legal / Other","Education"],"location":{"virtual":"","full":["Kunming","China","China"],"name":"","street":"","city":"Kunming","state":"China","ZIP":"","country":"China"},"organizers":["Academic Communications"],"societies":[],"indexes":[],"emails":["workshop9@126.com","_editor@hotmail.com"]}