{"name":"5th International Conference on Automation, Control and Robotics Engineering","series":"","short":"CACRE 2020","website":"http://www.cacre.org","content":"Call for paper 5th International Conference on Automation, Control and Robotics Engineering (CACRE 2020) July . 16-18, 2020 / Dalian, China http://www.cacre.org/ 5th International Conference on Automation, Control and Robotics Engineering (CACRE 2020), which is in conjunction with the 5th International Conference on Artificial Intelligence and Robotics ( ICAIR 2020), co-organized by Dalian Maritime University and Hong Kong Society of Mechanical Engineers(HKSME), sponsored by Georgia Institute of Technology and Sichuan University. The conference will be held at Dalian, China from July 16 to 18, 2020\\. The CACRE has been held for four years since 2016, attracting scholars and students from all over the world. The CACRE 2020 Conference will provide a wonderful forum for you to update your knowledge base and explore the innovations in Automation, Control and Robotics Engineering. The conference will strive to offer you plenty of networking opportunities to meet and interact with the leading scientists, engineers and researchers, friends and colleagues as well as sponsors and exhibitors. ●Publication and Indexing All submissions will be peer reviewed, and all the registered and presented papers will be published in Conference Proceedings, which will be indexed by EI Compendex, Scopus, Thomson Reuters (WoS), Inspec, and other indexing organizations. #CACRE 2019 was published in ACM-International Conference Proceedings Series and Indexed by Ei Compendex. ●Topics of interest for submission include, but are not limited to: Robotics Science and Engineering Control Science and Engineering Automation Science and Engineering Vision Science and Engineering More topics can be found at: http://www.cacre.org/Cfp.html ●Paper Submission 1.You can choose to submit your paper directly to cacre@smehk.org 2.You can submit your full paper through electronic submission system: https://cmt3.research.microsoft.com/CACRE2020 ●Call for participants 1, Presenter: If you are interested in giving presentation on conference,without publishing your paper in the proceeding, you need to submit the abstract and title of your presentation to us:cacre@smehk.org 2, Listener: You are welcome to attend this great event. You need to complete the registration as Listener before the registration deadline. 3, Reviewer: We sincerely welcome professors, associate professors, teachers and other experts in the areas of Automation, Control and Robotics join the conference as a reviewer. ●Contact Us: If you have any question, please feel free to contact our conference secretary. Ms. Amber Cao Tel:+852-30506862 Email :cacre@smehk.org http://www.cacre.org/","date_start":"2020-07-16","date_end":"2020-07-18","important_dates":{"abstract":"","full":"2020-06-15","notification":"","final":""},"topics":["Engineering & Technology","Other","Robotics"],"location":{"virtual":"","full":["Dalian","China"],"name":"","street":"","city":"Dalian","state":"","ZIP":"","country":"China"},"organizers":["Hong Kong Society of Mechanical Engineers(HKSME)"],"societies":[],"indexes":[],"emails":["cacre@smehk.org"]}