{"name":"The 4th Int'l Conference on Soil Remediation and Plant Protection","series":"","short":"SRPP 2022","website":"https://www.novevents.org/conference/SRPP2022","content":"The 4th Int'l Conference on Soil Remediation and Plant Protection (SRPP 2022) Website：https://www.novevents.org/conference/SRPP2022/ Date：November 25-27, 2022 Venue：Guilin, China Online Registration Entrance：https://www.novevents.org/RegistrationSubmission/default.aspx?ConferenceID=1524 The 4th Int'l Conference on Soil Remediation and Plant Protection (SRPP 2022) will be held during November 25-27, 2022 in Guilin, China. This Conference will cover issues on Soil Science Soil and Global Change, Soil Ecology, Soil Environment, Plant Protection and other Related Topics. It dedicates to creating a stage for exchanging the latest research results and sharing the advanced research methods in related fields. Attendance Methods 1\\. Full Paper submission Submit full paper ( Regular Attendance + Paper Publication + Presentation ) You are invited to submit papers and participate in our academic exchange. One author will be invited to make an oral presentation and the paper will be published by peer-reviewed open access journal and submitted to CNKI and Google Scholar for indexing. 2.Abstract submission Submit abstract ( Regular Attendance + Abstract + Presentation ) You are welcome to submit abstract for oral presentation or poster presentation. 3.Regular Attendance ( No Submission Required ) You're also welcome to attend our conference (without submitting full paper or abstract) Publication and Presentation Publication: All the accepted papers will be published by a peer-reviewed open access journal that can ensure the widest dissemination of your published work Index: CNKI and Google Scholar Note: 1\\. If you want to present your research results but do NOT wish to publish a paper, you may simply submit an Abstract. 2\\. The simple Abstract submission should include the title, contents, keywords, authors names, affiliations and emails. The length is suggested to be controlled within 1 page and no more than 2 pages. 3\\. You will receive the review results within 3-5 working days after submission. If you do not get any notification within the time limit, please contact us as soon as possible. Contact Us Email: rolin\\_zhang@163.com (Seminar.Group@hotmail.com) Tel: +86 13264702250 QQ: 1349406763 WeChat: 3025797047 Official Account: Academic Communications","date_start":"2022-11-25","date_end":"2022-11-27","important_dates":{"abstract":"","full":"2022-11-17","notification":"","final":""},"topics":["Life Sciences","Ecology"],"location":{"virtual":"","full":["Guilin","China"],"name":"","street":"","city":"Guilin","state":"","ZIP":"","country":"China"},"organizers":["Academic Communications"],"societies":[],"indexes":[],"emails":["_zhang@163.com","seminar.group@hotmail.com"]}