{"name":"The 3rd Int'l Symposium on Superconductivity and Magnetism","series":"","short":"ISSM 2022","website":"http://www.wsaugust.org/conference/ISSM2022","content":"The 3rd Int'l Symposium on Superconductivity and Magnetism (ISSM 2022) Conference Date: August 13-15, 2022 Conference Venue: Xiamen, China Website: http://www.wsaugust.org/conference/ISSM2022 Online Registration System: https://www.wsaugust.org/RegistrationSubmission/default.aspx?ConferenceID=1500 Email: wsaugust@126.com The 3rd Int'l Symposium on Superconductivity and Magnetism (ISSM 2022) will be held from August 13-15, 2022 in Xiamen, China. This Conference will cover issues on Superconductivity and Magnetism. It dedicates to creating a stage for exchanging the latest research results and sharing the advanced research methods. If you wish to serve the conference as an invited speaker, please send email to us with your CV. We'll contact with you asap. Publication and Presentation Publication: Open Access Journalï¼Œplease contact us for detailed information Index: CNKI and Google Scholar Note: If you want to present your research results but do NOT wish to publish a paper, you may simply submit an Abstract to our Registration System. Contact Us Email: wsaugust@126.com (Editor.RolinZhang@gmail.com) Tel: +86 18627814037 QQ: 1349406763 Wechat: 3025797047 Official Account: Academic Communications Attendance Methods 1.Submit full paper (Regular Attendance+Paper Publication+Presentation) You are welcome to submit full paper, all the accepted papers will be published by Open access journal. 2\\. Submit abstract (Regular Attendance+Abstract+Presentation) 3\\. Regular Attendance (No Submission Required) Conference Topics Accelerator magnets Ancillary materials for superconducting applications Applied superconductivity Biomedical diagnostics and imaging Cables (HTS, LTS), CICC, and current leads Critical current and flux pinning Critical temperature and critical fields Cryogenics for superconducting devices and system integration Electromagnetic compatibility Energy storage Functional magnetic materials and non-recording applications Fusion magnets GMR of multilayers, magnetic contacts and constrictions High-temperature superconductivity HTS magnets Insulation and dielectrics Intermetallic and other hard magnets Large superconducting and related systems Levitation, transportation, and propulsion Magnet design and analysis techniques Magnet stability, magnetization effects, AC losses and protection Magnetic fluids and separation Magnetic microscopy and imaging Magnetic semiconductors Magnetic thin films and nanostructures Magnetic tunneling junctions Magnetization and time-dependent losses Magneto-caloric materials and devices Magnetodynamics and ferromagnetic resonance Magneto-elastic materials and devices Magnetoimpedance and high frequency materials Magneto-optic materials and devices Micromagnetics and multiscale modeling Molecular and novel magnetic materials Multiferroic materials Nanostructured and composite hard magnetic materials Novel biomedical therapies and nanomedicine Organic and carbon-based spin transport Permanent magnet materials Pnictides and related materials Properties important for applications Rare earth transition metal borides Recording physics, modeling, theory and testing Shielding, levitation and propulsion Soft magnetic materials Spin transfer torque Superconducting electrical power devices Superconducting electronics Superconducting magnets Superconducting phase transition Superconductivity and zero electrical resistance","date_start":"2022-08-13","date_end":"2022-08-15","important_dates":{"abstract":"","full":"2022-07-13","notification":"","final":""},"topics":["Physical Science & Math","Physics","Superconductivity"],"location":{"virtual":"","full":["Xiamen","China"],"name":"","street":"","city":"Xiamen","state":"","ZIP":"","country":"China"},"organizers":["Academic Communications"],"societies":[],"indexes":[],"emails":["wsaugust@126.com","editor.rolinzhang@gmail.com"]}