{"name":"International Conference on Foreign Language Education and Linguistics","series":"","short":"FLEL 2021","website":"https://www.sepconf.org/conference/FLEL2021","content":"International Conference on Foreign Language Education and Linguistics (FLEL 2021) Website: https://www.sepconf.org/conference/FLEL2021/ Date: October 22-24, 2021 Venue: Xi’an Grand Dynasty Culture Hotel, Xi’an China Organizer Meeting Link: https://www.academicx.org/ Online Submission: https://www.sepconf.org/RegistrationSubmission/default.aspx?ConferenceID=1390 Email Submission: workshop9@126.com About FLEL2021: International Conference on Foreign Language Education and Linguistics (FLEL 2021) will be held from October 22 to 24, 2021 in Xi'an, China. This Conference will cover issues on Foreign Language Education and Linguistics and other related topics. It dedicates to creating a stage for exchanging the latest research results and sharing the advanced research methods in related fields. Publication and Presentation: Publication: All the accepted papers will be published by a peer-reviewed open access journal that can ensure the widest dissemination of your published work. For more information, please contact us (workshop9@126.com). Index: CNKI and Google Scholar Note: If you want to present your research results but do NOT wish to publish a paper, you may simply submit an Abstract to our Registration System. Participation Methods: Full Paper Submission: Regular Attendance + Paper Publication + Presentation. One author will be invited to make an oral presentation and the paper will be published Abstract Submission: Regular Attendance + Abstract Presentation. Abstract will be accepted and author will be invited to make an oral presentation. Audience Participation: Regular Attendance (No Submission Required) Keynote speakers: 45 minutes theme report Contact Us: Email: workshop9@126.com Tel: +86 18672346485 QQ: 1349406763 WeChat: 3025797047 Twitter: conf\\_Committee Topics: Applied Linguistics Computer Assisted Language Learning Conversational Analysis Cultural Studies Curriculum Development and Syllabus Design Deep Language Processing Dialogue Systems Discourse Analysis Discourse Analysis and Critical Discourse Analysis English for Specific Purposes Fluent Teacher Interactions Foreign Language Teaching and Learning Functional Grammar General Linguistics Globalization Studies and world English’s Information and Computer Technology in TEFL Innovation in language Teaching and learning Intercultural Education Intercultural studies Language Acquisition and learning Language Planning, Literature, Syntax and Semantics Language Testing and Assessment Linguistic Literacy Studies Literature Pragmatics Pronunciation Modeling Psycholinguistics Second Language Semantics Sociolinguistics Speech Processing Speech Quality and Intelligibility Tests Stylistics, Language and Culture, Cognition, and Pragmatics Bilingual and Multilingual Education Teaching English as a Foreign/ Second Language TESOL / TESL / TEFL Text Understanding Systems Text/Corpus Linguistics Translation Studies","date_start":"2021-10-22","date_end":"2021-10-24","important_dates":{"abstract":"","full":"2021-09-30","notification":"","final":""},"topics":["Education / Legal / Other","Education","linguistics"],"location":{"virtual":"","full":["Xi'an","China"],"name":"","street":"","city":"Xi'an","state":"","ZIP":"","country":"China"},"organizers":[""],"societies":[],"indexes":[],"emails":["workshop9@126.com"]}