{"name":"12th International Conference on Artificial Intelligence, Soft Computing and Applications","series":"","short":"AIAA 2022","website":"https://cndc2022.org/aiaa/index","content":"12th International Conference on Artificial Intelligence, Soft Computing and Applications (AIAA 2022) December 23 \\~ 24, 2022, Sydney, Australia https://cndc2022.org/aiaa/index Scope & Topics 12th International Conference on Artificial Intelligence, Soft Computing and Applications (AIAA 2022) will provide an excellent international forum for sharing knowledge and results in theory, methodology and applications of Artificial Intelligence, Soft Computing. The Conference looks for significant contributions to all major fields of the Artificial Intelligence, Soft Computing in theoretical and practical aspects. The aim of the Conference is to provide a platform to the researchers and practitioners from both academia as well as industry to meet and share cutting-edge development in the field. Topics of interest include, but are not limited to, the following • Artificial Intelligence • AI Algorithms • Artificial Intelligence Tools & Applications • Automatic Control • Bioinformatics • Natural Language Processing • CAD Design & Testing • Data Mining and Machine Learning Tools • Fuzzy Logic • Heuristic and AI Planning Strategies and Tools • Computational Theories of Learning • Hybrid Intelligent Systems • Information Retrieval • Intelligent System Architectures • Knowledge Representation • Knowledge-based Systems • Mechatronics • Multimedia & Cognitive Informatics • Neural Networks • Parallel Processing • Pattern Recognition • Pervasive Computing and Ambient Intelligence • Programming Languages • Reasoning and Evolution • Recent Trends and Developments • Robotics • Soft Computing and Applications • Fuzzy Systems • Neural Networks • Machine Learning • Probabilistic Reasoning • Evolutionary Computing • Hybrid Intelligent Systems • Software Agents • Morphic Computing • Image Processing • E-commerce, E-medicine • Rough Sets • Symbolic Machine Learning • Wavelet • Signal or Image Processing • Vision Recognition • Biomedical Engineering • Telecommunications • Reactive Distributed AI • Nano & Micro-systems • Data Visualization • Semantic Web Techniques and Technologies • Soft Computing Theory and Applications • Software & Hardware Architectures • Web Intelligence Applications & Search Paper Submission Authors are invited to submit papers through the conference Submission System by November 19, 2022\\. Submissions must be original and should not have been published previously or be under consideration for publication while being evaluated for this conference. The proceedings of the conference will be published by Computer Science Conference Proceedings in Computer Science & Information Technology (CS & IT) series (Confirmed). Selected papers from AIAA 2022, after further revisions, will be published in the special issues of the following journals. • International Journal on Soft Computing (IJSC) • International Journal of Artificial Intelligence & Applications (IJAIA) • Information Technology in Industry (ITII) Contact Us Here's where you can reach us: aiaa@cndc2022.org (or) aiaaconference@yahoo.com For more details, please visit: https://cndc2022.org/aiaa/index Paper Submission Link: https://cndc2022.org/submission/index.php","date_start":"2022-12-23","date_end":"2022-12-24","important_dates":{"abstract":"","full":"2022-11-19","notification":"","final":""},"topics":["Engineering & Technology","Computer/Informatics","data mining"],"location":{"virtual":"","full":["Sydney","Australia"],"name":"","street":"","city":"Sydney","state":"","ZIP":"","country":"Australia"},"organizers":["AIAA 2022"],"societies":[],"indexes":[],"emails":["aiaa@cndc2022.org","aiaaconference@yahoo.com"]}