{"name":"2022 Int'l Conference on Information Security and Network Security","series":"","short":"ISNS 2022","website":"http://www.confjuly.org/conference/ISNS2022","content":"2022 Int'l Conference on Information Security and Network Security (ISNS 2022) Conference Date: July 15-17, 2022 Conference Venue: Chengdu, China Website: http://www.confjuly.org/conference/ISNS2022 Online Registration System: https://www.confjuly.org/RegistrationSubmission/default.aspx?ConferenceID=1494 Email: intelconf@163.com 2022 Int'l Conference on Information Security and Network Security (ISNS 2022) will be held during July 15-17, 2022 in Chengdu, China. The conference will cover issues on Access Control, Anti-Virus and Anti-Worms, Authentication and Authorization, Active Defense Systems, Adaptive Defense Systems, Analysis, Benchmark of Security Systems, Biometric Security, Complex Systems Security, etc. It dedicates to creating a stage for exchanging the latest research results and sharing the advanced research methods in related fields. If you wish to serve the conference as an invited speaker, please send email to us with your CV. We'll contact with you asap. Publication and Presentation Publication: Open Access Journalï¼Œplease contact us for detailed information Index: CNKI and Google Scholar Note: If you want to present your research results but do NOT wish to publish a paper, you may simply submit an Abstract to our Registration System. Contact Us Email: intelconf@163.com (workshop\\_editor@hotmail.com) Tel: +86 13296503784 (Monday to Friday) QQ: 1349406763 WeChat: 3025797047 Official Account: Academic Communications Attendance Methods 1.Submit full paper (Regular Attendance+Paper Publication+Presentation) You are welcome to submit full paper, all the accepted papers will be published by Open access journal. 2\\. Submit abstract (Regular Attendance+Abstract+Presentation) 3\\. Regular Attendance (No Submission Required) Conference Topics Access Control Anti-Virus and Anti-Worms Authentication and Authorization Active Defense Systems Adaptive Defense Systems Analysis, Benchmark of Security Systems Biometric Security Complex Systems Security Cryptography Data and System Integrity Database Security Distributed Systems Security Data Protection Electronic Commerce Security Fraud Control Grid Security High Performance Network Virtualization High Performance Security Systems Hardware Security Information Hiding and Watermarking Information Privacy Information Security Engineering Intellectual Property Protection Intrusion Detection Internet and Network Forensics Intrusion Detection and Prevention Key Management and Key Recovery Language-based Security Large-scale Attacks and Defense Network Security Risk Evaluation and Security Certification Security and Privacy for Social Computing Security Evaluation Security for Mobile Computing Security Models Security Protocols Signature and Key Agreement Protocol Software Security System Security Security in Cloud and Grid Systems Security in E-Commerce Security in Pervasive/Ubiquitous Computing Security and Privacy in Smart Grid Security and Privacy in Wireless Networks Secure Mobile Agents and Mobile Code Security Policy Security Protocols Security Simulation and Tools Security Theory and Tools Standards and Assurance Methods Trusted Computing and Trustworthy Computing Technology","date_start":"2022-07-15","date_end":"2022-07-17","important_dates":{"abstract":"","full":"2022-06-15","notification":"","final":""},"topics":["Engineering & Technology","Computer/Informatics","Information Security"],"location":{"virtual":"","full":["Chengdu","China"],"name":"","street":"","city":"Chengdu","state":"","ZIP":"","country":"China"},"organizers":["Academic Communications"],"societies":[],"indexes":[],"emails":["intelconf@163.com","_editor@hotmail.com"]}