{"name":"4th International Conference on Machine Learning & Applications","series":"","short":"CMLA 2022","website":"https://www.cseit2022.org/cmla/index","content":"4th International Conference on Machine Learning & Applications (CMLA 2022) June 25 \\~ 26, 2022, Copenhagen, Denmark https://www.cseit2022.org/cmla/index Scope & Topics 4th International Conference on Machine Learning & Applications (CMLA 2022) will provide an excellent international forum for sharing knowledge and results in theory, methodology and applications of on Machine Learning & Applications. The aim of the conference is to provide a platform to the researchers and practitioners from both academia as well as industry to meet and share cutting-edge development in the field. Authors are solicited to contribute to the conference by submitting articles that illustrate research results, projects, surveying works and industrial experiences that describe significant advances in the following areas, but are not limited to. Topics of interest include, but are not limited to, the following • Machine Learning Algorithms • Learning in knowledge-intensive systems • Learning Methods and analysis • Supervised Machine Learning • Unsupervised Machine Learning • Deep Learning • Neural Networks • Reinforcement Learning • Predictive Learning • Learning Problems • Computer Vision • Bayesian Network • Data Mining Paper Submission Authors are invited to submit papers through the conference Submission System by June 11, 2022\\. Submissions must be original and should not have been published previously or be under consideration for publication while being evaluated for this conference. The proceedings of the conference will be published by Computer Science Conference Proceedings in Computer Science & Information Technology (CS & IT) series (Confirmed). Selected papers from CMLA 2022, after further revisions, will be published in the special issues of the following journals. • Machine Learning and Applications: An International Journal (MLAIJ) • International Journal of Artificial Intelligence & Applications (IJAIA) • Advances in Vision Computing: An International Journal (AVC) Contact Us Here's where you can reach us: cmla@cseit2022.org (or) cmlaconference@yahoo.com For more details, please visit: https://www.cseit2022.org/cmla/index Paper Submission Link: https://www.cseit2022.org/submission/index.php","date_start":"2022-06-25","date_end":"2022-06-26","important_dates":{"abstract":"","full":"2022-06-11","notification":"","final":""},"topics":["Engineering & Technology","Computer/Informatics","Machine Learning"],"location":{"virtual":"","full":["Copenhagen","Denmark","Denmark"],"name":"","street":"","city":"Copenhagen","state":"Denmark","ZIP":"","country":"Denmark"},"organizers":["CMLA 2022"],"societies":[],"indexes":[],"emails":["cmla@cseit2022.org","cmlaconference@yahoo.com"]}