{"name":"5th International Conference on Natural Language Processing and Trends","series":"","short":"NATAP 2022","website":"https://csita2022.org/natap/index","content":"5th International Conference on Natural Language Processing and Trends (NATAP 2022) June 18 \\~ 19, 2022, Sydney, Australia https://csita2022.org/natap/index Scope 5th International Conference on Natural Language Processing and Trends (NATAP 2022) will provide an excellent international forum for sharing knowledge and results in theory, methodology and applications of Natural Language Computing. The Conference looks for significant contributions to all major fields of the Natural Language Computing in theoretical and practical aspects. Topics of Interest • Phonology, Morphology • Chunking/Shallow Parsing • Parsing/Grammatical Formalisms • Semantic Processing • Lexical Semantics • Ontology • Linguistic Resources • Statistical and Knowledge based Methods • POS Tagging • Paraphrasing/Entailment/Generation • Discourse • Machine Translation • Information Retrieval • Text Mining • Information Extraction • Question Answering • Dialog Systems • Spoken Language Processing • Speech Recognition and Synthesis Paper Submission Authors are invited to submit papers through the Submission System by May 21, 2022\\. Submissions must be original and should not have been published previously or be under consideration for publication while being evaluated for this conference. The proceedings of the conference will be published by Computer Science Conference Proceedings in Computer Science & Information Technology (CS&IT) series(Confirmed). Selected papers from NATAP 2022, after further revisions, will be published in the special issue of the following journals • International Journal of Computer Science & Information Technology (IJCSIT) - INSPEC, WJCI Indexed • International Journal on Natural Language Computing (IJNLC) • International Journal on Information Theory (IJIT) • International Journal on Computational Science & Applications (IJCSA) Important Dates • Submission Deadline : May 21, 2022 • Authors Notification :June 07, 2022 • Registration & Camera -Ready Paper Due: June 10, 2022 Contact us Here's where you can reach us : natapconf@gmail.com or natap@csita2022.org","date_start":"2022-06-18","date_end":"2022-06-19","important_dates":{"abstract":"","full":"2022-05-21","notification":"","final":""},"topics":["Arts & Humanities","Languages/Literature","Natural Language Processing"],"location":{"virtual":"","full":["Sydney","Australia"],"name":"","street":"","city":"Sydney","state":"","ZIP":"","country":"Australia"},"organizers":["natap"],"societies":[],"indexes":[],"emails":["natapconf@gmail.com","natap@csita2022.org"]}