{"name":"8th International Conference on Software Engineering","series":"","short":"SOFE 2022","website":"https://acsty2022.org/sofe/index","content":"8th International Conference on Software Engineering (SOFE 2022) January 22 \\~ 23, 2022, Zurich, Switzerland https://acsty2022.org/sofe/index Scope & Topics 8th International Conference on Software Engineering (SOFE 2022) will provide an excellent international forum for sharing knowledge and results in theory, methodology and applications of Software Engineering. The goal of this Conference is to bring together researchers and practitioners from academia and industry to focus on understanding Modern software engineering concepts and establishing new collaborations in these areas. Authors are solicited to contribute to the Conference by submitting articles that illustrate research results, projects, surveying works and industrial experiences that describe significant advances in the areas of software engineering & applications. Topics of interest include, but are not limited to the following: • Advanced Topics in Software Engineering • Knowledge-based Systems and Formal Methods • Languages and Formal Methods • Managing Software Projects • Multimedia and Visual Software Engineering • Quality Management • Search Engines and Information Retrieval • Software Engineering Decision Making • Software Engineering Practice • Software Maintenance and Testing • Software Process • Web Engineering • Web-based Education Systems and Learning Applications Paper Submission Authors are invited to submit papers through the conference Submission System by December 18, 2021\\. Submissions must be original and should not have been published previously or be under consideration for publication while being evaluated for this conference. The proceedings of the conference will be published by Computer Science Conference Proceedings in Computer Science & Information Technology (CS & IT) series (Confirmed). Selected papers from SOFE 2022, after further revisions, will be published in the special issues of the following journals • International Journal of Software Engineering & Applications (IJSEA) • Computer Science & Engineering: An International Journal (CSEIJ) • Advanced Computing: An International Journal (ACIJ) • Information Technology in Industry (ITII)New - ESCI Indexed Important Dates • Submission Deadline : December 18, 2021 • Authors Notification : January 10, 2022 • Registration & Camera-Ready Paper Due : January 15, 2022 Contact Us Here's where you can reach us: sofe@acsty2022.org or sofeaconf@yahoo.com Submission System https://acsty2022.org/submission/index.php","date_start":"2022-01-22","date_end":"2022-01-23","important_dates":{"abstract":"","full":"2021-12-18","notification":"","final":""},"topics":["Engineering & Technology","Computer/Informatics","Quality Management"],"location":{"virtual":"","full":["Zurich","Switzerland","Switzerland"],"name":"","street":"","city":"Zurich","state":"Switzerland","ZIP":"","country":"Switzerland"},"organizers":[""],"societies":[],"indexes":[],"emails":["sofe@acsty2022.org","sofeaconf@yahoo.com"]}