{"name":"The 7th Int'l Conference on Remote Sensing Technologies and Applications","series":"","short":"ICRSTA 2022","website":"http://www.confjuly.org/conference/ICRSTA2022","content":"The 7th Int'l Conference on Remote Sensing Technologies and Applications (ICRSTA 2022) Conference Date: July 15-17, 2022 Conference Venue: Chengdu, China Website: http://www.confjuly.org/conference/ICRSTA2022 Online Registration System: https://www.confjuly.org/RegistrationSubmission/default.aspx?ConferenceID=1493 Email: intelconf@163.com The 7th Int'l Conference on Remote Sensing Technologies and Applications (ICRSTA 2022) will be held during July 15-17, 2022 in Chengdu, China. The conference will cover issues on Automated feature extraction, Classification and Data Mining Techniques, GIS / Earth Monitoring and Mapping, Global change studies, Global Positioning and Navigation Systems, Hazard monitoring, Image Processing Techniques , etc. It dedicates to creating a stage for exchanging the latest research results and sharing the advanced research methods in related fields. If you wish to serve the conference as an invited speaker, please send email to us with your CV. We'll contact with you asap. Publication and Presentation Publication: Open Access Journal，please contact us for detailed information Index: CNKI and Google Scholar Note: If you want to present your research results but do NOT wish to publish a paper, you may simply submit an Abstract to our Registration System. Contact Us Email: intelconf@163.com (workshop\\_editor@hotmail.com) Tel: +86 13296503784 (Monday to Friday) QQ: 1349406763 WeChat: 3025797047 Official Account: Academic Communications Attendance Methods 1.Submit full paper (Regular Attendance+Paper Publication+Presentation) You are welcome to submit full paper, all the accepted papers will be published by Open access journal. 2\\. Submit abstract (Regular Attendance+Abstract+Presentation) 3\\. Regular Attendance (No Submission Required) Conference Topics 3D infrastructure modeling 3D scene reconstruction Applications in Agriculture and Forestry Applications in Archaeology Applications in Biodiversity Conservation and Management Applications in Coastal and Marine Management Applications in Earth’s Climate Change Applications in Health Management Applications in Natural Disasters/Hazards Applications in Natural Resources and Environmental Management Applications in Traffic and Transportation Applications in Urban Planning and Management Applications in Water Resource Management Automated feature extraction Classification and Data Mining Techniques Coastal zone change detection Cultural heritage documentation Earthquakes Education and Remote Sensing Floods Forest Fires GIS / Earth Monitoring and Mapping Global change studies Global Positioning and Navigation Systems Hazard monitoring Image Processing Techniques Innovative Algorithms Land Degradation (soil erosion, desertification) Landslides/mudflows Man-made and other relevant aspects Mapping / Photogrammetry Mapping with SAR and LiDAR Marine waters monitoring Marked point process extractors Microwave Remote Sensing Multi-scale segmentation Novel Applications Object extraction Oil spill detection and tracking Optical Remote Sensing Photogrammetric computer vision Point cloud processing Random forest classifiers Range image processing Renewable energy mapping Sea pollution/Oil-spill detection Sensor Systems and Platforms Sparse and redundant representation Spatial Technologies and Landscape Spatio-temporal data fusion Storm Damage Support Vector Machine classifiers Traffic surveillance and monitoring Transportation infrastructure inventory Other Related Topics","date_start":"2022-07-15","date_end":"2022-07-17","important_dates":{"abstract":"","full":"2022-06-15","notification":"","final":""},"topics":["Engineering & Technology","Computer/Informatics"],"location":{"virtual":"","full":["Chengdu","China"],"name":"","street":"","city":"Chengdu","state":"","ZIP":"","country":"China"},"organizers":["Academic Communications"],"societies":[],"indexes":[],"emails":["intelconf@163.com","_editor@hotmail.com"]}