{"name":"3rd International Conference on NLP & Information Retrieval","series":"","short":"NLPI 2022","website":"https://www.necom2022.org/nlpi/index","content":"3rd International Conference on NLP & Information Retrieval (NLPI 2022) April 23\\~24, 2022, Copenhagen, Denmark https://www.necom2022.org/nlpi/index Scope & Topics 3rd International Conference on NLP & Information Retrieval (NLPI 2022) will provide an excellent international forum for sharing knowledge and results in theory, methodology and applications of Natural Language Computing and Information Retrieval. Authors are solicited to contribute to the conference by submitting articles that illustrate research results, projects, surveying works and industrial experiences that describe significant advances in the following areas, but are not limited to. Topics of interest include, but are not limited to, the following: • Chunking / Shallow Parsing • Computational Linguistics & NLP • Decentralized knowledge representation, search and IR • Dialog Systems • Discourse • Event and anomaly detection - Sentiment analysis • Graph, deep-learning-based methods of NLP and IR • Information Extraction, Retrieval • Information Retrieval and AI • Interactive, dynamic as well as contextual and personalised IR • IR result evaluation and relevance feedback • Lexical Semantics • Linguistic Resources • Machine Translation • Ontology • Opinion, personality and emotion detection in social media • Paraphrasing / Entailment / Generation • Parsing / Grammatical Formalisms • Phonology, Morphology • POS Tagging • Question Answering • Semantic Processing & NLP • Social and multimedia IR • Speech Recognition and Synthesis • Spoken Language Processing • Statistical and Knowledge based Methods • Text Mining • Topic recognition, tracking and subject indexing • Visualization of NLP and IR results Paper Submission Authors are invited to submit papers through the conference Submission System by March 12, 2022\\. Submissions must be original and should not have been published previously or be under consideration for publication while being evaluated for this conference. The proceedings of the conference will be published by Computer Science Conference Proceedings in Computer Science & Information Technology (CS & IT) series (Confirmed). Selected papers from NLPI 2022, after further revisions, will be published in the special issue of the following journal. • International Journal on Natural Language Computing (IJNLC) • International Journal of Web & Semantic Technology (IJWesT) Important Dates • Submission Deadline : March 12, 2022 • Authors Notification : March 31, 2022 • Registration & Camera-Ready Paper Due : April 05, 2022 Contact Us Here’s where you can reach us : nlpi@necom2022.org (or) nlpiconf@yahoo.com","date_start":"2022-04-23","date_end":"2022-04-24","important_dates":{"abstract":"","full":"2022-03-12","notification":"","final":""},"topics":["Engineering & Technology","Computer/Informatics","mining"],"location":{"virtual":"","full":["Copenhagen","Denmark","Denmark"],"name":"","street":"","city":"Copenhagen","state":"Denmark","ZIP":"","country":"Denmark"},"organizers":["NLPI 2022"],"societies":[],"indexes":[],"emails":["nlpi@necom2022.org","nlpiconf@yahoo.com"]}