{"name":"10th International Conference on Software Engineering and Applications","series":"","short":"SEAPP 2021","website":"https://cst2021.org/seapp/index","content":"10th International Conference on Software Engineering and Applications (SEAPP 2021) December 23 \\~ 24, 2021, Sydney, Australia https://cst2021.org/seapp/index Scope & Topics 10th International Conference on Software Engineering and Applications (SEAPP 2021) will provide an excellent international forum for sharing knowledge and results in theory, methodology and applications of Software Engineering and Applications. The goal of this Conference is to bring together researchers and practitioners from academia and industry to focus on understanding Modern software engineering concepts and establishing new collaborations in these areas. Authors are solicited to contribute to the Conference by submitting articles that illustrate research results, projects, surveying works and industrial experiences that describe significant advances in the areas of software engineering & applications. Topics of interest include, but are not limited to, the following • The Software Process • Software Engineering Practice • Web Engineering • Quality Management • Managing Software Projects • Advanced Topics in Software Engineering • Multimedia and Visual Software Engineering • Software Maintenance and Testing • Languages and Formal Methods • Web-based Education Systems and Learning Applications • Software Engineering Decision Making • Knowledge-based Systems and Formal Methods Paper Submission Authors are invited to submit papers through the conference Submission System by December 04, 2021(Final Call). Submissions must be original and should not have been published previously or be under consideration for publication while being evaluated for this conference. The proceedings of the conference will be published by Computer Science Conference Proceedings in Computer Science & Information Technology (CS & IT) series (Confirmed). Selected papers from SEAPP 2021, after further revisions, will be published in the special issue of the following journal. • International Journal of Software Engineering & Applications (IJSEA) - ERA Indexed • Computer Science & Engineering: An International Journal (CSEIJ) • Advanced Computing: An International Journal (ACIJ) • International Journal of Information Sciences and Techniques (IJIST) • International Journal of Computer Science, Engineering and Information Technology (IJCSEIT) • International Journal in Foundations of Computer Science & Technology (IJFCST) • International Journal of Information Technology, Control and Automation (IJITCA) Important Dates Submission Deadline : December 04, 2021(Final Call) Authors Notification : December 15, 2021 Registration & Camera-Ready Paper Due : December 18, 2021 Contact Us Here's where you can reach us: seapp@cst2021.org or jseconf@yahoo.com Submission System https://cst2021.org/submission/index.php","date_start":"2021-12-23","date_end":"2021-12-24","important_dates":{"abstract":"","full":"2021-12-04","notification":"","final":""},"topics":["Engineering & Technology","Computer/Informatics","Software Engineering"],"location":{"virtual":"","full":["Sydney","Australia"],"name":"","street":"","city":"Sydney","state":"","ZIP":"","country":"Australia"},"organizers":[""],"societies":[],"indexes":[],"emails":["seapp@cst2021.org","jseconf@yahoo.com"]}