{"name":"6th International Conference on Bioscience & Engineering","series":"","short":"BIOENG 2022","website":"https://csita2022.org/bioeng/index","content":"6th International Conference on Bioscience & Engineering (BIOENG 2022) June 18\\~19, 2022, Copenhagen, Denmark https://csita2022.org/bioeng/index Scope: 6th International Conference on Bioscience & Engineering (BIOENG 2022) will provide an excellent international forum for sharing knowledge and results in theory, methodology and applications impacts and challenges of Bioscience and Engineering. The conference documents practical and theoretical results which make a fundamental contribution for the development of Bioscience and Engineering. The aim of the conference is to provide a platform to the researchers and practitioners from both academia as well as industry to meet and share cutting-edge development in the field. Topics of interest:  Biochemical Engineering  Biochemistry  Bioinformatics  Health Informatics  Biomedicine  Bioscience Engineering  Biotechnology  Bio-fermentation Technology  Food Science & Technology  Genetics  Geo microbiology  Microbiology  Molecular Biology of Plants  Zoo physiology Paper submission Authors are invited to submit papers through the Submission System by May 28,2022\\. Submissions must be original and should not have been published previously or be under consideration for publication while being evaluated for this conference. The proceedings of the conference will be published by as a Special Issue in the Bioscience & Engineering: An International Journal (BIOEJ). Selected papers from BIOENG 2022, after further revisions, will be published in the special issue of the following journal.  Bioscience & Engineering: An International Journal (BIOEJ)  Ecology: An International Journal (ECOJ)  International Journal of Advances in Biology (IJAB)  International Journal of Biomedical Engineering and Science (IJBES)  Agricultural Science: An International journal (AGRIJ) Important dates: • Submission Deadline(Final Call) : May 28,2022 • Notification : June 10,2022 • Final Manuscript Due : June 13,2022 • Publication Date : Determined by the Editor-in-Chief Contact us: Here's where you can reachus : bioeng@csita2022.org or bioengconf@yahoo.com","date_start":"2022-06-18","date_end":"2022-06-19","important_dates":{"abstract":"","full":"2022-05-28","notification":"","final":""},"topics":["Life Sciences","Biotechnology/ Bioinformatics","molecular biology"],"location":{"virtual":"","full":["Copenhagen","Denmark","Denmark"],"name":"","street":"","city":"Copenhagen","state":"Denmark","ZIP":"","country":"Denmark"},"organizers":["BIOENG 2022"],"societies":[],"indexes":[],"emails":["bioeng@csita2022.org","bioengconf@yahoo.com"]}