{"name":"The 3rd Int'l Conference on Light Alloys and Metal Materials","series":"","short":"LAMM 2022","website":"http://www.wsaugust.org/conference/LAMM2022","content":"The 3rd Int'l Conference on Light Alloys and Metal Materials (LAMM 2022) Conference Date: August 13-15, 2022 Conference Venue: Xiamen, China Website: http://www.wsaugust.org/conference/LAMM2022 Online Registration System: https://www.wsaugust.org/RegistrationSubmission/default.aspx?ConferenceID=1505 Email: wsaugust@126.com The 3rd Int'l Conference on Light Alloys and Metal Materials (LAMM 2022) will be held from August 13-15, 2022 in Xiamen, China. This Conference will cover issues on Light Alloys and Metal Materials. It dedicates to creating a stage for exchanging the latest research results and sharing the advanced research methods. If you wish to serve the conference as an invited speaker, please send email to us with your CV. We'll contact with you asap. Publication and Presentation Publication: Open Access Journal，please contact us for detailed information Index: CNKI and Google Scholar Note: If you want to present your research results but do NOT wish to publish a paper, you may simply submit an Abstract to our Registration System. Contact Us Email: wsaugust@126.com (Editor.RolinZhang@gmail.com) Tel: +86 18627814037 QQ: 1349406763 Wechat: 3025797047 Official Account: Academic Communications Attendance Methods 1.Submit full paper (Regular Attendance+Paper Publication+Presentation) You are welcome to submit full paper, all the accepted papers will be published by Open access journal. 2\\. Submit abstract (Regular Attendance+Abstract+Presentation) 3\\. Regular Attendance (No Submission Required) Conference Topics Adaptive material and structureAge hardening and ageing processes Alloying behavior Alloys based on the aluminium–copper system Alloys based on the aluminium–silicon system Aluminium alloys Aluminium–magnesium alloys Aluminium–zinc–magnesium alloys Amorphous alloys Cast aluminium alloys Castability and casting processes Casting of light alloys Complex metallic alloys Complex structural and functional alloys Corrosion prevention and management Electroplating and allied processes Grain refinement Heat-treatable alloys Intermetallic compounds Intermetallic materials Intermetallics Kirkendall effect Light alloys and light metals Magnesium alloys Maraging steel Mechanical alloying Mechanical behavior Melting, alloying, and casting Metallic foams Metallic glasses and high entropy alloys Metallurgy Nanophase alloys Physical vapor deposition Precious metals Quasicrystals Rapid solidification processing Rare earth metals Rare metal materials and engineering Rare metals Refractory metals Refractory metals Solidification of light alloys Titanium alloys Titanium aluminides Work hardening and annealing Wrought magnesium alloys Zirconium-containing casting alloys Zirconium-free casting alloys Structure-property-correlations","date_start":"2022-08-13","date_end":"2022-08-15","important_dates":{"abstract":"","full":"2022-07-13","notification":"","final":""},"topics":["Engineering & Technology","Material/Nanotechnology"],"location":{"virtual":"","full":["Xiamen","China"],"name":"","street":"","city":"Xiamen","state":"","ZIP":"","country":"China"},"organizers":["Academic Communications"],"societies":[],"indexes":[],"emails":["wsaugust@126.com","editor.rolinzhang@gmail.com"]}