{"name":"8th International Conference on Networks, Mobile Communication","series":"","short":"NMCO 2022","website":"https://csita2022.org/nmco/index","content":"8th International Conference on Networks, Mobile Communication (NMCO 2022) June 18 \\~ 19, 2022, Sydney, Australia https://csita2022.org/nmco/index Scope 8th International Conference on Networks, Mobile Communication (NMCO 2022) is a forum for presenting new advances and research results in the fields of Network, Mobile communications, and Telematics. The aim of the conference is to provide a platform to the researchers and practitioners from both academia as well as industry to meet and share cutting-edge development in the field. Topics of Interest • Information / Content Centric Networks (ICN) • Internet Measurement and Modeling • Internet of Things (IoT) • Machine Learning and AI in Networking • Vehicle-to-everything (V2X) and Autonomous cars • Vehicular Networks & Intelligent Transportation • 5G/6G Cellular Systems and Heterogeneous Networks • Adhoc and Sensor Networks • Big data / Cloud computing and Networks • Big Data / IoT Analytics in Networking • Blockchain and Distributed Ledger • Critical Success Factors for Mobile Communication Diffusion • Cross-Cultural Mobile Communication Issues • Efficacy of Mobile Communications • Heterogeneous Wireless Networks • Integrated Mobile Marketing Communications • Integration and Interworking of Wired and Wireless Networks • Internet and Web Applications • Location Management for Mobile Communications • Measurement & Performance Analysis • Metric Mobile Business Enterprise • Mobile and Handheld Devices in the Education • Mobile Communication Applications • Mobile Communication Security Issues and Requirements • Mobile Communications and Telematics • Mobile Computing Software Architectures • Mobile Computing • Mobile Network Management and Service Infrastructure • Mobile Network Traffic Engineering, Performance & Optimization • Mobile Networks & Wireless LAN • Network & Communications • Privacy and Security in Mobile Computing and Wireless Systems • SDN/NFV and Network Programmability • Software-Defined Networking (SDN) and Network Virtualization • Tele-Learning • Telematics • Ubiquitous Networks • VR/AR Streaming • Wireless Communications • Wireless Multimedia Systems Paper Submission Authors are invited to submit papers through the Submission System by May 14, 2022\\. Submissions must be original and should not have been published previously or be under consideration for publication while being evaluated for this conference. The proceedings of the conference will be published by Computer Science Conference Proceedings in Computer Science & Information Technology (CS&IT) series(Confirmed). Selected papers from NMCO 2022, after further revisions, will be published in the special issue of the following journals • International Journal of Computer Networks & Communications (IJCNC) - ERA, WJCI, Scopus Indexed • International Journal of Wireless & Mobile Networks (IJWMN) - WJCI, ERA Indexed • International Journal of Network Security & Its Applications (IJNSA) - WJCI, ERA Indexed • International Journal of Multimedia & Its Applications(IJMA) - WJCI, ERA Indexed • International Journal of Database Management Systems( IJDMS ) - WJCI, IS Indexed • International Journal of Web & Semantic Technology (IJWesT) - IS Indexed Important Dates • Submission Deadline : May 21, 2022 • Authors Notification : June 07, 2022 • Registration & Camera -Ready Paper Due: June 10, 2022 Contact us Here's where you can reach us : nmcoconf@yahoo.com or nmco@csita2022.org","date_start":"2022-06-18","date_end":"2022-06-19","important_dates":{"abstract":"","full":"2022-05-21","notification":"","final":""},"topics":["Engineering & Technology","Computer/Informatics"],"location":{"virtual":"","full":["Sydney","Australia","Australia"],"name":"","street":"","city":"Sydney","state":"Australia","ZIP":"","country":"Australia"},"organizers":["NMCO"],"societies":[],"indexes":[],"emails":["nmcoconf@yahoo.com","nmco@csita2022.org"]}