{"name":"2022 International Conference on Medicinal Chemistry and Drug Discovery","series":"","short":"MCDD 2022","website":"https://www.confjuly.org/conference/MCDD2022","content":"2022 International Conference on Medicinal Chemistry and Drug Discovery (MCDD 2022) Website：https://www.confjuly.org/conference/MCDD2022/ Date：July 15-17, 2022 Venue：Chengdu, China Online Registration Entrance：https://www.confjuly.org/RegistrationSubmission/default.aspx?ConferenceID=1495 2022 International Conference on Medicinal Chemistry and Drug Discovery (MCDD 2022) will be held during July 15-17, 2022 in Chengdu, China. The conference will cover issues on Medicinal Chemistry, Drug Discovery, etc. It dedicates to creating a stage for exchanging the latest research results and sharing the advanced research methods in related fields. Attendance Methods 1\\. Full Paper submission Submit full paper ( Regular Attendance + Paper Publication + Presentation ) You are invited to submit papers and participate in our academic exchange. One author will be invited to make an oral presentation and the paper will be published by peer-reviewed open access journal and submitted to CNKI and Google Scholar for indexing. 2.Abstract submission Submit abstract ( Regular Attendance + Abstract + Presentation ) You are welcome to submit abstract for oral presentation or poster presentation. 3.Regular Attendance ( No Submission Required ) You're also welcome to attend our conference (without submitting full paper or abstract) Publication and Presentation Publication: All the accepted papers will be published by a peer-reviewed open access journal that can ensure the widest dissemination of your published work Index: CNKI and Google Scholar Note: 1\\. If you want to present your research results but do NOT wish to publish a paper, you may simply submit an Abstract. 2\\. The simple Abstract submission should include the title, contents, keywords, authors names, affiliations and emails. The length is suggested to be controlled within 1 page and no more than 2 pages. 3\\. You will receive the review results within 3-5 working days after submission. If you do not get any notification within the time limit, please contact us as soon as possible. Contact Us Email: intelconf@163.com (workshop\\_editor@hotmail.com) Tel: +86 13296503784 (Monday to Friday) QQ: 1349406763 WeChat: 3025797047 Official Account: Academic Communications","date_start":"2022-07-15","date_end":"2022-07-17","important_dates":{"abstract":"","full":"2022-07-05","notification":"","final":""},"topics":["Medicine & Health","Pharmaceutical / Medicinal"],"location":{"virtual":"","full":["Chengdu","China"],"name":"","street":"","city":"Chengdu","state":"","ZIP":"","country":"China"},"organizers":["Academic Communications"],"societies":[],"indexes":[],"emails":["intelconf@163.com","_editor@hotmail.com"]}