{"name":"3rd International Conference on Machine Learning & Trends","series":"","short":"MLT 2022","website":"https://icaita2022.org/mlt/index","content":"3rd International Conference on Machine Learning & Trends (MLT 2022) March 19 \\~ 20, 2022, Vienna, Austria https://icaita2022.org/mlt/index Scope 3rd International Conference on Machine Learning & Trends (MLT 2022) will provide an excellent international forum for sharing knowledge and results in theory, methodology and applications of on Machine Learning & its Trends. The aim of the conference is to provide a platform to the researchers and practitioners from both academia as well as industry to meet and share cutting-edge development in the field. Authors are solicited to contribute to the conference by submitting articles that illustrate research results, projects, surveying works and industrial experiences that describe significant advances in the areas of Machine Learning & its Trends. Topics of interest • Applications • Learning in knowledge-intensive systems • Learning Methods and analysis • Learning Problems • Trends Paper Submission Authors are invited to submit papers through the conference Submission System by February 19, 2022.Submissions must be original and should not have been published previously or be under consideration for publication while being evaluated for this conference. The proceedings of the conference will be published by Computer Science Conference Proceedings in Computer Science & Information Technology (CS & IT) series (Confirmed). Selected papers from MLT 2022, after further revisions, will be published in the special issues of the following journals • Machine Learning and Applications: An International Journal (MLAIJ) • International Journal of Artificial Intelligence & Applications (IJAIA) Important Dates • Submission Deadline: February 19, 2022 • Authors Notification: March 05, 2022 • Registration & camera – Ready Paper Due: March 08, 2022 Contact Us Here's where you can reach us: mlt@icaita2022.org (or) mltconf@yahoo.com For other details: https://icaita2022.org/mlt/index Paper Submission Link: https://icaita2022.org/submission/index.php","date_start":"2022-03-19","date_end":"2022-03-20","important_dates":{"abstract":"","full":"2022-02-19","notification":"","final":""},"topics":["Engineering & Technology","Other","Machine Learning"],"location":{"virtual":"","full":["Vienna","Austria","Austria"],"name":"","street":"","city":"Vienna","state":"Austria","ZIP":"","country":"Austria"},"organizers":["MLT"],"societies":[],"indexes":[],"emails":["mlt@icaita2022.org","mltconf@yahoo.com"]}