{"name":"4th International Conference on Artificial Intelligence and Machine Learning","series":"","short":"CAIML 2023","website":"https://itcse2023.org/caiml/index","content":"4th International Conference on Artificial Intelligence and Machine Learning (CAIML 2023) July 29 \\~ 30, 2023, London, United Kingdom https://itcse2023.org/caiml/index Scope & Topics 4th International Conference on Artificial Intelligence and Machine Learning (CAIML 2023) will provide an excellent international forum for sharing knowledge and results in theory, methodology and applications of Artificial Intelligence and Machine Learning. The Conference looks for significant contributions to all major fields of the Artificial Intelligence, Machine Learning in theoretical and practical aspects. The aim of the Conference is to provide a platform to the researchers and practitioners from both academia as well as industry to meet and share cutting-edge development in the field. Authors are solicited to contribute to the conference by submitting articles that illustrate research results, projects, surveying works and industrial experiences that describe significant advances in the following areas, but are not limited to: Topics of interest include, but are not limited to, the following • Artificial Intelligence • AI Algorithms • Artificial Intelligence Tools and Application • Automatic Control • Bioinformatics • CAD Design and Testing • Computational Theories of Learning • Computer Vision and Speech Understanding • Data Mining and Machine Learning Tools • Fuzzy Logic • Heuristic and AI Planning Strategies and Tools • Hybrid Intelligent Systems • Information Retrieval • Intelligent System Architecture • Knowledge Representation • Knowledge-based Systems • Mechatronics • Multimedia & Cognitive Informatics • Natural Language Processing • Neural Networks • Parallel Processing • Pattern Recognition • Pervasive Computing and Ambient Intelligence • Programming Languages • Reasoning and Evolution • Recent Trends and Developments • Robotics • Semantic Web Techniques and Technologies • Soft computing theory and Applications • Software & Hardware Architectures • Web Intelligence Applications & Search • Machine Learning • Applications • Learning in knowledge-intensive systems • Learning Methods and analysis • Learning Problems Paper Submission Authors are invited to submit papers through the conference Submission System by February 18, 2023\\. Submissions must be original and should not have been published previously or be under consideration for publication while being evaluated for this conference. The proceedings of the conference will be published by Computer Science Conference Proceedings in Computer Science & Information Technology (CS & IT) series (Confirmed). Selected papers from CAIML 2023, after further revisions, will be published in the special issue of the following journals. • Machine Learning and Applications: An International Journal (MLAIJ) • International Journal of Artificial Intelligence & Applications (IJAIA) • International Journal on Soft Computing (IJSC) • International Journal on Soft Computing, Artificial Intelligence and Applications (IJSCAI) • Advances in Vision Computing: An International Journal (AVC) • International Journal of Network Security & Its Applications (IJNSA) - ERA, WJCI Indexed Contact Us Here's where you can reach us: caiml@itcse2023.org (or) caimlconf@yahoo.com For more details, please visit: https://itcse2023.org/caiml/index Paper Submission Link: https://itcse2023.org/submission/index.php","date_start":"2023-07-29","date_end":"2023-07-30","important_dates":{"abstract":"","full":"2023-02-18","notification":"","final":""},"topics":["Engineering & Technology","Computer/Informatics","Artificial intelligence"],"location":{"virtual":"","full":["London","United Kingdom","United Kingdom"],"name":"","street":"","city":"London","state":"United Kingdom","ZIP":"","country":"United Kingdom"},"organizers":["CAIML 2023"],"societies":[],"indexes":[],"emails":["caiml@itcse2023.org","caimlconf@yahoo.com"]}