{"name":"8th International Conference on Artificial Intelligence and Soft Computing","series":"","short":"AIS 2022","website":"https://csit2022.org/ais/index","content":"8th International Conference on Artificial Intelligence and Soft Computing (AIS 2022) August 20 \\~ 21, 2022, Chennai, India https://csit2022.org/ais/index Scope & Topics 8th International Conference on Artificial Intelligence and Soft Computing (AIS 2022) will provide an excellent international forum for sharing knowledge and results in theory, methodology, and applications of Artificial Intelligence, Soft Computing. The Conference looks for significant contributions to all major fields of the Artificial Intelligence, Soft Computing in theoretical and practical aspects. The aim of the Conference is to provide a platform to the researchers and practitioners from both academia as well as industry to meet and share cutting-edge development in the field. Authors are solicited to contribute to the conference by submitting articles that illustrate research results, projects, surveying works and industrial experiences that describe significant advances in the following areas, but are not limited to. Topics of interest include, but are not limited to, the following: • AI Algorithms • Information Retrieval • Intelligent System Architectures • Knowledge Representation • Knowledge-based Systems • Mechatronics • Multimedia & Cognitive Informatics • Neural Networks • Parallel Processing • Pattern Recognition • Pervasive Computing and Ambient Intelligence • Programming Languages Artificial Intelligence • Soft Computing and Applications • Artificial Intelligence Tools & Applications • Automatic Control • Bioinformatics • Natural Language Processing • CAD Design & Testing • Computer Vision and Speech Understanding • Data Mining and Machine Learning Tools • Fuzzy Logic • Heuristic and AI Planning Strategies and Tools • Computational Theories of Learning • Hybrid Intelligent Systems • Reasoning and Evolution • Recent Trends and Developments • Robotics • Neural Networks • Machine Learning • Probabilistic Reasoning • Evolutionary Computing • Hybrid Intelligent Systems • Software Agents • Morphic Computing • Image processing • E-commerce, E-medicine • Rough Sets • Symbolic Machine Learning • Wavelet • Signal or Image Processing • Vision Recognition • Biomedical Engineering • Telecommunications • Reactive Distributed AI • Nano & Micro-systems • Data Visualization • Semantic Web Techniques and Technologies • Soft Computing Theory and Applications • Software & Hardware Architectures • Web Intelligence Applications & Search Paper Submission Authors are invited to submit papers through the conference Submission System by July 09, 2022\\. Submissions must be original and should not have been published previously or be under consideration for publication while being evaluated for this conference. The proceedings of the conference will be published by Computer Science Conference Proceedings in Computer Science & Information Technology (CS & IT) series (Confirmed). Selected papers from AIS 2022, after further revisions, will be published in the special issue of the following journals. • International Journal of Soft Computing (IJSC) • Information Technology in Industry (ITII) • International Journal of Artificial Intelligence & Applications (IJAIA) Important Dates • Submission Deadline : July 09, 2022 • Authors Notification : August 02, 2022 • Final Manuscript Due: August 09, 2022 Contact Us Here's where you can reach us : ais@csit2022.org or aisconf@yahoo.com For other details please visit : https://csit2022.org/ais/index Submission Link : https://csit2022.org/submission/index.php","date_start":"2022-08-20","date_end":"2022-08-21","important_dates":{"abstract":"","full":"2022-07-09","notification":"","final":""},"topics":["Engineering & Technology","Computer/Informatics","Artificial intelligence"],"location":{"virtual":"","full":["Chennai","India"],"name":"","street":"","city":"Chennai","state":"","ZIP":"","country":"India"},"organizers":["AIS 2022"],"societies":[],"indexes":[],"emails":["ais@csit2022.org","aisconf@yahoo.com"]}