{"name":"2nd International Conference on Education and Technology","series":"","short":"EDUTEC 2023","website":"https://edutec2023.org/index","content":"2nd International Conference on Education and Technology (EDUTEC 2023) January 21-22, 2023, Virtual Conference https://edutec2023.org/index Scope & Topics 2nd International Conference on Education and Technology (EDUTEC 2023) will act as a major forum for the presentation of innovative ideas, approaches, developments, and research projects in the areas of Education. It also aims to provide a platform for exchanging ideas in new emerging trends that needs more focus and exposure and will attempt to publish proposals that strengthen our goals. Topics of interest include, but are not limited to, the following • Collaborative, Interactive Learning • Games and Simulations in Education • Global Issues in Education and Research • Innovative Educational Practices • Institutional management and performance • Integrating Technology in Curriculum: Challenges & Strategies • Learning / Teaching Methodologies and Assessment • Learning Science & Analysis • Mobile / Ubiquitous Computing in Education • Multimedia in Education • Pandemic-based Educational Research • Pedagogy Enhancement with E-Learning • Professional Development for Teachers in ICT • Research in Progress • Social theory • Special education • Student Selection Criteria in Interdisciplinary Studies • Teacher Evaluation • Technology Support for Pervasive Learning • Tools for 21st Century Learning • Virtual and Remote Laboratories • Vocational, Higher education • Web 2.0, Social Networking, Blogs and Wikis • Web-based Tools for Education Paper Submission Authors are invited to submit papers through the conference Submission System by January 07, 2023(Final call). Submissions must be original and should not have been published previously or be under consideration for publication while being evaluated for this conference. The proceedings of the conference will be published by International Journal on Cybernetics & Informatics (IJCI) (Confirmed). Selected papers from EDUTEC 2023, after further revisions, will be published in the special issue of the following journal. • International Journal of Education (IJE) • International Journal on Integrating Technology in Education (IJITE) Important Dates • Submission Deadline : January 07, 2023(Final call) • Authors Notification : January 12, 2023 • Registration & Camera-Ready Paper Due : January 15, 2023 Contact Us Here's where you can reach us : edutec@edutec2023.org or edutecconf@yahoo.com","date_start":"2023-01-21","date_end":"2023-01-22","important_dates":{"abstract":"","full":"2023-01-07","notification":"","final":""},"topics":["Education / Legal / Other","Education","Interactive Learning"],"location":{"virtual":"","full":["Virtual Conference","United States"],"name":"","street":"","city":"Virtual Conference","state":"","ZIP":"","country":"United States"},"organizers":[""],"societies":[],"indexes":[],"emails":["edutec@edutec2023.org","edutecconf@yahoo.com"]}