{"name":"11th International Conference on Soft Computing, Artificial Intelligence and Applications","series":"","short":"SCAI 2022","website":"https://iccsea2022.org/scai/index","content":"11th International Conference on Soft Computing, Artificial Intelligence and Applications (SCAI 2022) November 26 \\~ 27, 2022, London, United Kingdom https://iccsea2022.org/scai/index Scope & Topics 11th International Conference on Soft Computing, Artificial Intelligence and Applications (SCAI 2022) will provide an excellent international forum for sharing knowledge and results in theory, methodology and applications of artificial intelligence, soft computing. The conference looks for significant contributions to all major fields of the artificial intelligence, soft computing in theoretical and practical aspects. The aim of the conference is to provide a platform to the researchers and practitioners from both academia as well as industry to meet and share cutting-edge development in the field. Authors are solicited to contribute to the conference by submitting articles that illustrate research results, projects, surveying works and industrial experiences that describe significant advances in the following areas, but are not limited to. Topics of interest include, but are not limited to, the following • Soft Computing • Fuzzy Systems • Neural Networks • Machine Learning • Probabilistic Reasoning • Evolutionary Computing • Pattern Recognition • Hybrid Intelligent Systems • Software Agents • Morphic Computing • Image Processing • E-commerce, e-medicine • Rough Sets • Symbolic Machine Learning • Wavelet • Signal or Image Processing • Vision Recognition • Biomedical Engineering • Telecommunications • Reactive Distributed AI • Nano & Micro-systems • Data Visualization • Artificial Intelligence • AI Algorithms • Artificial Intelligence Tools & Applications • Automatic Control • Bioinformatics • Natural Language Processing • CAD Design & Testing • Computer Vision and Speech Understanding • Data Mining and Machine Learning Tools • Fuzzy Logic • Heuristic and AI Planning Strategies and Tools • Computational Theories of Learning • Hybrid Intelligent Systems • Information Retrieval • Intelligent System Architectures • Knowledge Representation • Knowledge-based Systems • Mechatronics • Multimedia & Cognitive Informatics • Neural Networks • Parallel Processing • Pervasive Computing and Ambient Intelligence • Programming Languages • Reasoning and Evolution • Recent Trends and Developments • Robotics • Semantic Web Techniques and Technologies • Soft Computing Theory and Applications • Software & Hardware Architectures • Web Intelligence Applications & Search Paper Submission Authors are invited to submit papers through the conference Submission System by November 05, 2022\\. Submissions must be original and should not have been published previously or be under consideration for publication while being evaluated for this conference. The proceedings of the conference will be published by Computer Science Conference Proceedings in Computer Science & Information Technology (CS & IT) series (Confirmed). Selected papers from SCAI 2022, after further revisions, will be published in the special issues of the following journals • International Journal of Artificial Intelligence & Applications (IJAIA) • International Journal of Fuzzy Logic Systems (IJFLS) • International Journal on Soft Computing, Artificial Intelligence and Applications (IJSCAI) • International Journal on Soft Computing (IJSC) • Information Technology in Industry (ITII) Important Dates • Submission Deadline : November 05, 2022 • Authors Notification : November 15, 2022 • Registration & Camera-Ready Paper Due : November 22, 2022 Contact Us Here's where you can reach us :scai@iccsea2022.orgor scaiconf34@yahoo.com","date_start":"2022-11-26","date_end":"2022-11-27","important_dates":{"abstract":"","full":"2022-11-05","notification":"","final":""},"topics":["Life Sciences","Biotechnology/ Bioinformatics","Pattern Recognition"],"location":{"virtual":"","full":["London","United Kingdom"],"name":"","street":"","city":"London","state":"","ZIP":"","country":"United Kingdom"},"organizers":[""],"societies":[],"indexes":[],"emails":["scai@iccsea2022.orgor","scaiconf34@yahoo.com"]}