{"name":"9th International Conference on Cryptography and Information Security","series":"","short":"CRIS 2023","website":"https://cosit2023.org/cris/index","content":"9th International Conference on Cryptography and Information Security (CRIS 2023) May 20 \\~ 21, 2023, Zurich, Switzerland https://cosit2023.org/cris/index Call for Papers 9th International Conference on Cryptography and Information Security (CRIS 2023) provides a forum for researchers who address this issue and to present their work in a peer-reviewed forum. It aims to bring together scientists, researchers and students to exchange novel ideas and results in all aspects of cryptography, coding and Information security. Authors are solicited to contribute to the conference by submitting articles that illustrate research results, projects, surveying works and industrial experiences that describe significant advances in the following areas, but are not limited to: Topics of interest include, but are not limited to, the following • Cryptographic Protocols • Cryptography and Coding • Untraceability • Privacy and Authentication • Key Management • Trust Management • Quantum Cryptography • Computational Intelligence in Security • Artificial Immune Systems • Biological and Evolutionary Computation • Intelligent Agents and Systems • Reinforcement and Unsupervised Learning • Autonomy-Oriented Computing • Co-evolutionary Algorithms • Fuzzy Systems • Biometric Security • Trust Models and Metrics • Regulation and Trust Mechanisms • Data Integrity • Models for Authentication, Trust and Authorization • Wireless Network Security • Information Hiding • E- Commercel • Data and System Integrity • Access Control and Intrusion Detection • Intrusion Detection and Vulnerability Assessment • Authentication and Non-repudiation • Identification and Authentication • Insider Threats and Countermeasures • Intrusion Detection & Prevention • Secure Cloud Computing • Security Information Systems Architecture and Design and • Security Patterns • Security Management • Security Requirements (Threats, Vulnerabilities, Risk, Formal Methods, etc.) • Sensor and Mobile Ad Hoc Network Security • Service, Systems Design and QoS Network Security • Software Security • Security and Privacy in Mobile Systems • Security and Privacy in Pervasive/Ubiquitous Computing • Security and Privacy in Web Services • Security and Privacy Policies • Security Area Control • Security Deployment • Security Engineering • Security for Grid Computing • Security in Distributed Systems Paper Submission Authors are invited to submit papers through the conference Submission System by January 21, 2023\\. Submissions must be original and should not have been published previously or be under consideration for publication while being evaluated for this conference. The proceedings of the conference will be published by Computer Science Conference Proceedings in Computer Science & Information Technology (CS & IT) series (Confirmed). Selected papers from CRIS 2023, after further revisions, will be published in the special issue of the following journal. • International Journal on Cryptography and Information Security (IJCIS) • International Journal of Network Security & Its Applications (IJNSA) - ERA, WJCI Indexed • International Journal of Wireless & Mobile Networks (IJWMN) - ERA, WJCI Indexed • International Journal of Security, Privacy and Trust Management (IJSPTM) • Information Technology in Industry (ITII) Important Dates • Submission Deadline: January 21, 2023 • Authors Notification: February 18, 2023 • Registration & camera - Ready Paper Due: February 25, 2023 Contact Us Here's where you can reach us: cris@cosit2023.org (or) crissecretary@gmail.com Submission System https://cosit2023.org/submission/index.php","date_start":"2023-05-20","date_end":"2023-05-21","important_dates":{"abstract":"","full":"2023-01-21","notification":"","final":""},"topics":["Engineering & Technology","Computer/Informatics","Key Management"],"location":{"virtual":"","full":["Zurich","Switzerland"],"name":"","street":"","city":"Zurich","state":"","ZIP":"","country":"Switzerland"},"organizers":[""],"societies":[],"indexes":[],"emails":["cris@cosit2023.org","crissecretary@gmail.com"]}