{"name":"9th International Conference on Wireless and Mobile Network (WiMNET 2022)","series":"","short":"","website":"https://comit2022.org/wimnet/index","content":"9th International Conference on Wireless and Mobile Network (WiMNET 2022) October 22 \\~ 23, 2022, Sydney, Australia https://comit2022.org/wimnet/index Scope & Topics 9th International Conference on Wireless and Mobile Network (WiMNET 2022) is dedicated to address the challenges in the areas of wireless & mobile networks. The conference looks for significant contributions to the Wireless and Mobile computing in theoretical and practical aspects. The Wireless and Mobile computing domain emerges from the integration among personal computing, networks, communication technologies, cellular technology and the internet technology. Authors are solicited to contribute to the Conference by submitting articles that illustrate research results, projects, surveying works and industrial experiences that describe significant advances in the following areas, but are not limited to. Topics of interest include, but are not limited to, the following: • 5G enabled Mobile IOT Applications • 5G, 5G mobile Networks • AI, IOT, 5G Convergence • Fiber optic communication • Heterogeneous Wireless Networks • Internet Access and Broadband Technologies • Internet of Things • Measurement & Performance Analysis • Mobile Adhoc Network Routing and Sensor Networks • Mobile and Wireless Communications • Mobile Computing • Network Protocols & Wireless Networks • Next Generation Mobile Networks • Recent Trends in Wireless & Mobile Networks • Routing, Switching and Addressing Techniques & Algorithms • SDN and NFV for Wireless Mobile Networks • Spectrum Allocation and Management • Time sensitive IoT / 5G Applications • Traffic and Congestion Control, QoS, Resource Management • Ubiquitous Networks • Vehicle to Everything (V2X) Services • Wireless & Mobile Network Architectures • Wireless & Mobile Network Operations & Management • Wireless & Mobile Network Security Paper Submission Authors are invited to submit papers through the conference Submission System by October 08, 2022 (Final Call). Submissions must be original and should not have been published previously or be under consideration for publication while being evaluated for this conference. The proceedings of the conference will be published by Computer Science Conference Proceedings in Computer Science & Information Technology (CS & IT) series (Confirmed). Selected papers from WiMNET 2022, after further revisions, will be published in the special issues of the following journals. • International Journal of Computer Networks & Communications (IJCNC)- ERA Indexed, Scopus Indexed, WJCI Indexed • International Journal of Wireless & Mobile Networks (IJWMN) - ERA Indexed, WJCI Indexed • The International Journal on Cloud Computing: Services and Architecture (IJCCSA) • International Journal of Mobile Network Communications & Telematics (IJMNCT) • International Journal on AdHoc Networking Systems (IJANS) • Information Technology in Industry (ITII) Important Dates • Submission Deadline : October 08, 2022 (Final Call) • Authors Notification : Oct 15, 2022 • Final Manuscript Due : Oct 18, 2022 Contact Us Here's where you can reach us : wimnet@comit2022.org or wimnet.conf@yahoo.com For other details please visit : https://comit2022.org/wimnet/index Submission Link : https://comit2022.org/submission/index.php","date_start":"2022-10-22","date_end":"2022-10-23","important_dates":{"abstract":"","full":"2022-10-08","notification":"","final":""},"topics":["Arts & Humanities","Other","Networking"],"location":{"virtual":"","full":["Sydney","Australia"],"name":"","street":"","city":"Sydney","state":"","ZIP":"","country":"Australia"},"organizers":[""],"societies":[],"indexes":[],"emails":["wimnet@comit2022.org","wimnet.conf@yahoo.com"]}