{"name":"3rd International Conference on NLP & Artificial Intelligence Techniques","series":"","short":"NLAI 2022","website":"https://iccsea2022.org/nlai/index","content":"3rd International Conference on NLP & Artificial Intelligence Techniques (NLAI 2022) November 26 \\~ 27, 2022, London, United Kingdom https://iccsea2022.org/nlai/index Scope& Topics 3rd International Conference on NLP & Artificial Intelligence Techniques (NLAI 2022) will provide an excellent international forum for sharing knowledge and results in theory, methodology and applications of NLP & Artificial Intelligence Techniques. The Conference looks for significant contributions to all major fields of NLP and Artificial Intelligence in theoretical and practical aspects. The aim of the Conference is to provide a platform to the researchers and practitioners from both academia as well as industry to meet and share cutting-edge development in the field. Authors are solicited to contribute to the Conference by submitting articles that illustrate research results, projects, surveying works and industrial experiences that describe significant advances in the following areas, but are not limited to. Topics of interest include, but are not limited to, the following NLP • Phonology, Morphology • Chunking/Shallow Parsing • Parsing/Grammatical Formalisms • Semantic Processing • Lexical Semantics • Ontology • Linguistic Resources • Statistical and Knowledge based Methods • POS Tagging • Discourse • Paraphrasing/Entailment/Generation • Machine Translation • Information Retrieval • Text Mining • Information Extraction • Question Answering • Dialog Systems • Spoken Language Processing • Speech Recognition and Synthesis • Computational Linguistics& NLP • Information Retrieval and AI • Semantic & NLP • NLP & AI Artificial Intelligence • Adaptive systems • AI Algorithms • Artificial Intelligence and Cloud Computing • Artificial Intelligence and Internet of Things • Artificial Intelligence Cyber Security • Artificial Intelligence tools & Applications • Automated Machine Learning • Bioinformatics, Biometrics • Business Intelligence • Data and Web mining • Deep Learning • Ensemble Method • Evolutionary Computation • Financial Engineering • Fuzzy set theory, Fuzzy control and System • Geo-informatics • Hybrid and Nonlinear system • Inductive Learning • Information Fusion • Information Retrieval • Intelligent Agent • Intelligent and Knowledge based system • Intelligent Control • Logistics • Machine Learning Tools • Media computing • Neural network and support vector machine • Pattern Recognition • Rough and fuzzy rough set • Visual information processing Paper Submission Authors are invited to submit papers through the conference Submission System by September 17, 2022\\. Submissions must be original and should not have been published previously or be under consideration for publication while being evaluated for this conference. The proceedings of the conference will be published by Computer Science Conference Proceedings in Computer Science & Information Technology (CS & IT) series (Confirmed). Selected papers from NLAI 2022, after further revisions, will be published in the special issues of the following journals. • International Journal of Artificial Intelligence & Applications (IJAIA) • International Journal of Fuzzy Logic Systems (IJFLS) • International Journal on Soft Computing, Artificial Intelligence and Applications (IJSCAI) • International Journal of Soft Computing (IJSC) • International Journal on Natural Language Computing (IJNLC) • International Journal of Web & Semantic Technology (IJWesT) Important Dates Second Batch : (Submissions after September 03, 2022) • Submission Deadline : September 17, 2022 • Authors Notification : October 25, 2022 • Registration & Camera-Ready Paper Due : November 03, 2022 Contact Us Here's where you can reach us : nlai@iccsea2022.org or nlai\\_conference@yahoo.com","date_start":"2022-11-26","date_end":"2022-11-27","important_dates":{"abstract":"","full":"2022-09-17","notification":"","final":""},"topics":["Engineering & Technology","Computer/Informatics","Cloud Computing"],"location":{"virtual":"","full":["london","United Kingdom"],"name":"","street":"","city":"london","state":"","ZIP":"","country":"United Kingdom"},"organizers":["NLAI 2022"],"societies":[],"indexes":[],"emails":["nlai@iccsea2022.org","_conference@yahoo.com"]}