{"name":"5th International Conference on Bioscience & Engineering","series":"","short":"BIEN 2022","website":"https://csit2022.org/bien/index","content":"5th International Conference on Bioscience & Engineering (BIEN 2022) August 20 \\~ 21, Chennai, India https://csit2022.org/bien/index SCOPE 5th International Conference on Bioscience & Engineering (BIEN 2022) will provide an excellent International forum for sharing knowledge and results in theory, methodology and applications impacts and challenges of Bioscience and Engineering. The goal of this Conference is to bring together researchers and practitioners from academia and industry to focus on Bioscience and Engineering advancements and establishing new collaborations in these areas. Original research papers, state-of-the-art reviews are invited for publication in all areas of Bioscience and Engineering. TOPICS OF INTEREST • Animal Biotechnology • Applied Microbiology • Bio-Chemical Engineering • Bio-Chemistry • Bio-Fermentation Technology • Bio-Informatics • Biological systems and models • Bio-Medicine • Bio-Science Engineering • Bio-Technology • Cell Biology • Computer Assisted Intervention Systems • Drug designing • Engineering Models in Bio -Medicine • Food Science & Technology • Genetics • Genetics and Molecular Biology • Geomicrobiology • Health Informatics • Microbiology • Molecular Biology of Plants • Nano mechanisms for molecular systems • Nano biotechnology • Plant System Physiology • Structural Biology • Zoophysiology Paper Submission Authors are invited to submit papers through the conference Submission System by August 06, 2022(final call). Submissions must be original and should not have been published previously or be under consideration for publication while being evaluated for this conference. The proceedings of the conference will be published by Bioscience & Engineering: An International Journal (BIOEJ). Selected papers from BIEN 2022, after further revisions, will be published in the special issue of the following journals • International Journal on Bioinformatics & Biosciences (IJBB) • Ecology: An International Journal (ECOJ) • International Journal of Advances in Biology (IJAB) • International Journal of Biomedical Engineering and Science (IJBES) • Life Sciences: An International Journal (LSIJ) IMPORTANT DATES • Submission Deadline : August 06, 2022(final call) • Authors Notification : August 14, 2022 • Registration & Camera-Ready Paper Due : August 17, 2022 Contact Us Here's where you can reach us : bien@csit2022.org or bienconference@yahoo.com","date_start":"2022-08-20","date_end":"2022-08-21","important_dates":{"abstract":"","full":"2022-08-06","notification":"","final":""},"topics":["Life Sciences","Biotechnology/ Bioinformatics","chemistry"],"location":{"virtual":"","full":["Chennai","India"],"name":"","street":"","city":"Chennai","state":"","ZIP":"","country":"India"},"organizers":["BIEN 2022"],"societies":[],"indexes":[],"emails":["bien@csit2022.org","bienconference@yahoo.com"]}