{"name":"12th International Conference on Database and Data Mining","series":"","short":"DBDM 2024","website":"https://ccnet2024.org/dbdm/index","content":"12th International Conference on Database and Data Mining (DBDM 2024) January 27 \\~ 28, 2024, Copenhagen, Denmark https://ccnet2024.org/dbdm/index Scope & Topics 12th International Conference on Database and Data Mining (DBDM 2024) Conference provides a forum for researchers who address this issue and to present their work in a peer-reviewed forum. Authors are solicited to contribute to the conference by submitting articles that illustrate research results, projects, surveying works and industrial experiences that describe significant advances in the following areas, but are not limited to these topics only. Topics of interest include, but are not limited to, the following: Data Mining • Data Mining Foundations • Data Mining Applications • Knowledge Processing Database • Constraint Modeling and Processing • Data and Information Integration & Modeling • Data and Information Privacy and Security • Data and Information Quality • Data and Information Networks • Data and Information Semantics • Data and Information Streams • Data Management in Grid and P2P Systems • Data Mining Algorithms • Data Mining Systems, Data Warehousing, OLAP • Database and Information System Architecture and Performance • Data Structures and Data Management Algorithms • DB Systems & Applications • Digital Libraries • Distributed, Parallel, P2P and Grid-based Databases • Electronic Commerce and Web Technologies • Electronic Government & E-Participation • Expert Systems and Decision Support Systems • Expert Systems, Decision Support Systems & Applications • Information Retrieval and Database Systems • Information Systems • Interoperability • Knowledge Acquisition, Discovery & Management • Knowledge and Information Processing • Knowledge Modeling • Knowledge Processing • Metadata Management • Mobile Data and Information • Multi-Databases and Database Federation • Multimedia, Object, Object Relational and Deductive Databases • Pervasive Data and Information • Process Modeling • Process Support and Automation • Query Processing and Optimization • Semantic Web and Ontologies • Sensor Data Management • Statistical and Scientific Databases • Temporal, Spatial and High Dimensional Databases • Trust, Privacy & Security in Digital Business • User Interfaces to Databases and Information Systems • Very Large Data Bases • Workflow Management and Databases • WWW and Databases • XML and Databases Paper Submission Authors are invited to submit papers through the conference Submission System by October 08, 2023\\. Submissions must be original and should not have been published previously or be under consideration for publication while being evaluated for this conference. The proceedings of the conference will be published by Computer Science Conference Proceedings in Computer Science & Information Technology (CS & IT) series (Confirmed). Selected papers from DBDM 2024, after further revisions, will be published in the special issue of the following journals • International Journal of Database Management Systems (IJDMS) - WJCI Indexed • International Journal of Data Mining & Knowledge Management Process (IJDKP) - WJCI Indexed • International Journal of Web & Semantic Technology (IJWesT) - IS Indexed • Information Technology in Industry (ITII) Important Dates: • Submission Deadline : October 08, 2023 • Authors Notification : November 30, 2023 • Registration & camera - Ready Paper Due : December 07, 2023 Contact Us Here's where you can reach us: dbdm@ccnet2024.org (or) dbdmconf@yahoo.com Submission System Link: https://ccnet2024.org/submission/index.php","date_start":"2024-01-27","date_end":"2024-01-28","important_dates":{"abstract":"","full":"2023-10-08","notification":"","final":""},"topics":["Arts & Humanities","Other"],"location":{"virtual":"","full":["Copenhagen","Denmark"],"name":"","street":"","city":"Copenhagen","state":"","ZIP":"","country":"Denmark"},"organizers":["12th International Conference on Database and Data Mining (DBDM 2024)"],"societies":[],"indexes":[],"emails":["dbdm@ccnet2024.org","dbdmconf@yahoo.com"]}