{"name":"7th International Conference on Software Engineering and Applications","series":"","short":"SOEA 2023","website":"https://aisca2023.org/soea/index","content":"7th International Conference on Software Engineering and Applications (SOEA 2023) January 02 \\~ 03, 2023, Zurich, Switzerland https://aisca2023.org/soea/index Scope 7th International Conference on Software Engineering and Applications (SOEA 2023) will provide an excellent international forum for sharing knowledge and results in theory, methodology and applications of Artificial Intelligence, Soft Computing and Applications. The aim of the conference is to provide a platform to the researchers and practitioners from both academia as well as industry to meet and share cutting-edge development in the field. Authors are solicited to contribute to this conference by submitting articles that illustrate research results, projects, surveying works and industrial experiences that describe significant advances in the following areas, but are not limited to. Topics of Interest • Advanced Topics in Software Engineering • Knowledge-based Systems and Formal Methods • Languages and Formal Methods • Managing Software Projects • Multimedia and Visual Software Engineering • Quality Management • Search Engines and Information Retrieval • Software Engineering Decision Making • Software Engineering Practice • Software Maintenance and Testing • The Software Process • Web Engineering Paper Submission Authors are invited to submit papers through the conference Submission System by December 10, 2022\\. Submissions must be original and should not have been published previously or be under consideration for publication while being evaluated for this conference. The proceedings of the conference will be published by Computer Science Conference Proceedings in Computer Science & Information Technology (CS & IT) series (Confirmed). Selected papers from SOEA 2023, after further revisions, will be published in the special issue of the following journals • International Journal of Software Engineering & Applications (IJSEA) • International Journal of Computer Science & Information Technology (IJCSIT) – INSPEC Indexed, WJCI Indexed • Information Technology in Industry (ITII) Important Dates • Submission Deadline: December 10, 2022 • Authors Notification: December 20, 2022 • Registration & Camera-Ready Paper Due: December 26, 2022 Contact Us Here's where you can reach us: soea@aisca2023.org or soea@yahoo.com Submission link: https://aisca2023.org/submission/index.php","date_start":"2023-01-02","date_end":"2023-01-03","important_dates":{"abstract":"","full":"2022-12-10","notification":"","final":""},"topics":["Engineering & Technology","Computer/Informatics","software engineering"],"location":{"virtual":"","full":["Zurich","Switzerland","Switzerland"],"name":"","street":"","city":"Zurich","state":"Switzerland","ZIP":"","country":"Switzerland"},"organizers":["SOEA 2023"],"societies":[],"indexes":[],"emails":["soea@aisca2023.org","soea@yahoo.com"]}