{"name":"3rd International Conference on Big Data, IOT & NLP","series":"","short":"BINLP 2023","website":"https://csty2023.org/binlp/index","content":"3rd International Conference on Big Data, IOT & NLP (BINLP 2023) October 21 \\~ 22, 2023, Sydney, Australia https://csty2023.org/binlp/index Scope 3rd International Conference on Big Data, IOT & NLP (BINLP 2023) will provide an excellent international forum for sharing knowledge and results in theory, methodology and applications of Big Data, IoT and NLP. Authors are solicited to contribute to the conference by submitting articles that illustrate research results, projects, surveying works and industrial experiences that describe significant advances in the areas of Big Data, Internet of Things and NLP. Authors are solicited to contribute to the conference by submitting articles that illustrate research results, projects, surveying works and industrial experiences that describe significant advances in the following areas, but are not limited to. Topics of interest include, but are not limited to, the following: • Argumentation Mining and Applications • Deep Learning, Neural Languages and NLP • Social Media and Web Analytics • Question Answering (QA) • Corpus Analysis • Semantic Web, Open Linked Data, and Ontologies • Natural Language in Conceptual Modeling • Natural language and Ubiquitous Computing • NLP techniques for Internet of Things (IoT) • NLP techniques for ambient intelligence • Big Data & Business Intelligence • Information Extraction, Retrieval • Semantic Processing & NLP • Security and Privacy for IoT • IoT-enabled Innovation and Entrepreneurship • IoT Applications and Services • Experimental Results and Deployment Scenarios • Electronics and Signal processing for IoT • Connectivity and Networking Paper Submission Authors are invited to submit papers through the conference Submission System by May 31, 2023\\. Submissions must be original and should not have been published previously or be under consideration for publication while being evaluated for this conference. The proceedings of the conference will be published by Computer Science Conference Proceedings in Computer Science & Information Technology (CS & IT) series (Confirmed). Selected papers from BINLP 2023, after further revisions, will be published in the special issues of the following journals • International Journal of Next - Generation Networks (IJNGN) • The International Journal of Ambient Systems and Applications (IJASA) • International Journal of Ubiquitous Computing (IJU) • International Journal on Natural Language Computing (IJNLC) • International Journal of Grid Computing & Applications (IJGCA) • Information Technology in Industry (ITII) Important Dates • Submission Deadline : May 31, 2023 • Authors Notification : July 31, 2023 • Registration & Camera-Ready Paper Due : August 12, 2023 Contact Us Here's where you can reach us : binlp@csty2023.org or binlpconf@yahoo.com Paper Submission URL: https://csty2023.org/submission/index.php Related Conference : 9th International Conference on Computer Science and Information Technology (CSTY 2023) Contact Us: csty@csty2023.org","date_start":"2023-10-21","date_end":"2023-10-22","important_dates":{"abstract":"","full":"2023-05-31","notification":"","final":""},"topics":["Engineering & Technology","Electrical/ Electronic","Internet of Things"],"location":{"virtual":"","full":["sydney","Australia"],"name":"","street":"","city":"sydney","state":"","ZIP":"","country":"Australia"},"organizers":["BINLP"],"societies":[],"indexes":[],"emails":["binlp@csty2023.org","binlpconf@yahoo.com","csty@csty2023.org"]}