{"name":"17th International Conference on Network Security & Applications","series":"","short":"CNSA 2024","website":"https://ccseit2024.org/cnsa/index","content":"17th International Conference on Network Security & Applications (CNSA 2024) January 20 \\~ 21, 2024, Zurich, Switzerland https://ccseit2024.org/cnsa/index Scope &Topics 17th International Conference on Network Security & Applications (CNSA 2024) focuses on all technical and practical aspects of security and its applications for wired and wireless networks. The goal of this conference is to bring together researchers and practitioners from academia and industry to focus on understanding modern security threats and counter measures and establishing new collaborations in these areas. We expect that the conference and its publications will be a trigger for further related research and technology improvements in this important subject. The topics suggested by this conference can be discussed in term of concepts, surveys, state of the art, research, standards, implementations, running experiments, applications and industrial case studies. Topics of interest include, but are not limited to the following Artificial intelligence, Machine Learning for Security Attacks on Virtualized Systems Blockchain Technology and Cyber Security Cloud Security Cognitive Security Cryptographic Protocols Cyber Physical System (CPS) security Database and System Security Data Center Network Control, Security and Optimization Designing a Security Policy E-mail Security, Spam, Phishing, E-mail fraud Hardware-Based Attacks Internet of Things (IoT) Security Internet Security, Applications Security & Network Management Intrusion Detection and Prevention Network and Wireless Network Security Peer-to-Peer Network Security Performance Evaluations of Protocols & Security Applications Security in Fog / edge Computing Security of Virtual Machines Security threats & Countermeasures (DDoS, MiM, Session Hijacking, Replay attack, Phishing, Scams etc,) Security, trust and privacy challenges Smart City Security Smart Grid security Ubiquitous Computing Security Virus, Worms, Trojan Protection Web 2.0 security Paper Submission Authors are invited to submit papers through the conference Submission System by Submission Deadline : January 06, 2024 (Last Call). Submissions must be original and should not have been published previously or be under consideration for publication while being evaluated for this conference. The proceedings of the conference will be published by Computer Science Conference Proceedings in Computer Science & Information Technology (CS & IT) series (Confirmed). Selected papers from CNSA 2024, after further revisions, will be published in the special issues of the following journals International Journal of Computer Networks & Communications (IJCNC) - Scopus, ERA, WJCI Indexed International Journal of Network Security & Its Applications (IJNSA) - ERA,WJCI Indexed International Journal on Cryptography and Information Security (IJCIS) International Journal of Security, Privacy and Trust Management (IJSPTM) Information Technology in Industry (ITII) Important Dates First Batch : (Submissions after December 16, 2023) Submission Deadline : Submission Deadline : January 06, 2024 (Last Call) Authors Notification : January 13, 2023 Registration & camera - Ready Paper Due : January 16, 2023 Contact Us Here's where you can reach us : cnsa@ccseit2024.org or cnsaconference@yahoo.com For other details: https://ccseit2024.org/cnsa/index Paper Submission Link: https://ccseit2024.org/submission/index.php","date_start":"2024-01-20","date_end":"2024-01-21","important_dates":{"abstract":"","full":"2024-01-06","notification":"","final":""},"topics":["Engineering & Technology","Other"],"location":{"virtual":"","full":["Zurich","Switzerland","Switzerland"],"name":"","street":"","city":"Zurich","state":"Switzerland","ZIP":"","country":"Switzerland"},"organizers":["CNSA 2024"],"societies":[],"indexes":[],"emails":["cnsa@ccseit2024.org","cnsaconference@yahoo.com"]}