{"name":"4th International Conference on Big Data, IOT and Block chain","series":"","short":"BIBC 2023","website":"https://www.csen2023.org/bibc/index","content":"4th International Conference on Big Data, IOT and Block chain (BIBC 2023) October 28 \\~ 29, 2023, Vienna, Austria https://www.csen2023.org/bibc/index Scope 4th International Conference on Big Data, IOT and Blockchain (BIBC 2023) will provide an excellent international forum for sharing knowledge and results in theory, methodology and applications of Big Data, IoT and Blockchain. Authors are solicited to contribute to the conference by submitting articles that illustrate research results, projects, surveying works and industrial experiences that describe significant advances in the areas of Big Data, Internet of Things and Blockchain advances. Topics of interest include, but are not limited to, the following • 5G and Networks for Big Data • AI for IoT • Big Data Analytics and Social Media • Big Data Applications, Bioinformatics, Multimedia etc • Big Data Infrastructure and platform • Big Data Management • Big Data Search and Mining • Big Data Security, Privacy and Trust • Big Data Techniques, models and algorithms • Big Data Tools and systems • Block chain and IoT • Cloud and grid computing for Big Data • Electronics and Signal processing for IoT • Energy Efficiency and Sustainability in IoT • Human Interaction with IoT • Interoperability in IoT • IoT Applications and Industry 4.0 • IoT Communication Technologies • IoT Edge and Cloud Architectures • IoT enabled Innovation and Entrepreneurship • IOT Experimental Results and Deployment Scenarios • Machine Learning and AI for Big Data • Machine learning and IoT • Robotic IoT Systems • Security and Privacy for IoT • Self-adaptation for IoT Systems • Software Engineering for IoT • Web of Things • Block Chain issues and trends • Block chain Attacks on Existing Systems • Block chain Consensus Algorithms • Block chain Foundations • Block chain New Design • Block chain Privacy • Block chain Scalability • Block chain-based security for the IoT • Block chain, Big data and IOT advances Paper Submission Authors are invited to submit papers through the conference Submission System by September 09, 2023\\. Submissions must be original and should not have been published previously or be under consideration for publication while being evaluated for this conference. The proceedings of the conference will be published by Computer Science Conference Proceedings in Computer Science & Information Technology (CS & IT) series (Confirmed). Selected papers from BIBC 2023, after further revisions, will be published in the special issue of the following journal. • International Journal of Computer Networks & Communications (IJCNC) - Scopus, ERA, WJCI Indexed • International Journal of Network Security & Its Applications (IJNSA)- ERA, WJCI Indexed • International Journal of Ubiquitous Computing (IJU) • International Journal of Ambient Systems and Applications (IJASA) • International Journal of Security, Privacy and Trust Management (IJSPTM) • Information Technology in Industry (ITII) Important Dates • Submission Deadline : September 09, 2023 • Authors Notification : October 10, 2023 • Registation & Camera – Ready Paper Due : October 15, 2023 Contact Us Here's where you can reach us : bibc@csen2023.org (or) bibcconf@yahoo.com Paper Submission Link : https://www.csen2023.org/submission/index.php","date_start":"2023-10-28","date_end":"2023-10-29","important_dates":{"abstract":"","full":"2023-09-09","notification":"","final":""},"topics":["Business","Information-Technology"],"location":{"virtual":"","full":["Vienna","Austria"],"name":"","street":"","city":"Vienna","state":"","ZIP":"","country":"Austria"},"organizers":["BIBC"],"societies":[],"indexes":[],"emails":["bibc@csen2023.org","bibcconf@yahoo.com"]}