{"name":"12th International Conference on Computer Science, Engineering and Applications","series":"","short":"ICCSEA 2022","website":"https://iccsea2022.org/index","content":"12th International Conference on Computer Science, Engineering and Applications (ICCSEA 2022) November 26 \\~ 27, 2022, London, United Kingdom https://iccsea2022.org/index Scope & Topics 12th International Conference on Computer Science, Engineering and Applications (ICCSEA 2022) will provide an excellent international forum for sharing knowledge and results in theory, methodology and applications of computer science, engineering and applications. The conference looks for significant contributions to all major fields of the computer science and information technology in theoretical and practical aspects. The aim of the conference is to provide a platform to the researchers and practitioners from both academia as well as industry to meet and share cutting-edge development in the field. Authors are solicited to contribute to the conference by submitting articles that illustrate research results, projects, surveying works and industrial experiences that describe significant advances in the following areas, but are not limited to. Topics of interest include, but are not limited to, the following • Algorithms and Bioinformatics • Big Data • Blockchain • Compiler Design • Computer Architecture and Real Time Systems • Computer Education • Data Mining • Database and Data Mining • Deep Learning • Dependable, Reliable and Autonomic Computing • Distributed and Parallel Systems & Algorithms • DSP/Image Processing/Pattern Recognition/Multimedia • Embedded System and Software • Game and Software Engineering • Geographical Information Systems/ Global Navigation Satellite Systems (GIS/GNSS) • Grid and Scalable Computing • Intelligent Information & Database Systems • Internet of Things • Machine Learning & Applications • Mobile and Ubiquitous Computing • Modeling and Simulation • Multimedia Systems and Services • Natural Language Processing • Networking and Communications • NLP • Operating Systems • Performance Evaluation • Programming Languages • Security and Information Assurance • Soft Computing (AI, Neural Networks, Fuzzy Systems, etc.) • Software Engineering • Theoretical Computer Science • Web and Internet Computing Paper Submission Authors are invited to submit papers through the conference Submission System by October 22, 2022\\. Submissions must be original and should not have been published previously or be under consideration for publication while being evaluated for this conference. The proceedings of the conference will be published by Computer Science Conference Proceedings in Computer Science & Information Technology (CS & IT) series (Confirmed). Selected papers from ICCSEA 2022, after further revisions, will be published in the special issues of the following journals. • International Journal of Computer Networks & Communications (IJCNC) - Scopus, WJCI, ERA Indexed • International Journal of Network Security & Its Applications (IJNSA) - ERA, WJCI Indexed • International Journal of Wireless & Mobile Networks (IJWMN) - ERA, WJCI Indexed • International Journal of Database Management Systems (IJDMS) - IS, WJCI Indexed • Computer Science & Engineering: An International Journal (CSEIJ) • International Journal of Information Technology Convergence and Services (IJITCS) • International Journal of Computer science and Engineering Survey (IJCSES) • Advanced Computing: An International Journal (ACIJ) • International Journal in Foundations of Computer Science & Technology (IJFCST) • International Journal on Computation Science & Application(IJCSA) • International Journal of Information Technology, Control and Automation (IJITCA) • International Journal of Computer Science, Engineering and Information Technology (IJCSEIT) • International Journal of Information Sciences and Techniques (IJIST) • International Journal of Advanced Information Technology (IJAIT) • International Journal of Computer Science, Engineering and Applications (IJCSEA) • Information Technology in Industry (ITII) Important Dates Third Batch : (Submissions after October 08, 2022) • Submission Deadline : October 22, 2022 • Authors Notification : November 15, 2022 • Registration & Camera-Ready Paper Due : November 22, 2022 Contact Us Here's where you can reach us : iccsea@iccsea2022.org or iccseaconf@yahoo.com","date_start":"2022-11-26","date_end":"2022-11-27","important_dates":{"abstract":"","full":"2022-10-22","notification":"","final":""},"topics":["Engineering & Technology","Computer/Informatics","software engineering"],"location":{"virtual":"","full":["london","United Kingdom"],"name":"","street":"","city":"london","state":"","ZIP":"","country":"United Kingdom"},"organizers":["ICCSEA 2022"],"societies":[],"indexes":[],"emails":["iccsea@iccsea2022.org","iccseaconf@yahoo.com"]}