{"name":"The 6th Int'l Conference on Statistics, Mathematical Modelling and Analysis","series":"","short":"SMMA 2023","website":"https://www.maymeeting.org/conference/SMMA2023","content":"The 6th Int'l Conference on Statistics, Mathematical Modelling and Analysis (SMMA 2023) Website：https://www.maymeeting.org/conference/SMMA2023/ Date：May 30-June 1, 2023 Venue：Chengdu, China Online Registration Entrance：https://www.maymeeting.org/RegistrationSubmission/default.aspx?ConferenceID=1594 The 6th Int'l Conference on Statistics, Mathematical Modelling and Analysis (SMMA 2023) will be held in Chengdu, China, during May 30-June 1, 2023\\. The aim of SMMA is to provide a stage for researchers, engineers, academicians as well as industrial professionals from all over the world to present their research results and development activities in Applied statistics, Data modeling and analysis, Design of simulation experiments, Statistical analysis system programming, Statistical applications, Statistical genetics, Statistics and mathematics education, etc. SMMA 2023 will be a valuable and important platform for inspiring international and interdisciplinary exchange at the forefront of Statistics, Mathematical Modelling and Analysis. Attendance Methods 1\\. Full Paper submission Submit full paper ( Regular Attendance + Paper Publication + Presentation ) You are invited to submit papers and participate in our academic exchange. One author will be invited to make an oral presentation and the paper will be published by peer-reviewed open access journal and submitted to CNKI and Google Scholar for indexing. 2.Abstract submission Submit abstract ( Regular Attendance + Abstract + Presentation ) You are welcome to submit abstract for oral presentation or poster presentation. 3.Regular Attendance ( No Submission Required ) You're also welcome to attend our conference (without submitting full paper or abstract) Publication and Presentation Publication: All the accepted papers will be published by a peer-reviewed open access journal that can ensure the widest dissemination of your published work Index: CNKI and Google Scholar Note: 1\\. If you want to present your research results but do NOT wish to publish a paper, you may simply submit an Abstract. 2\\. The simple Abstract submission should include the title, contents, keywords, authors names, affiliations and emails. The length is suggested to be controlled within 1 page and no more than 2 pages. 3\\. You will receive the review results within 3-5 working days after submission. If you do not get any notification within the time limit, please contact us as soon as possible. 4\\. You are welcome to submit papers in Chinese and please contact us for more details. Contact Us Email: wsconf5@163.com Tel: +86 132 6470 2250 (From Monday to Friday) QQ: 1349406763 WeChat: 3025797047 Official Account: Academic Communications","date_start":"2023-05-30","date_end":"2023-06-01","important_dates":{"abstract":"","full":"2023-05-23","notification":"","final":""},"topics":["Physical Science & Math","Mathematics","Statistics, Mathematical"],"location":{"virtual":"","full":["Chengdu","China"],"name":"","street":"","city":"Chengdu","state":"","ZIP":"","country":"China"},"organizers":["Academic Communications"],"societies":[],"indexes":[],"emails":["wsconf5@163.com"]}