{"name":"7th International Conference on Artificial Intelligence, Soft Computing and Applications","series":"","short":"AISCA 2023","website":"https://aisca2023.org","content":"7th International Conference on Artificial Intelligence, Soft Computing and Applications (AISCA 2023) January 02 \\~ 03, 2023, Zurich, Switzerland https://aisca2023.org/ Scope 7th International Conference on Artificial Intelligence, Soft Computing And Applications (AISCA 2023) will provide an excellent international forum for sharing knowledge and results in theory, methodology and applications of Artificial Intelligence, Soft Computing and Applications. The aim of the conference is to provide a platform to the researchers and practitioners from both academia as well as industry to meet and share cutting-edge development in the field. Authors are solicited to contribute to this conference by submitting articles that illustrate research results, projects, surveying works and industrial experiences that describe significant advances in the following areas, but are not limited to. Topics of interest • Artificial Intelligence • AI Algorithms • Artificial Intelligence tools & Applications • Automatic Control • Bioinformatics • Natural Language Processing • CAD Design & Testing • Computer Vision and Speech Understanding • Data Mining and Machine Learning Tools • Fuzzy Logic • Heuristic and AI Planning Strategies and Tools • Computational Theories of Learning • Hybrid Intelligent Systems • Information Retrieval • Intelligent System Architectures • Knowledge Representation • Knowledge-based Systems • Mechatronics • Multimedia & Cognitive Informatics • Parallel Processing • Robotics • Semantic Web Techniques and Technologies • Soft computing theory and applications • Software & Hardware Architectures • Soft Computing • Fuzzy Systems • Neural Networks • Machine learning • Probabilistic Reasoning • Evolutionary Computing • Pattern recognition • Hybrid intelligent systems • Software agents • Morphic Computing • Image processing • E-commerce, e-medicine • Rough Sets • Symbolic machine learning • Wavelet • Signal or Image Processing • Vision Recognition • Biomedical Engineering • Telecommunications • Reactive Distributed AI • Nano & Micro-systems • Data Visualization • Pervasive computing and ambient intelligence • Programming Languages • Reasoning and Evolution • Recent Trends and Developments • Web Intelligence Applications & Search Paper Submission Authors are invited to submit papers through the conference Submission System by December 17, 2022 (Final Call). Submissions must be original and should not have been published previously or be under consideration for publication while being evaluated for this conference. The proceedings of the conference will be published by Computer Science Conference Proceedings in Computer Science & Information Technology (CS & IT) series (Confirmed). Selected papers from AISCA 2023, after further revisions, will be published in the special issue of the following journals • International Journal of Soft Computing (IJSC) • International Journal of Artificial Intelligence & Applications (IJAIA) • International Journal on Soft Computing, Artificial Intelligence and Applications (IJSCAI) • Information Technology in Industry (ITII) Important Dates • Submission Deadline : December 17, 2022 (Final Call) • Authors Notification : December 27, 2022 • Registration & Camera-Ready Paper Due : December 29, 2022 Contact Us Here's where you can reach us: aisca@aisca2023.org or aiscaconfe@yahoo.com","date_start":"2023-01-02","date_end":"2023-01-03","important_dates":{"abstract":"","full":"2022-12-17","notification":"","final":""},"topics":["Engineering & Technology","Computer/Informatics","soft computing"],"location":{"virtual":"","full":["Zurich","Switzerland","Switzerland"],"name":"","street":"","city":"Zurich","state":"Switzerland","ZIP":"","country":"Switzerland"},"organizers":["AISCA 2023"],"societies":[],"indexes":[],"emails":["aisca@aisca2023.org","aiscaconfe@yahoo.com"]}