{"name":"4th International Conference on Data Science and Cloud Computing","series":"","short":"DSCC 2023","website":" https://cse2023.org/dscc/index","content":"4th International Conference on Data Science and Cloud Computing (DSCC 2023) August 19 \\~ 20, 2023, Chennai, India https://cse2023.org/dscc/index Scope 4th International Conference on Computational Science and Engineering (DSCC 2023) will act as a major forum for the presentation of innovative ideas, approaches, developments, and research projects in the areas of Data Science, Cloud Computing and Applications. It will also serve to facilitate the exchange of information between researchers and industry professionals to discuss the latest issues and advancement in the area of Data Science, Cloud Computing & Applications. Authors are solicited to contribute to the conference by submitting articles that illustrate research results, projects, surveying works and industrial experiences that describe significant advances in Data Science, Cloud Computing & Applications. Topics of Interest Data mining foundations Parallel and Distributed Data Mining Algorithms, Data Streams Mining, Graph Mining, Spatial Data Mining, Text video, Multimedia Data Mining, Web Mining, Pre-Processing Techniques, Visualization, Security and Information Hiding in Data Mining. Data mining Applications Databases, Bioinformatics, Biometrics, Image Analysis, Financial Modeling, Forecasting, Classification, Clustering, Social Networks, Educational Data Mining. Knowledge Processing Data and Knowledge Representation, Knowledge Discovery Framework and Process, Including Pre- and Post-Processing, Integration of Data Warehousing, OLAP and Data Mining, Integrating Constraints and Knowledge in the KDD Process, Exploring Data Analysis, Inference of Causes, Prediction, Evaluating, Consolidating and Explaining Discovered Knowledge, Statistical Techniques for Generation a Robust, Consistent Data Model, Interactive Data Exploration / Visualization and Discovery, Languages and Interfaces for Data Mining, Mining Trends, Opportunities and Risks, Mining from Low-Quality Information Sources. Data Mining & Machine learning Tasks Machine Learning Applications, Learning in knowledge-intensive systems, Learning Methods and analysis, Learning Problems, Deep Learning Big Data Big Data Algorithms, Big Data Fundamentals, Infrastructures for Big Data, Big Data Management and Frameworks, Big Data Search, Big Data security, Big Data Applications Cloud Computing Cloud Application, Infrastructure and Platforms, Design Tool for Cloud Computing, Cloud Business, Service-Oriented Architecture in Cloud Computing, Cloud Based, Parallel Processing, Virtualization on Platforms in the Cloud, Location Based Services, Presence, Availability, and Locality, Mobile Clouds for New Millennium, Mobile Devices, Social Clouds (Social Networks in the Cloud), Maintenance and Management of Cloud Computing Cloud Computing Architecture, Cloud Applications in Vertical Industries, Cloud Storage and File Systems, Networks within Cloud systems, the Storage Area, and to the Outside Virtualization in the Context of Cloud Computing, Platforms, System Integration, Virtual Compute Clusters, Consolidation NoSQL Data Stores, Performance, SLA Management and Enforcement, Resource Provisioning, Security Techniques for the Cloud, Energy Management and Programming Environments, Data storage and Management in Cloud Computing, Case Studies and Theories in Cloud Computing, The Open Cloud: Cloud Computing and Open Source Paper Submission Authors are invited to submit papers through the Submission System by July 15,2023 Submissions must be original and should not have been published previously or be under consideration for publication while being evaluated for this conference. The proceedings of the conference will be published by Computer Science Conference Proceedings in Computer Science & Information Technology (CS&IT) series(Confirmed). Selected papers from DSCC 2023, after further revisions, will be published in the special issue of the following journals • International Journal of Database Management Systems (IJDMS) - WJCI Indexed • International Journal of Data Mining & Knowledge Management Process (IJDKP) - WJCI Indexed • International Journal on Cloud Computing: Services and Architecture (IJCCSA) Important Dates • Submission Deadline: July 15,2023 • Authors Notification: August 10, 2023 • Registration & Camera-Ready Paper Due: Aug 12,2023 Contact Us Here's where you can reach us: dscc@cse2023.org or dsccconference@yahoo.com","date_start":"2023-08-19","date_end":"2023-08-20","important_dates":{"abstract":"","full":"2023-07-15","notification":"","final":""},"topics":["Education / Legal / Other","Education"],"location":{"virtual":"","full":["chennai","India"],"name":"","street":"","city":"chennai","state":"","ZIP":"","country":"India"},"organizers":[""],"societies":[],"indexes":[],"emails":["dscc@cse2023.org","dsccconference@yahoo.com"]}