{"name":"11th International Conference of Networks and Communications","series":"","short":"NECO 2022","website":"https://iccsea2022.org/neco/index","content":"11th International Conference of Networks and Communications (NECO 2022) November 26 \\~ 27, 2022, London, United Kingdom https://iccsea2022.org/neco/index Scope & Topics 11th International Conference of Networks and Communications (NECO 2022) looks for significant contributions to the Computer Networks & Communications for wired and wireless networks in theoretical and practical aspects. Original papers are invited on Computer Networks, Network Protocols and Wireless Networks, Data Communication Technologies, and Network Security. The goal of this Conference is to bring together researchers and practitioners from academia and industry to focus on advanced networking concepts and establishing new collaborations in these areas. Authors are solicited to contribute to the conference by submitting articles that illustrate research results, projects, surveying works and industrial experiences that describe significant advances in the following areas, but are not limited to. Topics of interest include, but are not limited to, the following: • Communication Network Architectures and Design • Communication Network Protocols • Discrete Algorithms and Discrete Modeling • Emerging Technologies for Next Generation Network • Future Internet Architecture, Protocols and Services • Mobile and Wireless Networks • Network Applications • Social Networks & Web 2.0 Trust Management • Network Operation and Management • Policy of Trust in E-leaning Systems • Network Security and Privacy • Network Services and Applications • Ubiquitous Networks & Cloud Computing • 5G/6G Cellular Systems and Heterogeneous Networks • Big data / Cloud computing and Networks • Big Data / IoT Analytics in Networking • Blockchain and Distributed Ledger • Information / Content Centric Networks (ICN) • Internet Measurement and Modeling • Internet of Things (IoT) • Machine Learning and AI in Networking • SDN/NFV and Network Programmability • Software-Defined Networking (SDN) and Network Virtualization • Vehicle-to-everything (V2X) and Autonomous cars • Vehicular Networks & Intelligent Transportation • VR/AR Streaming Paper Submission Authors are invited to submit papers through the conference Submission System by November 12, 2022\\. Submissions must be original and should not have been published previously or be under consideration for publication while being evaluated for this conference. The proceedings of the conference will be published by Computer Science Conference Proceedings in Computer Science & Information Technology (CS & IT) series (Confirmed). Selected papers from NECO 2022, after further revisions, will be published in the special issues of the following journals • International Journal of Computer Networks & Communications (IJCNC) - Scopus, WJCI, ERA Indexed • International Journal of Network Security & Its Applications (IJNSA) - ERA, WJCI Indexed • International Journal of Wireless & Mobile Networks (IJWMN) - ERA, WJCI Indexed • International Journal on Applications of Graph Theory in Wireless Ad hoc Networks and Sensor Networks (GRAPH-HOC)- IS ndexed • International Journal of Next-Generation Networks (IJNGN) • International Journal of Peer-to-Peer networks (IJP2P) • International Journal of Distributed and Parallel Systems (IJDPS) • International Journal of Grid Computing & Applications (IJGCA) • Information Technology in Industry (ITII) Important Dates • Submission Deadline : November 12, 2022 • Authors Notification : November 15, 2022 • Registration & Camera-Ready Paper Due : November 22, 2022 Contact Us Here's where you can reach us: neco@iccsea2022.org or necoconf2022@gmail.com","date_start":"2022-11-26","date_end":"2022-11-27","important_dates":{"abstract":"","full":"2022-11-12","notification":"","final":""},"topics":["Engineering & Technology","Other","Network Security"],"location":{"virtual":"","full":["London","United Kingdom","United Kingdom"],"name":"","street":"","city":"London","state":"United Kingdom","ZIP":"","country":"United Kingdom"},"organizers":["NECO 2022"],"societies":[],"indexes":[],"emails":["neco@iccsea2022.org","necoconf2022@gmail.com"]}