{"name":"9th International Conference on Computer Science and Information Technology","series":"","short":"CSTY 2023","website":"https://csty2023.org","content":"9th International Conference on Computer Science and Information Technology (CSTY 2023) October 21 \\~ 22, 2023, Sydney, Australia https://csty2023.org/ Scope 9th International Conference on Computer Science and Information Technology (CSTY 2023) will provide an excellent international forum for sharing knowledge and results in theory, methodology and applications of Computer Science, Engineering and Information Technology. The Conference looks for significant contributions to all major fields of the Computer Science, Engineering and Information Technology in theoretical and practical aspects. Authors are solicited to contribute to the conference by submitting articles that illustrate research results, projects, surveying works and industrial experiences that describe significant advances in the following areas, but are not limited to. Topics of interest include, but are not limited to, the following: • Accessible Computing • Algorithms and Bioinformatics • Algorithms and Computation Theory • Artificial Intelligence and Soft Computing • Big Data • Bioinformatics and Biosciences • Blockchain • Computer Architecture • Computer Graphics and Animation • Computer Science / Information Technology Education • Cryptography and Information security • Data Communication and Computer Networks • Data Mining and Knowledge Management Process • Data Mining • Database Management Systems • Deep Learning • Design Automation • Digital Signal and Image Processing • Electronic Commerce • Embedded Systems • Genetic and Evolutionary Computation • Health Informatics • High Performance Computing • Information Retrieval • Internet Engineering & Web services • Internet of Things • Machine Learning & Applications • Management Information Systems • Measurement and Evaluation • Microarchitecture • Multimedia and Applications • NLP • Operating Systems • Programming Languages • Security, Privacy and Trust Management • Simulation and Modeling • Software Engineering • Ubiquitous computing • Wireless and Mobile networks Paper Submission Authors are invited to submit papers through the conference Submission System by September 09, 2023\\. Submissions must be original and should not have been published previously or be under consideration for publication while being evaluated for this conference. The proceedings of the conference will be published by Computer Science Conference Proceedings in Computer Science & Information Technology (CS & IT) series (Confirmed). Selected papers from CSTY 2023, after further revisions, will be published in the special issues of the following journals • International Journal of Computer Science & Information Technology (IJCSIT) –INSPEC, WJCI Indexed • International Journal of Network Security & Its Applications (IJNSA) – ERA, WJCI Indexed • International Journal of Mobile Network Communications & Telematics (IJMNCT) • International Journal of Ad hoc, sensor & Ubiquitous Computing (IJASUC) • International Journal of Software Engineering & Applications (IJSEA) – ERA listed • Information Technology in Industry (ITII) Important Dates • Submission Deadline : September 09, 2023 • Authors Notification : October 07, 2023 • Registration & Camera-Ready Paper Due : October 13, 2023 Contact Us Here's where you can reach us : csty@csty2023.org or cstyconf@gmail.com Paper Submission URL: https://csty2023.org/submission/index.php Related Conference : 3rd International Conference on Big Data, IOT & NLP (BINLP 2023) Contact Us: binlp@csty2023.org","date_start":"2023-10-21","date_end":"2023-10-22","important_dates":{"abstract":"","full":"2023-09-02","notification":"","final":""},"topics":["Engineering & Technology","Computer/Informatics"],"location":{"virtual":"","full":["Sydney","Australia","Australia"],"name":"","street":"","city":"Sydney","state":"Australia","ZIP":"","country":"Australia"},"organizers":["CSTY 2023"],"societies":[],"indexes":[],"emails":["csty@csty2023.org","cstyconf@gmail.com","binlp@csty2023.org"]}