{"name":"8th International Conference on Artificial Intelligence","series":"","short":"ARIN 2022","website":"https://csita2022.org/arin/index","content":"8th International Conference on Artificial Intelligence (ARIN 2022) June 18 \\~ 19, 2022, Sydney, Australia https://csita2022.org/arin/index Scope & Topics 8th International Conference on Artificial Intelligence (ARIN 2022) is a forum for presenting new advances and research results in the fields of Artificial Intelligence. The conference will bring together leading researchers, engineers and scientists in the domain of interest from around the world. The scope of the conference covers all theoretical and practical aspects of the Artificial Intelligence. Authors are solicited to contribute to the conference by submitting articles that illustrate research results, projects, surveying works and industrial experiences that describe significant advances in the following areas but are not limited to: Topics of interest include, but are not limited to, the following: • AI Algorithms • Artificial Intelligence Tools & Applications • Automatic Control • Bioinformatics • Natural Language Processing • CAD Design and Testing • Computer Vision and Speech Understanding • Data Mining and Machine Learning Tools • Fuzzy Logic • Heuristic and AI Planning Strategies and Tools • Computational Theories of Learning • Hybrid Intelligent Systems • Information Retrieval • Intelligent System Architectures • Neural Networks • Knowledge Representation • Knowledge-based Systems • Mechatronics • Multimedia and Cognitive Informatics • Parallel Processing • Pattern Recognition • Pervasive Computing and Ambient Intelligence • Programming Languages • Reasoning and Evolution • Recent Trends and Developments • Robotics • Semantic Web Techniques and Technologies • Soft Computing Theory and Applications • Software and Hardware Architectures • Web Intelligence Applications and Search Paper Submission Authors are invited to submit papers through the conference Submission System by May 128 2022\\. Submissions must be original and should not have been published previously or be under consideration for publication while being evaluated for this conference. The proceedings of the conference will be published by Computer Science Conference Proceedings in Computer Science & Information Technology (CS & IT) series (Confirmed). Selected papers from ARIN 2022, after further revisions, will be published in the special issue of the following journals • International Journal of Artificial Intelligence & Applications (IJAIA) • International Journal of Fuzzy Logic Systems (IJFLS) • International Journal on Soft Computing, Artificial Intelligence and Applications (IJSCAI) Important Dates • Submission Deadline : May 28, 2022 • Authors Notification : June 10, 2022 • Registration & Camera-Ready Paper Due : June 13, 2022 Contact Us Here's where you can reach us : arinconf@yahoo.com or arin@csita2022.org","date_start":"2022-06-18","date_end":"2022-06-19","important_dates":{"abstract":"","full":"2022-05-28","notification":"","final":""},"topics":["Arts & Humanities","Other","Artificial intelligence"],"location":{"virtual":"","full":["Sydney","Australia"],"name":"","street":"","city":"Sydney","state":"","ZIP":"","country":"Australia"},"organizers":[""],"societies":[],"indexes":[],"emails":["arinconf@yahoo.com","arin@csita2022.org"]}