{"name":"4th International Conference on Natural Language Processing and Computational Linguistics","series":"","short":"NLPCL 2023","website":" https://ccsit2023.org/nlpcl/index","content":"4th International Conference on Natural Language Processing and Computational Linguistics (NLPCL 2023) July 22 \\~ 23, 2023 Venue: Hilton Toronto, Toronto, Canada https://ccsit2023.org/nlpcl/index Scope & Topics 4th International Conference on Natural Language Processing and Computational Linguistics (NLPCL 2023) will provide an excellent international forum for sharing knowledge and results in theory, methodology and applications of Natural Language Computing and Computational Linguistics. The Conference looks for significant contributions to all major fields of the Natural Language processing and Computational Linguistics in theoretical and practical aspects. Topics of interest include but are not limited to: • Chunking / Shallow Parsing • Dialog Systems • Discourse • Information Extraction • Information Retrieval • Lexical Semantics • Linguistic Resources • Machine Learning in NLP • Machine Translation • NLP for Digital Humanities • NLP for Educational Purposes • NLP for Language Documentation and Preservation • Ontology • Paraphrasing / Entailment / Generation • Parsing / Grammatical Formalisms • Phonology, Morphology • POS tagging • Question Answering • Semantic Processing • Speech Recognition and Synthesis • Spoken Language Processing • Text Mining Paper Submission Authors are invited to submit papers through the conference Submission System by July 08, 2023\\. Submissions must be original and should not have been published previously or be under consideration for publication while being evaluated for this conference. The proceedings of the conference will be published by Computer Science Conference Proceedings in Computer Science & Information Technology (CS & IT) series (Confirmed). Selected papers from NLPCL 2023, after further revisions, will be published in the special issue of the following journal. • Machine Learning and Applications: An International Journal (MLAIJ) • International Journal on Natural Language Computing (IJNLC) • The International Journal of Artificial Intelligence & Applications (IJAIA) • Information Technology in Industry (ITII) New- ESCI(WOS) Indexed Important Dates Third Batch : (Submissions after May 07, 2023) • Submission Deadline : July 08, 2023 • Notification : July 15, 2023 • Registration & Camera-Ready Paper Due : July 18, 2023 Contact Us Here's where you can reach us: nlpcl@ccsit2023.org or nlpclconference@yahoo.com Submission Link - https://ccsit2023.org/submission/index.php","date_start":"2023-07-22","date_end":"2023-07-23","important_dates":{"abstract":"","full":"2023-07-08","notification":"","final":""},"topics":["Arts & Humanities","Languages/Literature"],"location":{"virtual":"","full":["Toronto","Canada","Canada"],"name":"","street":"","city":"Toronto","state":"Canada","ZIP":"","country":"Canada"},"organizers":["Hilton Toronto, Toronto, Canada"],"societies":[],"indexes":[],"emails":["nlpcl@ccsit2023.org","nlpclconference@yahoo.com"]}