{"name":"4th International Conference on Natural Language Computing Advances","series":"","short":"NLCA 2023","website":"https://itcse2023.org/nlca/index","content":"4th International Conference on Natural Language Computing Advances (NLCA 2023) July 29 \\~ 30, 2023, London, United Kingdom https://itcse2023.org/nlca/index Scope 4th International Conference on Natural Language Computing Advances (NLCA 2023) will provide an excellent international forum for sharing knowledge and results in theory, methodology and applications of Natural Language Computing and its advances. Authors are solicited to contribute to the conference by submitting articles that illustrate research results, projects, surveying works and industrial experiences that describe significant advances in NLP. Topics of interest include, but are not limited to, the following • Chunking/Shallow Parsing • Dialog Systems • Discourse • Information Extraction • Information Retrieval • Lexical Semantics • Linguistic Resources • Machine Translation • Ontology • Paraphrasing/Entailment/Generation • Parsing/Grammatical Formalisms • Phonology, Morphology • POS Tagging • Question Answering • Semantic Processing • Speech Recognition and Synthesis • Spoken Language Processing • Statistical and Knowledge based Methods • Text Mining • NLP and Machine Learning • NLP and Computational Linguistics • NLP and Information Retrieval • NLP and AI Paper Submission Authors are invited to submit papers through the conference Submission System by February 18, 2022\\. Submissions must be original and should not have been published previously or be under consideration for publication while being evaluated for this conference. The proceedings of the conference will be published by Computer Science Conference Proceedings in Computer Science & Information Technology (CS & IT) series (Confirmed). Selected papers from NLCA 2023, after further revisions, will be published in the special issue of the following journal. • International Journal on Natural Language Computing (IJNLC) • International Journal on Information Theory (IJIT) • International Journal on Computational Science & Applications (IJCSA) • Machine Learning and Applications: An International Journal (MLAIJ) • International Journal of Web & Semantic Technology (IJWesT) Important Dates • Submission Deadline : February 18, 2022 • Authors Notification : March 25, 2023 • Registration & Camera-Ready Paper Due : April 03, 2023 Contact Us Here's where you can reach us: nlca@itcse2023.org (or) nlcaconference@yahoo.com Submission URL: https://itcse2023.org/submission/index.php","date_start":"2023-07-29","date_end":"2023-07-30","important_dates":{"abstract":"","full":"2023-02-18","notification":"","final":""},"topics":["Engineering & Technology","Mining/Mineral","NATURA"],"location":{"virtual":"","full":["London","United Kingdom","United Kingdom"],"name":"","street":"","city":"London","state":"United Kingdom","ZIP":"","country":"United Kingdom"},"organizers":["NLCA 2023"],"societies":[],"indexes":[],"emails":["nlca@itcse2023.org","nlcaconference@yahoo.com"]}