{"name":"2nd International Conference on Big Data, IoT and Machine Learning","series":"","short":"BIOM 2022","website":" https://comit2022.org/biom/index","content":"2nd International Conference on Big Data, IoT and Machine Learning (BIOM 2022) October 22 \\~ 23, 2022, Sydney, Australia https://comit2022.org/biom/index Scope & Topics 2nd International Conference on Big Data, IoT and Machine Learning (BIOM 2022) will act as a major forum for the presentation of innovative ideas, approaches, developments, and research projects in the areas of Big Data, Internet of Things (IoT) and Machine Learning. It will also serve to facilitate the exchange of information between researchers and industry professionals to discuss the latest issues and advancement in the area of Big Data, IoT and Machine Learning. Authors are solicited to contribute to the conference by submitting articles that illustrate research results, projects, surveying works and industrial experiences that describe significant advances in the following areas, but are not limited to. Topics of interest include, but are not limited to, the following: • 5G and Networks for Big Data • Big Data Analytics and Social Media • Big Data Applications, Bioinformatics, Multimedia etc • Big Data Infrastructure and platform • Big Data Management • Big Data Mining • Big Data Search and Mining • Big Data Security, Privacy and Trust • Big Data Techniques, models and algorithms • Big Data Tools and systems • Cloud and grid computing for Big Data • Connectivity and Networking • Deep Learning • Electronics and Signal processing for IoT • Experimental Results and Deployment Scenarios • Internet of Things • IoT Applications and Services • IoT-enabled Innovation and Entrepreneurship • Learning in knowledge-intensive systems • Learning Methods and analysis • Learning Problems • Machine Learning and AI for Big Data • Machine Learning Applications • Security and Privacy for IoT Paper Submission Authors are invited to submit papers through the conference Submission System by October 01,2022\\. Submissions must be original and should not have been published previously or be under consideration for publication while being evaluated for this conference. The proceedings of the conference will be published by Computer Science Conference Proceedings in Computer Science & Information Technology (CS & IT) series (Confirmed). Selected papers from BIOM 2022, after further revisions, will be published in the special issue of the following journal. • International Journal of Data Mining & Knowledge Management Process (IJDKP) • International Journal of Database Management Systems (IJDMS) • Machine Learning and Applications: An International Journal (MLAIJ) • Advances in Vision Computing: An International Journal (AVC) • International Journal of Grid Computing & Applications (IJGCA) • International Journal of Ambient Systems and Applications (IJASA) • International Journal on Web Service Computing (IJWSC) Important Dates • Submission Deadline : October 01 ,2022 • Authors Notification : October 15, 2022 • Registration & Camera-Ready Paper Due : October 18, 2022 Contact Us Here’s where you can reach us : biom@comit2022.org or biomconf@yahoo.com","date_start":"2022-10-22","date_end":"2022-10-23","important_dates":{"abstract":"","full":"2022-10-01","notification":"","final":""},"topics":["Education / Legal / Other","Education","Deep Learning"],"location":{"virtual":"","full":["Sydney","Australia","Australia"],"name":"","street":"","city":"Sydney","state":"Australia","ZIP":"","country":"Australia"},"organizers":["BIOM 2022"],"societies":[],"indexes":[],"emails":["biom@comit2022.org","biomconf@yahoo.com"]}