{"name":"10th International Conference on Computer Networks & Data Communications","series":"","short":"CNDC 2023","website":"https://www.cndc2023.org/index","content":"10th International Conference on Computer Networks & Data Communications (CNDC 2023) November 25 \\~ 26, 2023, London, United Kingdom https://www.cndc2023.org/index Scope &Topics 10th International Conference on Computer Networks & Data Communications (CNDC 2023) will provide an excellent international forum for sharing knowledge and results in theory and applications of Computer Networks and Data Communications. The Conference looks for significant contributions to the Computer Networks and Communications for wired and wireless networks in theoretical and practical aspects. Original papers are invited on Networks, wireless and Mobile, Protocols and wireless networks and security. The aim of the conference is to provide a platform to the researchers and practitioners from both academia as well as industry to meet and share cutting-edge development in the field. Topics of interest include, but are not limited to the following • Adhoc and Sensor Networks • Heterogeneous Wireless Networks • High Speed Networks • Internet and Web Applications • Measurement & Performance Analysis • Mobile & Broadband Wireless Internet • Mobile Networks & Wireless LAN • Network Architectures • Network Based Applications • Network Protocols and Wireless Networks • Network Security • Next Generation Internet • Next Generation Web Architectures • Optical Networking • Peer to Peer and Overlay Networks • QoS and Resource Management • Recent Trends & Developments in Computer Networks • Routing, Switching and Addressing Techniques • Self-Organizing Networks and Networked Systems • Ubiquitous Networks • Wireless Communications • Wireless Multimedia Systems Paper Submission Authors are invited to submit papers through the conference Submission System by November 18, 2023(Final Call). Submissions must be original and should not have been published previously or be under consideration for publication while being evaluated for this conference. The proceedings of the conference will be published by Computer Science Conference Proceedings in Computer Science & Information Technology (CS & IT) series (Confirmed). Selected papers from CNDC 2023, after further revisions, will be published in the special issues of the following journals • International Journal of Computer Networks & Communications (IJCNC) - Scopus, ERA, WJCI Indexed • International Journal of Next-Generation Networks (IJNGN) • International Journal of Peer to Peer Networks (IJP2P) • International Journal of Distributed and Parallel Systems (IJDPS) • International Journal of Grid Computing & Applications (IJGCA) • International Journal of UbiComp (IJU) • International Journal of Ad hoc, Sensor & Ubiquitous Computing (IJASUC) • International Journal of Advanced Smart Sensor Network Systems (IJASSN) • International Journal on AdHoc Networking Systems (IJANS) • Information Technology in Industry (ITII) Important Dates • Submission Deadline : November 18, 2023(Final Call) • Authors Notification : November 22, 2023 • Registration & camera - Ready Paper Due : November 24, 2023 Contact Us Here's where you can reach us: cndc@cndc2023.org (or) cndconf@yahoo.com For other details: https://www.cndc2023.org/index Paper Submission Link: https://www.cndc2023.org/submission/index.php","date_start":"2023-11-25","date_end":"2023-11-26","important_dates":{"abstract":"","full":"2023-11-18","notification":"","final":""},"topics":["Education / Legal / Other","Education"],"location":{"virtual":"","full":["London","United Kingdom","United Kingdom"],"name":"","street":"","city":"London","state":"United Kingdom","ZIP":"","country":"United Kingdom"},"organizers":["10th International Conference on Computer Networks & Data Communications (CNDC 2023)"],"societies":[],"indexes":[],"emails":["cndc@cndc2023.org","cndconf@yahoo.com"]}