{"name":"The 6th Int'l Conference on Sport Science and Physical Education","series":"","short":"SSPE 2023","website":"https://www.marchconf.org/conference/SSPE2023","content":"The 6th Int'l Conference on Sport Science and Physical Education (SSPE 2023) Website：https://www.marchconf.org/conference/SSPE2023/ Date：March 24-26, 2023 Venue：Xiamen,China Online Registration Entrance：https://www.marchconf.org/RegistrationSubmission/default.aspx?ConferenceID=1579 The 6th Int'l Conference on Sport Science and Physical Education (SSPE 2023) will be held during March 24-26, 2023 in Xiamen,China. This Conference will cover issues on Sport Science and Physical Education，and other related topics. It dedicates to creating a stage for exchanging the latest research results and sharing the advanced research methods in related fields. Attendance Methods 1\\. Full Paper submission Submit full paper ( Regular Attendance + Paper Publication + Presentation ) You are invited to submit papers and participate in our academic exchange. One author will be invited to make an oral presentation and the paper will be published by peer-reviewed open access journal and submitted to CNKI and Google Scholar for indexing. 2.Abstract submission Submit abstract ( Regular Attendance + Abstract + Presentation ) You are welcome to submit abstract for oral presentation or poster presentation. 3.Regular Attendance ( No Submission Required ) You're also welcome to attend our conference (without submitting full paper or abstract) Publication and Presentation Publication: All the accepted papers will be published by a peer-reviewed open access journal that can ensure the widest dissemination of your published work Index: CNKI and Google Scholar Note: 1\\. If you want to present your research results but do NOT wish to publish a paper, you may simply submit an Abstract. 2\\. The simple Abstract submission should include the title, contents, keywords, authors names, affiliations and emails. The length is suggested to be controlled within 1 page and no more than 2 pages. 3\\. You will receive the review results within 3-5 working days after submission. If you do not get any notification within the time limit, please contact us as soon as possible. 4\\. You are welcome to submit papers in Chinese and please contact us for more details. Contact Us Email: Editor\\_Workshop@163.com Tel: +86 132 6470 2250 QQ: 1349406763 WeChat: 3025797047 Official Account: Academic Communications Call For Papers Topics: The conference is soliciting state-of-the-art research papers in the following areas of interest: Adapted Physical Activity Curriculum Design / Pedagogy of Physical Education Mass Sports Measurement and Evaluation Reform and Innovation Regulations and Policies Sport Sociology Sport Psychology/Physiology Sports Biomechanics Sports Coaching and Training Sports Engineering Sports Equipment and Technology Sports Medicine/Traumatology/Health Sports Nutrition/Foods Sports Industry/Economics Sports Statistics Sports Ergonomics Sports Organization and Management Sports Globalization School Sports University Sports Other Related Topics","date_start":"2023-03-24","date_end":"2023-03-26","important_dates":{"abstract":"","full":"2023-03-24","notification":"","final":""},"topics":["Education / Legal / Other","Education"],"location":{"virtual":"","full":["xiamen","China"],"name":"","street":"","city":"xiamen","state":"","ZIP":"","country":"China"},"organizers":["Academic Communications"],"societies":[],"indexes":[],"emails":["_workshop@163.com"]}