{"name":"7 th International Conference on Networks & Communications","series":"","short":"NETWORKS 2023","website":"https://csea2023.org/networks/index","content":"7 th International Conference on Networks & Communications (NETWORKS 2023) December 16 \\~ 17, 2023, Dubai, UAE https://csea2023.org/networks/index Scope & Topics 7 th International Conference on Networks & Communications (NETWORKS 2023) will provide an excellent international forum for sharing knowledge and results in theory, methodology and applications of Computer Networks and Communications. The aim of the conference is to provide a platform to the researchers and practitioners from both academia as well as industry to meet and share cutting-edge development in the field. Topics of interest  Addressing & Location Management  Adhoc and Sensor Networks  Big data / cloud computing  Broadband Access Technologies  Cross Layer Design and Optimization  Heterogeneous Wireless Networks  High Speed Networks  Internet and Web Applications  Internet of Things (IoT)  Machine learning  Machine-to-machine (M2M) communications  Measurement & Performance Analysis  Mobile & Broadband Wireless Internet  Mobile Networks & Wireless LAN  Network Architectures  Network Based Applications  Network Operations & Management  Network Protocols & Wireless Networks  Network Security Trust, & Privacy  Network Protocols & Wireless Networks  Next generation (5G) mobile networks Next Generation Internet & Web Architectures  Peer to Peer and Overlay Networks  QOS And Resource Management  Recent Trends & Developments in Computer Networks  Routing, Switching and Addressing Techniques  Self-Organizing Networks and Networked Systems  Software defined networking  Ubiquitous Networks Paper Submission Authors are invited to submit papers through the conference Submission System by December 09 ,2023 (Final Call). Submissions must be original and should not have been published previously or be under consideration for publication while being evaluated for this conference. The proceedings of the conference will be published by Computer Science Conference Proceedings in Computer Science & Information Technology (CS & IT) series (Confirmed). Selected papers from NETWORKS 2023, after further revisions, will be published in the special issue of the following journals.  International Journal of Computer Networks & Communications (IJCNC) - ERA Indexed, Scopus, WJCI Indexed  International Journal of Wireless & Mobile Networks (IJWMN) - ERA, WJCI Indexed  International Journal of Distributed and Parallel systems (IJDPS)  International Journal of Grid Computing & Applications (IJGCA)  International Journal of UbiComp (IJU)  International Journal of Mobile Network Communications & Telematics (IJMNCT)  International Journal of Ambient Systems and Applications (IJASA)  International Journal on Integrating Technology in Education (IJITE)  Information Technology in Industry (ITII) Important Dates  Submission Deadline : December 09, 2023 (Final Call)  Authors Notification : December 14, 2023  Registration & Camera-Ready Paper Due : December 15, 2023 Contact Us Here's where you can reach us : networks@csea2023.org or networksconf@gmail.com","date_start":"2023-12-16","date_end":"2023-12-17","important_dates":{"abstract":"","full":"2023-12-09","notification":"","final":""},"topics":["Engineering & Technology","Electrical/ Electronic","Networks","Networks & Communications"],"location":{"virtual":"","full":["Dubai","UAE","United Arab Emirates"],"name":"","street":"","city":"Dubai","state":"UAE","ZIP":"","country":"United Arab Emirates"},"organizers":["NETWORKS 2023"],"societies":[],"indexes":[],"emails":["networks@csea2023.org","networksconf@gmail.com"]}