{"name":"11th International Conference on Artificial Intelligence & Applications","series":"","short":"ARIA 2024","website":"https://csen2024.org/aria/index","content":"11th International Conference on Artificial Intelligence & Applications (ARIA 2024) December 21 \\~ 22, 2024, Sydney, Australia https://csen2024.org/aria/index Scope & Topics 11th International Conference on Artificial Intelligence & Applications (ARIA 2024) will provide an excellent international forum for sharing knowledge and results in theory, methodology and applications of Artificial Intelligence. The aim of the conference is to provide a platform to the researchers and practitioners from both academia as well as industry to meet and share cutting-edge development in the field. Authors are solicited to contribute to the conference by submitting articles that illustrate research results, projects, surveying works and industrial experiences that describe significant advances in the following areas, but are not limited to. Topics of interest include, but are not limited to, the following • AI Algorithms • Artificial Intelligence Tools & Applications • Automatic Control • Bioinformatics • Natural Language Processing • CAD Design and Testing • Computer Vision and Speech Understanding • Data Mining and Machine Learning Tools • Fuzzy Logic • Heuristic and AI Planning Strategies and Tools • Computational Theories of Learning • Hybrid Intelligent Systems • Information Retrieval • Intelligent System Architectures • Knowledge Representation • Knowledge-based Systems • Mechatronics • Multimedia and Cognitive Informatics • Neural Networks • Parallel Processing • Pattern Recognition • Pervasive Computing and Ambient Intelligence • Programming languages • Reasoning and Evolution • Recent Trends and Developments • Robotics • Semantic Web Techniques and Technologies • Soft Computing Theory and Applications • Software and Hardware Architectures • Web Intelligence Applications and Search Paper Submission Authors are invited to submit papers through the conference Submission System by November 02, 2024\\. Submissions must be original and should not have been published previously or be under consideration for publication while being evaluated for this conference. The proceedings of the conference will be published by Computer Science Conference Proceedings in Computer Science & Information Technology (CS & IT) series (Confirmed). Selected papers from ARIA 2024, after further revisions, will be published in the special issue of the following journals. • International Journal of Artificial Intelligence & Applications (IJAIA) • International Journal of Fuzzy Logic Systems (IJFLS) • International Journal on Soft Computing, Artificial Intelligence and Applications (IJSCAI) Important Dates • Submission Deadline: November 02, 2024 • Authors Notification: November 30, 2024 • Registration & Camera-Ready Paper Due: December 07, 2024 Contact Us Here's where you can reach us: aria@csen2024.org (or) aria\\_conf@yahoo.com For more details, please visit: https://csen2024.org/aria/index Paper Submission Link: https://csen2024.org/submission/index","date_start":"2024-12-21","date_end":"2024-12-22","important_dates":{"abstract":"","full":"2024-11-02","notification":"","final":""},"topics":["Engineering & Technology","Computer/Informatics","Artificial Intelligence","Natural Language Processing"],"location":{"virtual":"","full":["Sydney","Australia"],"name":"","street":"","city":"Sydney","state":"","ZIP":"","country":"Australia"},"organizers":["ARIA 2024"],"societies":[],"indexes":[],"emails":["aria@csen2024.org","_conf@yahoo.com"]}