{"name":"13th International Conference on Signal & Image Processing","series":"","short":"SIP 2024","website":"https://www.comit2024.org/sip/index","content":"13th International Conference on Signal & Image Processing (SIP 2024) August 17 \\~ 18, 2024, Chennai, India https://www.comit2024.org/sip/index Scope 13th International Conference on Signal & Image Processing (SIP 2024) will provide an excellent international forum for sharing knowledge and results in theory, methodology and applications of Signal and Image Processing. The Conference looks for significant contributions to all major fields of the Signal and Image Processing in theoretical and practical aspects. The aim of the conference is to provide a platform to the researchers and practitioners from both academia as well as industry to meet and share cutting-edge development in the field. Authors are solicited to contribute to the conference by submitting articles that illustrate research results, projects, surveying works and industrial experiences that describe significant advances in the following areas, but are not limited to. Topics of Interest • Applied Digital Signal Processing • Coding and Transmission • Digital Signal Processing in Communications • Emerging technologies • Emerging Technologies in Digital Signal Processing • Image & signal processing Applications • Image Acquisition and Display • Image and Video Processing & Analysis • Image formation • Image scanning, display and printing • Storage and Retrieval Paper Submission Authors are invited to submit papers through the Submission System by August 03, 2024(Final Call). Submissions must be original and should not have been published previously or be under consideration for publication while being evaluated for this conference. The proceedings of the conference will be published by Computer Science Conference Proceedings in Computer Science & Information Technology (CS&IT) series(Confirmed). Selected papers from SIP 2024, after further revisions, will be published in the special issue of the following journals • International Journal of Multimedia & Its Applications (IJMA) - ERA Indexed • Signal & Image Processing : An International Journal (SIPIJ) - WJCI Indexed • International Journal of VLSI design & Communication Systems (VLSICS) • International Journal on Organic Electronics (IJOE) • Advances in Vision Computing: An International Journal (AVC) • International Journal on Soft Computing (IJSC) Contact Us Here's where you can reach us : sip@comit2024.org or sipconfe@gmail.com Submission Link: https://www.comit2024.org/submission/index.php","date_start":"2024-08-17","date_end":"2024-08-18","important_dates":{"abstract":"","full":"2024-08-03","notification":"","final":""},"topics":["Engineering & Technology","Electrical/ Electronic","Signal Processing","Image Processing"],"location":{"virtual":"","full":["Chennai","India"],"name":"","street":"","city":"Chennai","state":"","ZIP":"","country":"India"},"organizers":["SIP"],"societies":[],"indexes":[],"emails":["sip@comit2024.org","sipconfe@gmail.com"]}