{"name":"5th International Conference on Soft Computing, Artificial Intelligence and Machine Learning","series":"","short":"SAIM 2024","website":"https://acsit2024.org/saim/index","content":"5th International Conference on Soft Computing, Artificial Intelligence and Machine Learning (SAIM 2024) April 27 \\~ 28, 2024, Copenhagen, Denmark https://acsit2024.org/saim/index Scope & Topics 5th International Conference on Soft Computing, Artificial Intelligence and Machine Learning (SAIM 2024) will provide an excellent international forum for sharing knowledge and results in theory, methodology and applications of Artificial Intelligence, Soft Computing, Machine Learning. Authors are solicited to contribute to the conference by submitting articles that illustrate research results, projects, surveying works and industrial experiences that describe significant advances in the following areas, but are not limited to. Topics of interest include, but are not limited to, the following • AI Algorithms • Artificial Intelligence • Automatic Control • Bioinformatics • Biomedical Engineering • CAD Design & Testing • Computational Theories of Learning • Computer Vision and Speech Understanding • Data Mining and Machine Learning Tools • Data Visualization • E-commerce and E-medicine • Evolutionary Computing • Fuzzy Logic / systems • Geographical Information Systems / Global Navigation Satellite Systems (GIS/GNSS) • Heuristic and AI Planning Strategies and Tools • Hybrid Intelligent Systems • Information Retrieval • Intelligent System Architectures • Knowledge Representation • Knowledge-based Systems • Machine Learning • Machine Learning Applications • Machine Learning in knowledge-intensive systems • Machine Learning Methods and analysis • Machine Learning Problems • Mechatronics • Morphic Computing • Multimedia & Cognitive Informatics • Nano & Micro-systems • Natural Language Processing • Neural Networks • Parallel Processing • Pattern Recognition • Pervasive Computing and Ambient Intelligence • Probabilistic Reasoning • Programming Languages • Reactive Distributed AI • Reasoning and Evolution • Recent Trends and Developments • Robotics • Rough Sets • Semantic Web Techniques and Technologies • Signal & Image Processing • Soft Computing • Soft Computing Theory and Applications • Symbolic Machine Learning • Telecommunications • Vision Recognition • Wavelet • Web Intelligence Applications & Search Paper Submission Authors are invited to submit papers through the conference Submission System by April 13, 2024\\. Submissions must be original and should not have been published previously or be under consideration for publication while being evaluated for this conference. The proceedings of the conference will be published by Computer Science Conference Proceedings in Computer Science & Information Technology (CS & IT) series (Confirmed). Selected papers from SAIM 2024, after further revisions, will be published in the special issue of the following journals. • International Journal on Soft Computing, Artificial Intelligence and Applications (IJSCAI) • International Journal on Soft Computing (IJSC) • International Journal of Artificial Intelligence & Applications (IJAIA) • Advances in Vision Computing: An International Journal (AVC) • Machine Learning and Applications: An International Journal (MLAIJ) Contact Us Here's where you can reach us: saim@acsit2024.org (or) saimconference@gmail.com For more details, please visit: https://acsit2024.org/saim/index Paper Submission Link: https://acsit2024.org/submission/index.php","date_start":"2024-04-27","date_end":"2024-04-28","important_dates":{"abstract":"","full":"2024-04-13","notification":"","final":""},"topics":["Engineering & Technology","Computer/Informatics","Artificial Intelligence","Machine Learning"],"location":{"virtual":"","full":["Copenhagen","Denmark"],"name":"","street":"","city":"Copenhagen","state":"","ZIP":"","country":"Denmark"},"organizers":["SAIM 2024"],"societies":[],"indexes":[],"emails":["saim@acsit2024.org","saimconference@gmail.com"]}