{"name":"13th International Conference on Digital Image Processing and Vision","series":"","short":"ICDIPV 2024","website":"https://itcse2024.org/icdipv/index","content":"13th International Conference on Digital Image Processing and Vision (ICDIPV 2024) September 28 \\~ 29, 2024, Toronto, Canada https://itcse2024.org/icdipv/index Scope & Topics 13th International Conference on Digital Image Processing and Vision (ICDIPV 2024) is a forum for presenting new advances and research results in the fields of Digital Image Processing and vision. The conference will bring together leading researchers, engineers and scientists in the domain of interest from around the world. Authors are solicited to contribute to the conference by submitting articles that illustrate research results, projects, surveying works and industrial experiences that describe significant advances in the following areas, but are not limited to. Topics of interest include, but are not limited to, the following • Applied Digital Signal Processing • Coding and Transmission • Computer Graphics and Visualization • Computer Vision • Data Analytics and Machine Learning • Deep Learning: Algorithms, Implementations, and applications • Digital Signal Processing in Communications • Emerging Technologies in Digital Signal Processing • Emerging Technologies • Human Biometrics and Security Systems • Internet of Things Technology • Image & signal processing Applications • Image Acquisition and Display • Image and Video Processing & Analysis • Image Formation • Image Scanning, Display and Printing • Machine Learning, Computer Graphics, Biological Vision • Medical Signal Acquisition, Analysis and Processing • Signal and Information Processing for Smart Systems • Signal and Information Processing in Education • Storage and Retrieval Paper Submission Authors are invited to submit papers through the conference Submission System by September 21, 2024 (Final Call). Submissions must be original and should not have been published previously or be under consideration for publication while being evaluated for this conference. The proceedings of the conference will be published by Computer Science Conference Proceedings in Computer Science & Information Technology (CS & IT) series (Confirmed). Selected papers from ICDIPV 2024, after further revisions, will be published in the special issues of the following journals. • Signal & Image Processing: An International Journal (SIPIJ) - WJCI Indexed • International Journal of VLSI design & Communication Systems (VLSICS) • International Journal of Embedded Systems and Applications (IJESA) • International Journal on Organic Electronics (IJOE) • Information Technology in Industry (ITII) Important Dates • Submission Deadline: September 21, 2024 (Final Call) • Authors Notification: September 25, 2024 • Registration & Camera-Ready Paper Due: September 27, 2024 Contact Us Here's where you can reach us: icdipv@itcse2024.org (or) icdipconf@yahoo.com For more details, please visit: https://itcse2024.org/icdipv/index Paper Submission Link: https://itcse2024.org/submission/index.php","date_start":"2024-09-28","date_end":"2024-09-29","important_dates":{"abstract":"","full":"2024-09-21","notification":"","final":""},"topics":["Engineering & Technology","Computer/Informatics","Image Processing","Computer Vision"],"location":{"virtual":"","full":["Toronto","Canada"],"name":"","street":"","city":"Toronto","state":"","ZIP":"","country":"Canada"},"organizers":["ICDIPV 2024"],"societies":[],"indexes":[],"emails":["icdipv@itcse2024.org","icdipconf@yahoo.com"]}