{"name":"10th International Conference on Artificial Intelligence and Soft Computing","series":"","short":"AISO 2024","website":"https://comit2024.org/aiso/index","content":"10th International Conference on Artificial Intelligence and Soft Computing (AISO 2024) August 17 \\~ 18, 2024, Chennai, India https://comit2024.org/aiso/index Scope & Topics 10th International Conference on Artificial Intelligence and Soft Computing (AISO 2024) will provide an excellent international forum for sharing knowledge and results in theory, methodology and applications of Artificial Intelligence, Soft Computing. The aim of the conference is to provide a platform to the researchers and practitioners from both academia as well as industry to meet and share cutting-edge development in the field. Authors are solicited to contribute to the conference by submitting articles that illustrate research results, projects, surveying works and industrial experiences that describe significant advances in the following areas, but are not limited to. Topics of interest include, but are not limited to, the following: • AI Algorithms • Artificial Intelligence Tools & Applications • Automatic Control • Bioinformatics • Biomedical Engineering • CAD Design & Testing • Computational Theories of Learning • Computer Vision and Speech Understanding • Data Mining and Machine Learning Tools • Data Visualization • E-commerce, E-medicine • Evolutionary Computing • Fuzzy Logic • Fuzzy Systems • Heuristic and AI Planning Strategies and Tools • Hybrid Intelligent Systems • Image processing • Information Retrieval • Intelligent System Architectures • Knowledge Representation • Knowledge-based Systems • Machine Learning • Mechatronics • Morphic Computing • Multimedia & Cognitive Informatics • Nano & Micro-systems • Natural Language Processing • Neural Networks • Parallel Processing • Pattern Recognition • Pervasive Computing and Ambient Intelligence • Probabilistic Reasoning • Programming Languages Artificial Intelligence • Reactive Distributed AI • Recent Trends and Developments • Robotics • Rough Sets • Signax or Image Processing • Soft Computing and Applications • Software Agents • Symbolic Machine Learning • Telecommunications • Vision Recognition • Wavelet Paper Submission Authors are invited to submit papers through the conference Submission System by April 13, 2024\\. Submissions must be original and should not have been published previously or be under consideration for publication while being evaluated for this conference. The proceedings of the conference will be published by Computer Science Conference Proceedings in Computer Science & Information Technology (CS & IT) series (Confirmed). Selected papers from AISO 2024, after further revisions, will be published in the special issues of the following journals • International Journal of Artificial Intelligence & Applications (IJAIA) • International Journal of Fuzzy Logic Systems (IJFLS) • International Journal on Soft Computing, Artificial Intelligence and Applications (IJSCAI) • Information Technology in Industry (ITII) Important Dates Second Batch : (Submissions after April 06, 2024) • Submission Deadline : April 13, 2024 • Authors Notification : May 25, 2024 • Registration & Camera-Ready Paper Due : June 01, 2024 Contact Us Here's where you can reach us : aiso@comit2024.org or aisoconference@yahoo.com For more details, please visit: https://comit2024.org/aiso/index Paper Submission Link: https://comit2024.org/submission/index.php","date_start":"2024-08-17","date_end":"2024-08-18","important_dates":{"abstract":"","full":"2024-04-13","notification":"","final":""},"topics":["Engineering & Technology","Computer/Informatics","Artificial Intelligence"],"location":{"virtual":"","full":["Chennai","India","India"],"name":"","street":"","city":"Chennai","state":"India","ZIP":"","country":"India"},"organizers":["AISO 2024"],"societies":[],"indexes":[],"emails":["aiso@comit2024.org","aisoconference@yahoo.com"]}