{"name":"10th International Conference on Image and Signal Processing","series":"","short":"ISPR 2024","website":"https://csita2024.org/ispr/index","content":"10th International Conference on Image and Signal Processing (ISPR 2024) March 16 \\~ 17, 2024, Vienna, Austria https://csita2024.org/ispr/index Scope & Topics 10th International Conference on Image and Signal Processing (ISPR 2024) is a forum for presenting new advances and research results in the fields of Digital Image Processing. The conference will bring together leading researchers, engineers and scientists in the domain of interest from around the world. The scope of the conference covers all theoretical and practical aspects of the Signal, Image Processing & Pattern Recognition. Authors are solicited to contribute to the conference by submitting articles that illustrate research results, projects, surveying works and industrial experiences. Authors are solicited to contribute to the conference by submitting articles that illustrate research results, projects, surveying works and industrial experiences that describe significant advances in the following areas, but are not limited to: Topics of interest include, but are not limited to, the following • 3D and Stereo Imaging • 3-D and Surface Reconstruction • Analog and Mixed Signal Processing • Application & Others • Application & Others • Applications (Biomedical, Bioinformatics, Genomic, Seismic, Radar, Sonar, Remote Sensing, Positioning, etc.) • Array Signal Processing • Audio/Speech Processing and Coding • Biomedical Imaging Technologies • Biometrics and Pattern Recognition • Cognitive and Biologically-inspired Vision • Color and Texture • Communication Signal processing • Computer Communication and Networks • Computer Vision & VR • Constraint Processing • Content-based Image retrieval • Content-based Image retrieval • Data Mining Techniques • DE for Image Processing • Detection and Estimation of Signal Parameters • Digital & Mobile Signal Processing • Digital & Mobile Signal Processing • Distributed Source Coding • Document Recognition • DSP Implementation and Embedded Systems • Face and Gesture • Face Recognition & Super-resolution Imaging • Face Recognition • Filter Design and Structures • FIR, IIR and Adaptive Filters • Fuzzy system applications in system and Control Engineering • Hardware Implementation for Signal Processing • Higher Order Spectral Analysis • Illumination and Reflectance Modeling • Image acquisition & Medical Image processing • Image and Video Retrieval • Image Coding and Compression • Image Processing & Understanding • Image Segmentation • Image-Based Modeling • Internet Signal Processing • Knowledge Representation and High-Level Vision • Medical Image Analysis • Motion Detection • Multidimensional Signal Processing • Multiple Filtering and Filter Banks • Multi-view Geometry • Neural Networks and Genetic Algorithms • Nonlinear Signals and Systems • Object Detection, Recognition and Categorization • Pattern Recognition and Analysis • Pattern Recognition in New Modalities • Performance Evaluation • Radar Signal Processing • Remote Sensing • Segmentation • Sensor Array and Multi-channel Processing • Shape Representation • Signal Identification • Signal Noise Control • Signal Processing Education • Signal Reconstruction • Sonar Signal Processing and Localization • Spectral Analysis • Speech, Audio and Music Processing • Statistic Learning & Pattern Recognition • Statistical & Optical Signal Processing • Statistical & Optical Signal Processing • Text processing • Time-Frequency Signal Analysis • Time-Frequency/Time-Scale Analysis • Video Analysis and Event Recognition • Video compression & Streaming • Video Signal Processing • Video Surveillance and Monitoring • Visualization • Watermarking Paper Submission Authors are invited to submit papers through the conference Submission System by March 02, 2024 (Final Call). Submissions must be original and should not have been published previously or be under consideration for publication while being evaluated for this conference. The proceedings of the conference will be published by The proceedings of the conference will be published by Computer Science Conference Proceedings in Computer Science & Information Technology (CS & IT) series (Confirmed). Selected papers from ISPR 2024, after further revisions, will be published in the special issue of the following journals. • Signal & Image Processing : An International Journal (SIPIJ) – WJCI Indexed • International Journal of VLSI Design & Communication Systems (VLSICS) • International Journal of Embedded Systems and Applications (IJESA) • International Journal of Multimedia & Its Applications (IJMA)- ERA , WJCI Indexed Important Dates • Submission Deadline : March 02, 2024(Final Call) • Authors Notification: March 12, 2024 • Final Manuscript Due: March 14, 2024 Contact Us: Here's where you can reach us : ispr@csita2024.org or isprconf@yahoo.com Submission URL : https://csita2024.org/submission/index.php","date_start":"2024-03-16","date_end":"2024-03-17","important_dates":{"abstract":"","full":"2024-03-02","notification":"","final":""},"topics":["Engineering & Technology","Computer/Informatics","Signal Processing","Image Processing"],"location":{"virtual":"","full":["Vienna","Austria"],"name":"","street":"","city":"Vienna","state":"","ZIP":"","country":"Austria"},"organizers":["ISPR 2024"],"societies":[],"indexes":[],"emails":["ispr@csita2024.org","isprconf@yahoo.com"]}