{"name":"5th International Conference on Advances in Artificial Intelligence Techniques (ArIT 2024)","series":"","short":"","website":"https://cseit2024.org/arit/index","content":"5th International Conference on Advances in Artificial Intelligence Techniques (ArIT 2024) July 27 \\~ 28, 2024, London, United Kingdom https://cseit2024.org/arit/index Scope & Topics 5th International Conference on Advances in Artificial Intelligence Techniques (ArIT 2024) will provide an excellent international forum for sharing knowledge and results in theory, methodology and applications of Artificial Intelligence and its advances. The Conference looks for significant contributions to all major fields of the Artificial Intelligence in theoretical and practical aspects. The aim of the Conference is to provide a platform to the researchers and practitioners from both academia as well as industry to meet and share cutting-edge development in the field. Authors are solicited to contribute to the conference by submitting articles that illustrate research results, projects, surveying works and industrial experiences that describe significant advances in the following areas, but are not limited to these topics only. Topics of interest include, but are not limited to the following • Adaptive systems • AI Algorithms • Artificial Intelligence and Cloud Computing • Artificial Intelligence and Internet of Things • Artificial Intelligence Cyber Security • Artificial Intelligence tools & Applications • Automated Machine Learning • Bioinformatics, Biometrics • Business Intelligence • Data and Web mining • Deep Learning • Ensemble Method • Evolutionary Computation • Financial Engineering • Fuzzy set theory, Fuzzy control and System • Geo-informatics • Hybrid and Nonlinear system • Inductive Learning • Information Fusion • Information Retrieval • Intelligent Agent • Intelligent and Knowledge based system • Intelligent Control • Logistics • Machine Learning Tools • Media computing • Neural network and support vector machine • Pattern Recognition • Rough and fuzzy rough set • Visual information processing Paper Submission Authors are invited to submit papers through the conference Submission System by April 27, 2024\\. Submissions must be original and should not have been published previously or be under consideration for publication while being evaluated for this conference. The proceedings of the conference will be published by Computer Science Conference Proceedings in Computer Science & Information Technology (CS & IT) series (Confirmed). Selected papers from ArIT 2024, after further revisions, will be published in the special issues of the following journals • International Journal of Artificial Intelligence & Applications (IJAIA) • International Journal of Fuzzy Logic Systems (IJFLS) • International Journal on Soft Computing, Artificial Intelligence and Applications (IJSCAI) • International Journal on Soft Computing (IJSC) • Information Technology in Industry (ITII) Important Dates Second Batch : (Submissions after April 06, 2024) • Submission Deadline : April 27, 2024 • Authors Notification : May 30, 2024 • Registration & camera - Ready Paper Due : June 07, 2024 Contact Us Here's where you can reach us : arit@cseit2024.org (or) aritsecretary@gmail.com For other details: https://cseit2024.org/arit/index Paper Submission Link: https://cseit2024.org/submission/index.php","date_start":"2024-07-27","date_end":"2024-07-28","important_dates":{"abstract":"","full":"2024-04-27","notification":"","final":""},"topics":["Engineering & Technology","Architectural/Environmental","Artificial Intelligence","Machine Learning"],"location":{"virtual":"","full":["London","United Kingdom","United Kingdom"],"name":"","street":"","city":"London","state":"United Kingdom","ZIP":"","country":"United Kingdom"},"organizers":["ArIT 2024"],"societies":[],"indexes":[],"emails":["arit@cseit2024.org","aritsecretary@gmail.com"]}