{"name":"10th International Conference on Software Engineering","series":"","short":"SOENG 2024","website":"https://csit2024.org/soeng/index","content":"10th International Conference on Software Engineering (SOENG 2024) https://csit2024.org/soeng/index June 22 \\~ 23, 2024, Sydney, Australia Scope 10th International Conference on Software Engineering (SOENG 2024) will provide an excellent international forum for sharing knowledge and results in theory, methodology and applications of Software Engineering and Applications. The goal of this conference is to bring together researchers and practitioners from academia and industry to focus on understanding Modern software engineering concepts and establishing new collaborations in these areas. Authors are solicited to contribute to the conference by submitting articles that illustrate research results, projects, surveying works and industrial experiences that describe significant advances in the following areas, but are not limited to. Topics of Interest • The Software Process • Software Engineering Practice • Web Engineering • Quality Management • Managing Software Projects • Advanced Topics in Software Engineering • Multimedia and Visual Software Engineering • Software Maintenance and Testing • Languages and Formal Methods • Web-based Education Systems and Learning Applications • Software Engineering Decision Making • Knowledge-based Systems and Formal Methods • Search Engines and Information Retrieval Paper Submission Authors are invited to submit papers through the conference Submission System by May 04 2024 . Submissions must be original and should not have been published previously or be under consideration for publication while being evaluated for this conference. The proceedings of the conference will be published by Computer Science Conference Proceedings in Computer Science & Information Technology (CS & IT) series (Confirmed). Selected papers from SOENG 2024, after further revisions, will be published in the special issue of the following journals • International Journal on Computational Science & Applications (IJCSA) • International Journal of Software Engineering & Applications (IJSEA) - ERA Indexed • International Journal of Security, Privacy and Trust Management (IJSPTM) • Information Technology in Industry (ITII) Important dates • Submission Deadline : May 04, 2024 • Authors Notification : June 11, 2024 • Registration & Camera-Ready Paper Due : June 15, 2024 Contact Us Here's where you can reach us : soeng@csit2024.org or soengconf@yahoo.com","date_start":"2024-06-22","date_end":"2024-06-23","important_dates":{"abstract":"","full":"2024-05-04","notification":"","final":""},"topics":["Engineering & Technology","Computer/Informatics","Software Engineering","Multimedia"],"location":{"virtual":"","full":["Sydney","Australia","Australia"],"name":"","street":"","city":"Sydney","state":"Australia","ZIP":"","country":"Australia"},"organizers":["SOENG 2024"],"societies":[],"indexes":[],"emails":["soeng@csit2024.org","soengconf@yahoo.com"]}