{"name":"5th International Conference on Cloud Computing, Security and Blockchain","series":"","short":"CLSB 2024","website":"https://csity2024.org/clsb/index","content":"5th International Conference on Cloud Computing, Security and Blockchain (CLSB 2024) October 19 \\~ 20, 2024, Sydney, Australia https://csity2024.org/clsb/index Scope & Topics 5th International Conference on Cloud Computing, Security and Blockchain (CLSB 2024) will act as a major forum for the presentation of innovative ideas, approaches, developments, and research projects in the areas of Cloud computing, Security and Blockchain. It will also serve to facilitate the exchange of information between researchers and industry professionals to discuss the latest issues and advancement in the area of Cloud Computing, Security and Blockchain. Authors are solicited to contribute to the conference by submitting articles that illustrate research results, projects, surveying works and industrial experiences that describe significant advances in the following areas, but are not limited to. Topics of interest include, but are not limited to, the following Cloud Computing • Case Studies and Theories in Cloud Computing • Cloud Application, Infrastructure and Platforms • Cloud Applications in Vertical Industries • Cloud Based, Parallel Processing • Cloud Business • Cloud Computing Architecture • Cloud Storage and File Systems • Consolidation NoSQL Data Stores • Data storage and Management in Cloud Computing • Design Tool for Cloud Computing • Energy Management and Programming Environments • HPC on Cloud • Location Based Services, Presence, Availability and Locality • Maintenance and Management of Cloud Computing • Map Reduce Techniques & Applications • Networks within Cloud systems, the Storage Area, and to the Outside Virtualization in the Context of Cloud Computing Platforms • Performance, SLA Management and Enforcement • Resource Provisioning • Service-Oriented Architecture in Cloud Computing • Social Clouds (Social Networks in the Cloud) • System Integration, Virtual Compute Clusters • The Open Cloud: Cloud Computing and Open Source • Virtualization on Platforms in the Cloud Security • Agent Based Trust Management • Authorization, Authentication and Identity Management • Cloud Integrity and Binding Issues • Cloud, P2P, Clusters and Grid Computing: Security and Role of Trust • Cryptographic primitives • Pervasive Computation Trust • Security Techniques for the Cloud • Trust and Reputation Management • Trust in Service-Oriented Architecture- Open Architecture and Services • Trust Management for virtual organizations • Trust Management system for Cloud • Trust, Security, Privacy, Policy management in cloud Blockchain • Blockchain Attacks on Existing Systems • Blockchain Authentication and authorization • Blockchain based security for the IoT • Blockchain Consensus Algorithms • Blockchain Foundations • Blockchain in digital forensic • Blockchain issues and trends • Blockchain New Design • Blockchain Privacy • Blockchain Scalability Paper Submission Authors are invited to submit papers through the conference Submission System by September 14, 2024\\. Submissions must be original and should not have been published previously or be under consideration for publication while being evaluated for this conference. The proceedings of the conference will be published by Computer Science Conference Proceedings in Computer Science & Information Technology (CS & IT) series (Confirmed). Selected papers from CLSB 2024, after further revisions, will be published in the special issue of the following journals. • International Journal of Computer Networks & Communications (IJCNC) - ERA, Scopus, WJCI Indexed • International Journal on Cloud Computing: Services and Architecture (IJCCSA) • International Journal on Web Service Computing (IJWSC) • International Journal of Network Security & Its Applications (IJNSA) - ERA, WJCI Indexed • Information Technology in Industry (ITII) Important Dates • Submission Deadline: September 14, 2024 • Authors Notification: September 30, 2024 • Registration & Camera-Ready Paper Due: October 07, 2024 Contact Us Here's where you can reach us: clsb@csity2024.org (or) clsbcon@yahoo.com For more details, please visit: https://csity2024.org/clsb/index Paper Submission Link: https://csity2024.org/submission/index.php","date_start":"2024-10-19","date_end":"2024-10-20","important_dates":{"abstract":"","full":"2024-09-14","notification":"","final":""},"topics":["Engineering & Technology","Computer/Informatics","Cloud Computing","Blockchain"],"location":{"virtual":"","full":["Sydney","Australia"],"name":"","street":"","city":"Sydney","state":"","ZIP":"","country":"Australia"},"organizers":["CLSB 2024"],"societies":[],"indexes":[],"emails":["clsb@csity2024.org","clsbcon@yahoo.com"]}