{"name":"15th International Conference on Internet Engineering & Web Services (InWeS 2024)","series":"","short":"","website":"https://inwes2024.org","content":"15th International Conference on Internet Engineering & Web Services (InWeS 2024) June 29 \\~ 30, 2024, Copenhagen, Denmark https://inwes2024.org/ Scope 15th International Conference on Internet Engineering & Web Services (InWeS 2024) will provide an excellent international forum for sharing knowledge and results in theory, methodology and applications of Internet Engineering & Web services environment. Current information age is witnessing a dramatic use of digital and electronic devices in the workplace and beyond. Internet Engineering & Web services present a rather arduous requirement of robustness, reliability and availability to the end user. Internet Engineering & Web services has received a significant and sustained research interest in terms of designing and deploying large scale and high performance computational applications in real life. The aim of the conference is to provide a platform to the researchers and practitioners from both academia as well as industry to meet and share cutting-edge development in the field. Topics of Interest • Architectures and Frameworks • Coding and Compression • Collaborative Systems & Techniques • Distance Learning • E-business Modeling and Applications • E-commerce Applications • Fault Tolerance • Information Retrieval • Internet Architecture Design • Internet of Things (IoT) • Internet Search Methods • Internet Security & Applications • Knowledge-Based Web Systems • Multimedia Web Tools, Architectures, and Broadcasting • Ontology and Web services • Optimization Methods • Security and Protection • Semantic Web • Software Agents • Web Data Mining and Database Management • Web Java-based Applications • Web Languages • Web Service Applications & Foundation • Web Services-Driven Business Process Management • Wireless & Mobile Based Applications, Services Paper Submission Authors are invited to submit papers through the conference Submission System by June 15, 2024 (Final Call). Submissions must be original and should not have been published previously or be under consideration for publication while being evaluated for this conference. The proceedings of the conference will be published by Computer Science Conference Proceedings in Computer Science & Information Technology (CS & IT) series (Confirmed). Selected papers from InWeS 2024, after further revisions, will be published in the special issue of the following journals. • International Journal of Web & Semantic Technology (IJWesT) - IS Indexed • International Journal on Web Service Computing (IJWSC) • International Journal on Cloud Computing: Services and Architecture (IJCCSA) • Information Technology in Industry (ITII) Important Dates • Submission Deadline: June 15, 2024 (Final Call) • Authors Notification: June 25, 2024 • Registration & Camera-Ready Paper Due: June 27, 2024 Contact Us Here's where you can reach us: inwes@inwes2024.org (or) inwesconference@gmail.com For more details, please visit: https://inwes2024.org/ Paper Submission Link: https://inwes2024.org/submission/index.php","date_start":"2024-06-29","date_end":"2024-06-30","important_dates":{"abstract":"","full":"2024-06-15","notification":"","final":""},"topics":["Engineering & Technology","Computer/Informatics","Internet Of Things (Iot)","Multimedia"],"location":{"virtual":"","full":["Copenhagen","Denmark"],"name":"","street":"","city":"Copenhagen","state":"","ZIP":"","country":"Denmark"},"organizers":["InWeS 2024"],"societies":[],"indexes":[],"emails":["inwes@inwes2024.org","inwesconference@gmail.com"]}