{"name":"5th International Conference on Natural Language Computing and AI","series":"","short":"NLCAI 2024","website":"https://ccsea2024.org/nlcai/index","content":"5th International Conference on Natural Language Computing and AI (NLCAI 2024) May 18 \\~ 19, 2024, Zurich, Switzerland https://ccsea2024.org/nlcai/index Scope 5th International Conference on Natural Language Computing and AI (NLCAI 2024) will provide an excellent international forum for sharing knowledge and results in theory, methodology and applications of Natural Language Computing, and AI. The Conference looks for significant contributions to all major fields of the Natural Language processing and machine learning in theoretical and practical aspects. Authors are solicited to contribute to the conference by submitting articles that illustrate research results, projects, surveying works and industrial experiences that describe significant advances in the areas of Natural Language Computing and AI. Topics of interest include, but are not limited to, the following: • Artificial Intelligence, Deep Learning • Big Data and Data Mining • Chunking/Shallow Parsing • Dialog Systems • Discourse • Information Extraction / Retrieval • Lexical Semantics • Linguistic Resources • Machine Learning for NLP • Machine Translation, Cross lingual and Multilingual applications • Natural Language Processing • Ontology • Paraphrasing/Entailment/Generation • Phonology,Morpholog • POS Tagging • Question Answering • Semantic Processing • Social Media and Social Network Analysis • Spoken Language Processing Speech Generation and Recognition • Statistical and Knowledge based Methods • Text Mining Paper Submission Authors are invited to submit papers through the conference Submission System by May 04, 2024\\. Submissions must be original and should not have been published previously or be under consideration for publication while being evaluated for this conference. The proceedings of the conference will be published by Computer Science Conference Proceedings in Computer Science & Information Technology (CS & IT) series (Confirmed). Selected papers from NLCAI 2024, after further revisions, will be published in the special issues of the following journals • International Journal on Natural Language Computing (IJNLC) • International Journal of Web & Semantic Technology (IJWesT) - IS Indexed • Machine Learning and Applications: An International Journal (MLAIJ) • International Journal of Computer Science & Information Technology (IJCSIT) - INSPEC, WJCI Indexed • International Journal of Artificial Intelligence & Applications (IJAIA) Important Dates Submission Deadline : May 04, 2024 Authors Notification : May 15, 2024 Registration & Camera-Ready Paper Due : May 17, 2024 Contact Us Here's where you can reach us : nlcai@ccsea2024.org or nlcaiconf@yahoo.com Paper Submission Link https://ccsea2024.org/submission/index.php","date_start":"2024-05-18","date_end":"2024-05-19","important_dates":{"abstract":"","full":"2024-04-05","notification":"","final":""},"topics":["Engineering & Technology","Computer/Informatics","Natural Language Processing"],"location":{"virtual":"","full":["Zurich","Switzerland"],"name":"","street":"","city":"Zurich","state":"","ZIP":"","country":"Switzerland"},"organizers":["NLCAI"],"societies":[],"indexes":[],"emails":["nlcai@ccsea2024.org","nlcaiconf@yahoo.com"]}