{"name":"16th International Conference on Computer Networks & Communications (CoNeCo 2024)","series":"","short":"","website":"https://acsit2024.org/coneco/index","content":"16th International Conference on Computer Networks & Communications (CoNeCo 2024) April 27 \\~ 28, 2024, Copenhagen, Denmark https://acsit2024.org/coneco/index Scope 16th International Conference on Computer Networks & Communications (CoNeCo2024)looks for significant contributions to the Computer Networks & Communications for Wired and Wireless Networks in theoretical and practical aspects. Original papers are invited on Computer Networks, Network Protocols and Wireless Networks, Data Communication Technologies, and Network Security. The goal of this Conference is to bring together researchers and practitioners from academia and industry to focus on advanced networking concepts and establishing new collaborations in these areas. Authors are solicited to contribute to the conference by submitting articles that illustrate research results, projects, surveying works and industrial experiences that describe significant advances in Computer Networks & Communications. Topics of interest include, but are not limited to, the following • 5G/6G Cellular Systems and Heterogeneous Networks • Adhoc and Sensor Networks • Big Data / IoT Analytics in Networking • Blockchain and Distributed Ledger • Cloud Computing • Heterogeneous Wireless Networks • High speed Networks • Information / Content centric networks (ICN) • Internet and Web Applications • Internet Measurement and Modeling • Internet of Things (IoT) • Machine Learning and AI in Networking • Measurement & Performance Analysis • Mobile & Broadband Wireless Internet • Mobile Networks & Wireless LAN • Modeling and Simulation • Network Architectures • Network Based Applications • Network Operations & management • Network Protocols & Wireless Networks • Network Security • Next Generation Internet • Next Generation Web Architectures • Peer to peer and Overlay Networks • QoS and Resource Management • Recent trends & Developments in Computer Networks • Routing, Switching and Addressing Techniques • Self-Organizing Networks and Networked Systems • Software-defined networking (SDN) and network virtualization • Ubiquitous Networks • Vehicle-to-everything (V2X) and autonomous cars • Vehicular Networks & Intelligent Transportation • VR/AR Streaming • Wireless Communications • Wireless Multimedia Systems Paper Submission Authors are invited to submit papers through the conference Submission System by April 13, 2024 (Final Call). Submissions must be original and should not have been published previously or be under consideration for publication while being evaluated for this conference. The proceedings of the conference will be published by Computer Science Conference Proceedings in Computer Science & Information Technology (CS & IT) series (Confirmed). Selected papers from CoNeCo 2024, after further revisions, will be published in the special issue of the following journal. • International Journal of Wireless & Mobile Networks (IJWMN) - ERA, WJCI Indexed • International Journal of Computer Networks & Communications (IJCNC) - ERA, WJCI, Scopus Indexed • International Journal of Network Security & Its Applications (IJNSA) - ERA, WJCI Indexed • International Journal of Next-Generation Networks (IJNGN) • Machine Learning and Applications: An International Journal (MLAIJ) Important Dates • Submission Deadline : April 13, 2024 (Final Call) • Authors Notification : April 18, 2024 • Registation& Camera – Ready Paper Due :April 20, 2024 Contact Us Here's where you can reach us : coneco@acsit2024.org (or) conecoconference@gmail.com Paper Submission Link : https://acsit2024.org/submission/index.php","date_start":"2024-04-27","date_end":"2024-04-28","important_dates":{"abstract":"","full":"2024-04-13","notification":"","final":""},"topics":["Engineering & Technology","Computer/Informatics","Networks & Communications","Networks"],"location":{"virtual":"","full":["Copenhagen","Denmark"],"name":"","street":"","city":"Copenhagen","state":"","ZIP":"","country":"Denmark"},"organizers":["CoNeCo 2024"],"societies":[],"indexes":[],"emails":["coneco@acsit2024.org","conecoconference@gmail.com"]}