{"name":"5th International Conference on Big Data and Machine Learning","series":"","short":"BDML 2024","website":"https://ccsea2024.org/bdml/index","content":"5th International Conference on Big Data and Machine Learning (BDML 2024) May 18 \\~ 19, 2024, Zurich, Switzerland https://ccsea2024.org/bdml/index Scope & Topics 5th International Conference on Big Data and Machine Learning (BDML 2024) will act as a major forum for the presentation of innovative ideas, approaches, developments, and research projects in the areas of Big Data and Machine Learning. It will also serve to facilitate the exchange of information between researchers and industry professionals to discuss the latest issues and advancement in the area of Big Data and Machine Learning. Authors are solicited to contribute to the conference by submitting articles that illustrate research results, projects, surveying works and industrial experiences that describe significant advances in Big Data and Machine Learning. Topics of interest include, but are not limited to the following Big Data  Big Data Techniques, models and algorithms  Big Data Infrastructure and platform  Big Data Search and Mining  Big Data Security, Privacy and Trust  Big Data Applications, Bioinformatics, Multimedia etc  Big Data Tools and systems  Big Data Mining  Big Data Management  Cloud and grid computing for Big Data  Machine Learning and AI for Big Data  Big Data Analytics and Social Media  5G and Networks for Big Data Machine Learning  Machine Learning Applications  Learning in knowledge-intensive systems  Learning Methods and analysis  Learning Problems  Deep Learning Paper Submission Authors are invited to submit papers through the conference Submission System by May 04, 2024\\. Submissions must be original and should not have been published previously or be under consideration for publication while being evaluated for this conference. The proceedings of the conference will be published by Computer Science Conference Proceedings in Computer Science & Information Technology (CS & IT) series (Confirmed). Selected papers from BDML 2024, after further revisions, will be published in the special issues of the following journals • International Journal of Data Mining & Knowledge Management Process (IJDKP) - WJCI Indexed • International Journal of Database Management Systems (IJDMS) - WJCI Indexed • Machine Learning and Applications: An International Journal (MLAIJ) • Advances in Vision Computing: An International Journal (AVC) • International Journal of Grid Computing & Applications (IJGCA) • Information Technology in Industry (ITII) Important Dates Second Batch : (Submissions after April 06, 2024) • Submission Deadline : May 04, 2024 • Authors Notification : May 15, 2024 • Registration & camera - Ready Paper Due : May 17, 2024 Contact Us Here's where you can reach us : bdml@ccsea2024.org or bdmlconf@yahoo.com For other details: https://ccsea2024.org/bdml/index Paper Submission Link: https://ccsea2024.org/submission/index.php","date_start":"2024-05-18","date_end":"2024-05-19","important_dates":{"abstract":"","full":"2024-05-04","notification":"","final":""},"topics":["Engineering & Technology","Other","Machine Learning","Big Data Mining & Analysis"],"location":{"virtual":"","full":["Zurich","Switzerland","Switzerland"],"name":"","street":"","city":"Zurich","state":"Switzerland","ZIP":"","country":"Switzerland"},"organizers":["BDML"],"societies":[],"indexes":[],"emails":["bdml@ccsea2024.org","bdmlconf@yahoo.com"]}