{"name":"16th International Conference on Wireless & Mobile Networks (WiMoNe 2024)","series":"","short":"","website":"https://cseit2024.org/wimone/index","content":"16th International Conference on Wireless & Mobile Networks (WiMoNe 2024) July 27 \\~ 28, 2024, London, United Kingdom https://cseit2024.org/wimone/index Scope 16th International Conference on Wireless & Mobile Networks (WiMoNe 2024) International Conference on Wireless & Mobile Networks (WiMoNe 2024) will provide an excellent international forum for sharing knowledge and results in theory, methodology and applications of Wireless & Mobile computing Environment. Current information age is witnessing a dramatic use of digital and electronic devices in the workplace and beyond. Wireless, Mobile Networks & its applications had received a significant and sustained research interest in terms of designing and deploying large scale and high performance computational applications in real life. The aim of the conference is to provide a platform to the researchers and practitioners from both academia as well as industry to meet and share cutting-edge development in the field. Authors are solicited to contribute to the conference by submitting articles that illustrate research results, projects, surveying works and industrial experiences that describe significant advances in the following areas, but are not limited to. Topics of Interest Include, But Are Not Limited To, The Following  Algorithms and Modeling for Tracking and Locating Mobile Users  Architectures, Protocols, and Algorithms to Cope with Mobile & Wireless Networks  Broadband Access Networks  Complexity Analysis of Algorithms for Mobile Environments  Cryptography, Security and Privacy of Mobile & Wireless Networks  Data Management on Mobile and Wireless Computing  Distributed Algorithms of Mobile Computing  Energy Saving Protocols for Ad Hoc and Sensor Networks  Information Access in Wireless Networks  Integration of Wired and Wireless Networks  Mobile Ad Hoc and Sensor Networks  Mobile Applications, Location-Dependent and Sensitive Applications  Nomadic Computing, Applications and Services Supporting the Mobile User  OS and Middleware Support for Mobile Computing and Networking  Performance of Mobile and Wireless Networks and Systems  Recent Trends in Mobile and Wireless Applications  Resource Management in Mobile, Wireless and Ad-Hoc Networks  Routing, and Communication Primitives in Ad Hoc and Sensor Networks  Satellite Communications  Service Creation and Management Environments for Mobile/Wireless Systems  Synchronization and Scheduling Issues in Mobile and Ad Hoc Networks  Ubiquitous Computing  Wireless & Mobile Issues Related to OS  Wireless Multimedia Systems  Wireless, Mobile Networks & Applications Paper Submission Authors are invited to submit papers through the conference Submission System by July 13, 2024\\. Submissions must be original and should not have been published previously or be under consideration for publication while being evaluated for this conference. The proceedings of the conference will be published by Computer Science Conference Proceedings in Computer Science & Information Technology (CS & IT) series (Confirmed). Selected papers from WiMoNe 2024, after further revisions, will be published in the special issue of the following journal.  International Journal of Wireless & Mobile Networks (IJWMN) - ERA, WJCI Indexed  International Journal of Computer Networks & Communications (IJCNC) - Scopus, ERA, WJCI Indexed  International Journal of Network Security & Its Applications (IJNSA) - ERA, WJCI Indexed  International Journal of Security, Privacy and Trust Management ( IJSPTM )  International Journal on Cryptography and Information Security (IJCIS)  Information Technology in Industry (ITII) Contact Us Here's where you can reach us : wimone@cseit2024.org (or) wimone\\_conf@yahoo.com","date_start":"2024-07-27","date_end":"2024-07-28","important_dates":{"abstract":"","full":"2024-07-13","notification":"","final":""},"topics":["Engineering & Technology","Computer/Informatics","Networks","Networks & Communications"],"location":{"virtual":"","full":["London","United Kingdom"],"name":"","street":"","city":"London","state":"","ZIP":"","country":"United Kingdom"},"organizers":["WIMONE 2024"],"societies":[],"indexes":[],"emails":["wimone@cseit2024.org","_conf@yahoo.com"]}