{"name":"5th International Conference on Cloud, Big Data and Web Services","series":"","short":"CBW 2024","website":"https://icaita2024.org/cbw/index","content":"5th International Conference on Cloud, Big Data and Web Services (CBW 2024) May 25 \\~ 26, 2024, Vancouver, Canada https://icaita2024.org/cbw/index Scope 5th International Conference on Cloud, Big Data and Web Services (CBW 2024) will act as a major forum for the presentation of innovative ideas, approaches, developments, and research projects in the areas of Cloud, Big Data and Web services. It will also serve to facilitate the exchange of information between researchers and industry professionals to discuss the latest issues and advancement in the area of Cloud, Big Data and web services. Authors are solicited to contribute to the conference by submitting articles that illustrate research results, projects, surveying works and industrial experiences that describe significant advances in the following areas, but are not limited to. Topics Of Interest • 5G and Networks for Big Data • Big Data • Big Data Analytics and Social Media • Big Data Applications, Bioinformatics, Multimedia etc • Big Data Infrastructure and platform • Big Data Management • Big Data Mining • Big Data Search and Mining • Big Data Security, Privacy and Trust • Big Data Techniques, models and algorithms • Big Data Tools and systems • Business Service Systems Theory and Models • Case Studies and Theories in Cloud Computing • Cloud and grid computing for Big Data • Cloud Application, Infrastructure and Platforms • Cloud Applications in Vertical Industries • Cloud Based, Parallel Processing • Cloud Business • Cloud Computing • Cloud Storage and File Systems • Cluster, Grid, Utility and Cloud Computing Models and Systems • Consolidation NoSQL Data Stores • Data storage and Management in Cloud Computing • Design Tool for Cloud Computing • Empirical Studies on Web Service Computing • Energy Management and Programming Environments • Evaluation and Quality Models of Web Service Computing • Knowledge and Semantic Approaches Web and Business Service Domains • Location Based Services, Presence, Availability, and Locality • Machine Learning and AI for Big Data • Maintenance and Management of Cloud Computing Cloud Computing Architecture • Mobile Clouds for New Millennium, Mobile Devices • Networks within Cloud systems, the Storage Area, and to the Outside Virtualization in the Context of Cloud Computing • Other Related Topics • Performance, SLA Management and Enforcement • Platforms • Qualitative and Quantitative Studies and Analysis on Web Service Systems • Resource Provisioning • Security Techniques for the Cloud • Service Oriented Architecture Models and Systems • Service-Oriented Architecture in Cloud Computing • Simulations and Developments of Web Service Computing Systems • Social Clouds (Social Networks in the Cloud) • System Integration, Virtual Compute Clusters • The Open Cloud: Cloud Computing and Open Source • Tools and Technologies for Web Service Computing • Uncertainty Issues and Studies in Web Service Practices and Systems • Virtualization on Platforms in the Cloud • Web and Business Information Services and Systems • Web Service Computing Metrics and Standards • Web Service Computing Theory and Models • Web Service Domain Specific Case Studies and Application Systems • Web Services Paper Submission Authors are invited to submit papers through the conference Submission System by May 04, 2024\\. Submissions must be original and should not have been published previously or be under consideration for publication while being evaluated for this conference. The proceedings of the conference will be published by Computer Science Conference Proceedings in Computer Science & Information Technology (CS & IT) series (Confirmed). Selected papers from CBW 2024, after further revisions, will be published in the special issue of the following journals • International Journal on Cloud Computing: Services and Architecture (IJCCSA) • International Journal on Web Service Computing (IJWSC) • International Journal of Grid Computing & Applications (IJGCA) • International Journal of Data Mining & Knowledge Management Process (IJDKP) – WJCI Indexed Important Dates Second Batch ; Submission After April 06, 2024 • Submission Deadline : May 04, 2024 • Authors Notification : May 18, 2024 • Registration & Camera-Ready Paper Due : May 21, 2024 Contact Us Here's where you can reach us : cbw@icaita2024.org or cbwconf@yahoo.com Submission System ; https://icaita2024.org/submission/index.php For More Information Please Visit ; https://icaita2024.org/cbw/index","date_start":"2024-05-25","date_end":"2024-05-26","important_dates":{"abstract":"","full":"2024-05-04","notification":"","final":""},"topics":["Engineering & Technology","Computer/Informatics","Data Mining"],"location":{"virtual":"","full":["Vancouver","Canada"],"name":"","street":"","city":"Vancouver","state":"","ZIP":"","country":"Canada"},"organizers":["CBW 2024"],"societies":[],"indexes":[],"emails":["cbw@icaita2024.org","cbwconf@yahoo.com"]}