{"name":"5th International Conference on Machine Learning Techniques and Data Science","series":"","short":"MLDS 2024","website":"https://www.iccsea2024.org/mlds/index","content":"5th International Conference on Machine Learning Techniques and Data Science (MLDS 2024) November 16 \\~ 17, 2024, Zurich, Switzerland https://www.iccsea2024.org/mlds/index Scope 5th International Conference on Machine Learning Techniques and Data Science (MLDS 2024) will provide an excellent international forum for sharing knowledge and results in theory, methodology and applications of Machine Learning Techniques and Data Science. Topics of interest include, but are not limited to, the following • Machine Learning • Deep Learning • Learning in knowledge-intensive systems • Learning Methods and analysis • Learning Problems • Machine Learning Applications • Machine Learning models and applications • Machine Learning Recommender systems • Machine Translation • Neural Networks / Deep Learning • Data Science • Big Data • Business Data • Data Analytics • Data Management • Data Mining • Data Science and Machine Learning • Databases • Forecasting • Hybrid Machine Learning Systems for Data Science • Natural Language Processing • Social Network Analysis • Time Series Analysis Paper Submission Authors are invited to submit papers through the conference Submission System by October 12, 2024\\. Submissions must be original and should not have been published previously or be under consideration for publication while being evaluated for this conference. The proceedings of the conference will be published by Computer Science Conference Proceedings in Computer Science & Information Technology (CS & IT) series (Confirmed). Selected papers from MLDS 2024, after further revisions, will be published in the special issue of the following journal.  International Journal of Artificial Intelligence & Applications (IJAIA)  Machine Learning and Applications: An International Journal (MLAIJ)  International Journal of Data Mining & Knowledge Management Process ( IJDKP ) - WJCI Indexed  International Journal of Database Management System (IJDMS) - WJCI Indexed  Information Technology in Industry (ITII) Important Dates • Submission Deadline : October 12, 2024 • Authors Notification : October 31, 2024 • Registration & camera - Ready Paper Due : November 05, 2024 Contact Us Here's where you can reach us : mlds@iccsea2024.org (or) mldsconf@gmail.com","date_start":"2024-11-16","date_end":"2024-11-17","important_dates":{"abstract":"","full":"2024-10-12","notification":"","final":""},"topics":["Engineering & Technology","Computer/Informatics","Machine Learning","Data Science"],"location":{"virtual":"","full":["zurich","Zurich","Switzerland Swaziland"],"name":"","street":"","city":"zurich","state":"Zurich","ZIP":"","country":"Switzerland Swaziland"},"organizers":["MLDS"],"societies":[],"indexes":[],"emails":["mlds@iccsea2024.org","mldsconf@gmail.com"]}