{"name":"4th International Conference on Cryptography and Blockchain","series":"","short":"CRBL 2024","website":"https://comit2024.org/crbl/index","content":"4th International Conference on Cryptography and Blockchain (CRBL 2024) August 17 \\~ 18, 2024, Chennai, India https://comit2024.org/crbl/index Scope & Topics 4th International Conference on Cryptography and Blockchain (CRBL 2024) will act as a major forum for the presentation of innovative ideas, approaches, developments, and research projects in the areas of Cryptography and Blockchain. It will also serve to facilitate the exchange of information between researchers and industry professionals to discuss the latest issues and advancement in the area of Cryptography and Blockchain. Authors are solicited to contribute to the conference by submitting articles that illustrate research results, projects, surveying works and industrial experiences that describe significant advances in the areas of software engineering formal method advances. Topics of interest include, but are not limited to, the following • Access Control and Intrusion Detection • Artificial Immune Systems • Authentication • Authentication and Non-repudiation • Autonomy-Oriented Computing • Biological & Evolutionary Computation • Biometric Security • Blockchain Attacks on Existing Systems • Blockchain Consensus Algorithms • Blockchain Foundations • Blockchain in digital forensic • BlockChain issues and trends • Blockchain New Design • Blockchain Privacy • Blockchain Scalability • Blockchain Authentication and authorization • Blockchain based security for the IoT • Coevolutionary Algorithms • Computational Intelligence in Security • Cryptographic protocols • Cryptography and Coding • Data & System Integrity • E- Commerce • Data Integrity • Fuzzy Systems • Identification and Authentication • Information Hiding • Insider Threats and Countermeasures • Intelligent Agents and Systems • Intrusion Detection & Prevention • Intrusion Detection and Vulnerability Assessment • Key management • Models for Authentication, Trust and Authorization • Privacy and authentication • Quantum cryptography • Regulation and Trust Mechanisms • Reinforcement & Unsupervised Learning • Secure Cloud Computing • Security and Privacy in Mobile Systems • Security and Privacy in Pervasive/Ubiquitous Computing • Security and Privacy in Web Services • Security and Privacy Policies • Security Area Control • Security Deployment • Security Engineering • Security for Grid Computing • Security in Distributed Systems • Security Information Systems Architecture and Design and Security Patterns • Security Management • Security Requirements (threats, vulnerabilities, risk, formal methods, etc.) • Sensor and Mobile Ad Hoc Network Security • Service and Systems Design and QoS Network Security • Software Security • Trust Management • Trust models and metrics • Untraceability Paper Submission Authors are invited to submit papers through the conference Submission System by August 03, 2024 (Final Call). Submissions must be original and should not have been published previously or be under consideration for publication while being evaluated for this conference. The proceedings of the conference will be published by Computer Science Conference Proceedings in Computer Science & Information Technology (CS & IT) series (Confirmed). Selected papers from CRBL 2024, after further revisions, will be published in the special issue of the following journals. • International Journal of Wireless & Mobile Networks (IJWMN) - ERA, WJCI Indexed • International Journal of Computer Networks & Communications (IJCNC) - Scopus, ERA, WJCI Indexed • International Journal on Cryptography and Information Security (IJCIS) • International Journal of Security, Privacy and Trust Management (IJSPTM) • International Journal of Network Security & Its Applications (IJNSA) - WJCI, ERA Indexed • Information Technology in Industry (ITII) Important Dates • Submission Deadline: August 03, 2024 (Final Call) • Authors Notification: August 10, 2024 • Registration & Camera-Ready Paper Due: August 13, 2024 Contact Us Here\\`s where you can reach us: crbl@comit2024.org (or) crblconference@gmail.com For more details, please visit: https://comit2024.org/crbl/index Paper Submission Link: https://comit2024.org/submission/index.php","date_start":"2024-08-17","date_end":"2024-08-18","important_dates":{"abstract":"","full":"2024-08-03","notification":"","final":""},"topics":["Engineering & Technology","Computer/Informatics","Cryptography","Blockchain"],"location":{"virtual":"","full":["Chennai","India"],"name":"","street":"","city":"Chennai","state":"","ZIP":"","country":"India"},"organizers":["CRBL 2024"],"societies":[],"indexes":[],"emails":["crbl@comit2024.org","crblconference@gmail.com"]}