{"name":"8th International Conference on Networks and Communications","series":"","short":"NET 2024","website":"https://aisca2024.org/net/index","content":"8th International Conference on Networks and Communications (NET 2024) February 17 \\~ 18, 2024, Dubai, UAE https://aisca2024.org/net/index Scope 8th International Conference on Networks and Communications (NET 2024) looks for significant contributions to the Computer Networks, Communications, wireless and mobile computing for wired and wireless networks in theoretical and practical aspects. Original papers are invited on computer Networks, network protocols and wireless networks, Data communication Technologies, network security and mobile computing. Authors are solicited to contribute to this conference by submitting articles that illustrate research results, projects, surveying works and industrial experiences that describe significant advances in the following areas, but are not limited to. Topics of interest include, but are not limited to, the following • 5G/6G Cellular Systems and Heterogeneous Networks • Big Data / IoT Analytics in Networking • Blockchain and Distributed Ledger • Communication Network Architectures, Protocols and Design • Emerging Technologies for Next Generation Network • Energy Saving Protocols for Ad hoc and Sensor Networks • Future Internet Architecture, Protocols and Services • Information / Content centric networks (ICN) • Internet Measurement and Modeling • Internet of Things (IoT) • Machine Learning and AI in Networking • Mobile Ad hoc and Sensor networks • Mobile and Wireless Networks • Network Applications, Operation and Management • Network Security and Privacy • Network Services and Applications • Nomadic Computing, Applications and Services Supporting the Mobile User • OS and Middleware Support for Mobile Computing and Networking • Performance of Mobile and Wireless Networks and Systems • Satellite Communications • SDN/NFV and Network Programmability • Software-defined networking (SDN) and network virtualization • Ubiquitous and Cloud Computing • Vehicle-to-everything (V2X) and autonomous cars • Vehicular Networks & Intelligent Transportation • VR/AR Streaming • Wireless Multimedia Systems Paper Submission Authors are invited to submit papers through the conference Submission System by February 03, 2024 (Final Call). Submissions must be original and should not have been published previously or be under consideration for publication while being evaluated for this conference. The proceedings of the conference will be published by Computer Science Conference Proceedings in Computer Science & Information Technology (CS & IT) series (Confirmed). Selected papers from NET 2024, after further revisions, will be published in the special issue of the following journal. • International Journal of Computer Networks & Communications (IJCNC) - Scopus, ERA, WJCI Indexed • International Journal of Network Security & Its Applications (IJNSA) - ERA,WJCI Indexed • International Journal on Applications of Graph Theory in Wireless Ad hoc Networks and Sensor Networks (GRAPH-HOC) • International Journal of Next-Generation Networks (IJNGN) • International Journal of Distributed and Parallel systems (IJDPS) • International Journal of Peer to Peer Networks (IJP2P) • International Journal of Grid Computing & Applications (IJGCA) • Information Technology in Industry (ITII) Important Dates • Submission Deadline : February 03, 2024 (Final Call) • Authors Notification : February 14, 2024 • Registation & Camera – Ready Paper Due : February 15, 2024 Contact Us Here's where you can reach us net@aisca2024.org or netconf@yahoo.com Paper Submission Link : https://aisca2024.org/submission/index.php","date_start":"2024-02-17","date_end":"2024-02-18","important_dates":{"abstract":"","full":"2024-02-03","notification":"","final":""},"topics":["Engineering & Technology","Other","Networks","Networks & Communications"],"location":{"virtual":"","full":["Dubai","United Arab Emirates"],"name":"","street":"","city":"Dubai","state":"","ZIP":"","country":"United Arab Emirates"},"organizers":["NET"],"societies":[],"indexes":[],"emails":["net@aisca2024.org","netconf@yahoo.com"]}