{"name":"5th International Conference on Data Science and Machine Learning","series":"","short":"DSML 2024","website":"https://csen2024.org/dsml/index","content":"5th International Conference on Data Science and Machine Learning (DSML 2024) December 21 \\~ 22, 2024, Sydney, Australia https://csen2024.org/dsml/index Scope & Topics 5th International Conference on Data Science and Machine Learning (DSML 2024) will act as a major forum for the presentation of innovative ideas, approaches, developments, and research projects in the areas of Data Science and Machine Learning. It will also serve to facilitate the exchange of information between researchers and industry professionals to discuss the latest issues and advancement in the area of Data Science and Machine Learning. Topics of interest include, but are not limited to, the following Data Mining • Parallel and Distributed Data Mining Algorithms • Data Streams Mining, Graph Mining, Spatial Data Mining • Text video, Multimedia Data Mining, Web Mining • Pre-Processing Techniques, Visualization • Security and Information Hiding in Data Mining • Data mining Applications Databases • Bioinformatics • Biometrics • Image Analysis • Financial Modeling • Forecasting, Classification, Clustering • Cryptography and Information security • Social Networks, Educational Data Mining Big Data • Big Data Algorithms • Big Data Fundamentals • Infrastructures for Big Data • Big Data Management and Frameworks • Big Data Search • Big Data security • Big Data Applications • Data Mining & Machine learning Tasks • Machine Learning Applications • Learning in knowledge-intensive systems • Learning Methods and analysis • Learning Problems Deep Learning • Knowledge Processing • Data and Knowledge Representation • Knowledge Discovery Framework and Process, Including Pre- and Post-Processing • Integration of Data Warehousing • OLAP and Data Mining • Inference of Causes, Prediction, Evaluating, Consolidating and Explaining Discovered Knowledge • Integrating Constraints and Knowledge in the KDD Process • Exploring Data Analysis • Statistical Techniques for Generation a Robust • Consistent Data Model • Interactive Data Exploration / Visualization and Discovery • Languages and Interfaces for Data Mining • Mining Trends, Opportunities and Risks Paper Submission Authors are invited to submit papers through the conference Submission System by November 02, 2024\\. Submissions must be original and should not have been published previously or be under consideration for publication while being evaluated for this conference. The proceedings of the conference will be published by Computer Science Conference Proceedings in Computer Science & Information Technology (CS & IT) series (Confirmed). Selected papers from DSML 2024, after further revisions, will be published in the special issue of the following journals. • International Journal of Database Management Systems (IJDMS) - WJCI Indexed • International Journal of Data Mining & Knowledge Management Process (IJDKP) - WJCI Indexed • Machine Learning and Applications: An International Journal (MLAIJ) • International Journal of Web & Semantic Technology (IJWesT) Contact Us Here's where you can reach us: dsml@csen2024.org (or) dsmlconfe@yahoo.com For more details, please visit: https://csen2024.org/dsml/index Paper Submission Link: https://csen2024.org/submission/index","date_start":"2024-12-21","date_end":"2024-12-22","important_dates":{"abstract":"","full":"2024-11-02","notification":"","final":""},"topics":["Engineering & Technology","Computer/Informatics","Data Science","Machine Learning"],"location":{"virtual":"","full":["Sydney","Australia"],"name":"","street":"","city":"Sydney","state":"","ZIP":"","country":"Australia"},"organizers":["DSML 2024"],"societies":[],"indexes":[],"emails":["dsml@csen2024.org","dsmlconfe@yahoo.com"]}