{"name":"10th International Conference on Artificial Intelligence and Soft Computing","series":"","short":"AIS 2024","website":"https://csit2024.org/ais/index","content":"10th International Conference on Artificial Intelligence and Soft Computing (AIS 2024) June 22 \\~ 23, 2024, Sydney, Australia https://csit2024.org/ais/index Call for Papers 10th International Conference on Artificial Intelligence and Soft Computing (AIS 2024) will provide an excellent international forum for sharing knowledge and results in theory, methodology, and applications of Artificial Intelligence, Soft Computing. The Conference looks for significant contributions to all major fields of the Artificial Intelligence, Soft Computing in theoretical and practical aspects. The aim of the Conference is to provide a platform to the researchers and practitioners from both academia as well as industry to meet and share cutting-edge development in the field. Authors are solicited to contribute to the conference by submitting articles that illustrate research results, projects, surveying works and industrial experiences that describe significant advances in the following areas, but are not limited to. Topics of interest include, but are not limited to, the following: • AI Algorithms • Information Retrieval • Intelligent System Architectures • Knowledge Representation • Knowledge-based Systems • Mechatronics • Multimedia & Cognitive Informatics • Neural Networks • Parallel Processing • Pattern Recognition • Pervasive Computing and Ambient Intelligence • Programming Languages Artificial Intelligence • Soft Computing and Applications • Artificial Intelligence Tools & Applications • Automatic Control • Bioinformatics • Natural Language Processing • CAD Design & Testing • Computer Vision and Speech Understanding • Data Mining and Machine Learning Tools • Multimedia Systems and Services • Fuzzy Logic • Heuristic and AI Planning Strategies and Tools • Computational Theories of Learning • Reasoning and Evolution • Recent Trends and Developments • Robotics • Neural Networks • Machine Learning • Probabilistic Reasoning • Evolutionary Computing • Hybrid Intelligent Systems • Software Agents • Morphic Computing • Image processing • E-commerce, E-medicine • Rough Sets • Symbolic Machine Learning • Wavelet • Signal or Image Processing • Vision Recognition • Biomedical Engineering • Telecommunications • Reactive Distributed AI • Nano & Micro-systems • Data Visualization • Semantic Web Techniques and Technologie • Soft Computing Theory and Applications • Software & Hardware Architectures • Web Intelligence Applications & Search Paper Submission Authors are invited to submit papers through the conference Submission System by May 04, 2024\\. Submissions must be original and should not have been published previously or be under consideration for publication while being evaluated for this conference. The proceedings of the conference will be published by Computer Science Conference Proceedings in Computer Science & Information Technology (CS & IT) series (Confirmed). Selected papers from AIS 2024, after further revisions, will be published in the special issue of the following journal.  International Journal of Soft Computing (IJSC)  International Journal of Artificial Intelligence & Applications (IJAIA)  Information Technology in Industry (ITII) Important Dates Second Batch : (Submissions after April 06, 2024) • Submission Deadline : May 04, 2024 • Authors Notification : June 11, 2024 • Registration & Camera-Ready Paper Due : June 15, 2024 Contact Us Here's where you can reach us: ais@csit2024.org(or aisconf@yahoo.com Submission Link: https://csit2024.org/submission/index.php","date_start":"2024-06-22","date_end":"2024-06-23","important_dates":{"abstract":"","full":"2024-05-04","notification":"","final":""},"topics":["Engineering & Technology","Other","Artificial Intelligence","Machine Learning"],"location":{"virtual":"","full":["Sydney","Australia"],"name":"","street":"","city":"Sydney","state":"","ZIP":"","country":"Australia"},"organizers":["AIS 2024"],"societies":[],"indexes":[],"emails":["ais@csit2024.org","aisconf@yahoo.com"]}