{"name":"10th International Conference on Signal and Image Processing","series":"","short":"SIPRO 2024","website":"https://ccsea2024.org/sipro/index","content":"10th International Conference on Signal and Image Processing (SIPRO 2024) May 18 \\~ 19, 2024, Zurich, Switzerland https://ccsea2024.org/sipro/index Scope & Topics 10th International Conference on Signal and Image Processing (SIPRO 2024) is a forum for presenting new advances and research results in the fields of Digital Image Processing. The conference will bring together leading researchers, engineers and scientists in the domain of interest from around the world. The scope of the conference covers all theoretical and practical aspects of the Signal, Image Processing & Pattern Recognition. Authors are solicited to contribute to the conference by submitting articles that illustrate research results, projects, surveying works and industrial experience. Authors are solicited to contribute to the conference by submitting articles that illustrate research results, projects, surveying works and industrial experiences that describe significant advances in the areas of Signal, Image Processing & Pattern Recognition. Topics of interest include, but are not limited to, the following • Image acquisition & Medical Image Processing • Pattern Recognition and Analysis • Visualization • Face Recognition & Super-resolution Imaging • 3D and Stereo Imaging • Application & Others • Image Coding and Compression • Face Recognition & Super-resolution Imaging • Image Segmentation • Face Recognition • 3-D and Surface Reconstruction • Analog and Mixed Signal Processing • Applications (Biomedical, Bioinformatics, Genomic, Seismic, Radar, Sonar, Remote Sensing, Positioning, etc.) • Array Signal Processing • Audio/Speech Processing and Coding • Digital & Mobile Signal Processing • Statistical & Optical Signal Processing • Data Mining Techniques • Motion Detection • Content-based Image retrieval • Video Signal Processing • Watermarking • Detection and Estimation of Signal Parameters • Signal Identification • Nonlinear Signals and Systems • Time-Frequency Signal Analysis • Signal Reconstruction • Spectral Analysis • Sonar Signal Processing and Localization • Speech, Audio and Music Processing • Statistic Learning & Pattern Recognition • Text processing • Filter Design and Structures • FIR, IIR, Adaptive Filters • Signal Noise Control • Multiple Filtering and Filter Banks • Biomedical Imaging Technologies • Biometrics and Pattern Recognition • Cognitive and Biologically-inspired Vision • Color and Texture • Communication Signal Processing • Computer Communication and Networks • Computer Vision & VR • Constraint Processing • Distributed Source Coding • Document Recognition • DSP Implementation and Embedded Systems • Face and Gesture • Hardware Implementation for Signal Processing • Higher Order Spectral Analysis • Illumination and Reflectance Modeling • Image and Video Retrieval • Image Processing & Understanding • Image-Based Modeling • Internet Signal Processing • Knowledge Representation and High-Level Vision • Medical Image Analysis • Multidimensional Signal Processing • Multi-view Geometry • Neural Networks and Genetic Algorithms • Object Detection, Recognition and Categorization • Pattern Recognition in New Modalities • DE for Image Processing • Performance Evaluation • Radar Signal Processing • Remote Sensing • Segmentation • Sensor Array and Multi-channel Processing • Shape Representation • Signal Processing Education • Time-Frequency/Time-Scale Analysis • Video Analysis and Event Recognition • Video compression & Streaming • Video Surveillance and Monitoring Paper Submission Authors are invited to submit papers through the conference Submission System by May 04, 2024 (Final Call). Submissions must be original and should not have been published previously or be under consideration for publication while being evaluated for this conference. The proceedings of the conference will be published by Computer Science Conference Proceedings in Computer Science & Information Technology (CS & IT) series (Confirmed). Selected papers from SIPRO 2024, after further revisions, will be published in the special issues of the following journals. • Signal & Image Processing : An International Journal (SIPIJ) - WJCI Indexed • International Journal of VLSI Design & Communication Systems (VLSICS) • International Journal of Embedded Systems and Applications (IJESA) • International Journal on Organic Electronics (IJOE) • International Journal of Multimedia & Its Applications (IJMA) - ERA, WJCI Indexed • Information Technology in Industry (ITII) Important Dates • Submission Deadline: May 04, 2024 (Final Call) • Authors Notification: May 15, 2024 • Registration & Camera-Ready Paper Due: May 17, 2024 Contact Us Here's where you can reach us: sipro@ccsea2024.org (or) siproconference@gmail.com For more details, please visit: https://ccsea2024.org/sipro/index Paper Submission Link: https://ccsea2024.org/submission/index.php","date_start":"2024-05-18","date_end":"2024-05-19","important_dates":{"abstract":"","full":"2024-05-04","notification":"","final":""},"topics":["Engineering & Technology","Computer/Informatics","Signal Processing","Image Processing"],"location":{"virtual":"","full":["Zurich","Switzerland"],"name":"","street":"","city":"Zurich","state":"","ZIP":"","country":"Switzerland"},"organizers":["SIPRO 2024"],"societies":[],"indexes":[],"emails":["sipro@ccsea2024.org","siproconference@gmail.com"]}