{"name":"5th International Conference on Machine Learning & Trends","series":"","short":"MLT 2024","website":"https://icaita2024.org/mlt/index","content":"5th International Conference on Machine Learning & Trends (MLT 2024) May 25 \\~ 26, 2024, Vancouver, Canada https://icaita2024.org/mlt/index Scope 5th International Conference on Machine Learning & Trends (MLT 2024) will provide an excellent international forum for sharing knowledge and results in theory, methodology and applications of on Machine Learning & its Trends. The aim of the conference is to provide a platform to the researchers and practitioners from both academia as well as industry to meet and share cutting-edge development in the field. Authors are solicited to contribute to the conference by submitting articles that illustrate research results, projects, surveying works and industrial experiences that describe significant advances in the following areas, but are not limited to. Topics of Interest • Applications • Bayesian Network • Computer Vision • Data Mining • Deep Learning • Learning in knowledge-intensive systems • Learning Methods and analysis • Learning Problems • Machine Learning Algorithms • Neural Networks • Predictive Learning • Reinforcement Learning • Supervised Machine Learning • Trends • Unsupervised Machine Learning Paper Submission Authors are invited to submit papers through the conference Submission System by May 04, 2024\\. Submissions must be original and should not have been published previously or be under consideration for publication while being evaluated for this conference. The proceedings of the conference will be published by Computer Science Conference Proceedings in Computer Science & Information Technology (CS & IT) series (Confirmed). Selected papers from MLT 2024, after further revisions, will be published in the special issue of the following journals • Machine Learning and Applications: An International Journal (MLAIJ) • International Journal of Artificial Intelligence & Applications (IJAIA) Important Dates • Submission Deadline : May 04, 2024 • Authors Notification : May 18, 2024 • Registration & Camera-Ready Paper Due : May 21, 2024 Contact Us Here's where you can reach us : mlt@icaita2024.org or mltconfe@yahoo.com Submission System Link : https://icaita2024.org/submission/index.php","date_start":"2024-05-25","date_end":"2024-05-26","important_dates":{"abstract":"","full":"2024-05-04","notification":"","final":""},"topics":["Engineering & Technology","Computer/Informatics","Machine Learning","Artificial Intelligence"],"location":{"virtual":"","full":["","Canada"],"name":"","street":"","city":"","state":"","ZIP":"","country":"Canada"},"organizers":["MLT 2024"],"societies":[],"indexes":[],"emails":["mlt@icaita2024.org","mltconfe@yahoo.com"]}