{"name":"10th International Conference on Image Processing and Pattern Recognition","series":"","short":"IPPR 2024","website":"https://csit2024.org/ippr/index","content":"10th International Conference on Image Processing and Pattern Recognition (IPPR 2024) June 22 \\~ 23, 2024, Sydney, Australia https://csit2024.org/ippr/index Scope 10th International Conference on Image Processing and Pattern Recognition (IPPR 2024) is a forum for presenting new advances and research results in the fields of Digital Image Processing. The Workshop will bring together leading researchers, engineers and scientists in the domain of interest from around the world. The scope of the journal covers all theoretical and practical aspects of the Digital Image Processing & Pattern Recognition, from basic research to development of application. Authors are solicited to contribute to the conference by submitting articles that illustrate research results, projects, surveying works and industrial experiences that describe significant advances in the following areas, but are not limited to. Topics of interest include, but are not limited to, the following • Image Coding and Compression • Face Recognition and Super-Resolution Imaging • Image Segmentation • Face Recognition • 3-D and Surface Reconstruction • 3D and Stereo Imaging • Analog and Mixed Signal Processing • Application and Others • Applications (Biomedical, Bioinformatics, Genomic, Seismic, Radar, Sonar, Remote Sensing, Positioning, etc.) • Array Signal Processing • Audio/Speech Processing and Coding • Digital and Mobile Signal Processing • Statistical and Optical Signal Processing • Data Mining Techniques • Motion Detection • Content-based Image Retrieval • Video Signal Processing • Watermarking • Detection and Estimation of Signal Parameters • Signal Identification • Nonlinear Signals and Systems • Time-Frequency Signal Analysis • Signal Reconstruction • Spectral Analysis • Filter Design and Structures • FIR, IIR and Adaptive Filters • Signal Noise Control • Multiple Filtering and Filter Banks • Biomedical Imaging Technologies • Biometrics and Pattern Recognition • Cognitive and Biologically-Inspired Vision • Color and Texture • Communication Signal processing • Computer Vision & VR • Constraint processing Computer • Communication and Networks • Internet Signal Processing • Knowledge Representation and High-Level Vision • Medical Image Analysis • Motion and Tracking Stereo and Structure from Motion • Multidimensional Signal Processing • Multi-view Geometry • Neural Networks and Genetic Algorithms • Object Detection, Recognition and Categorization • Pattern Recognition in New Modalities • PDE for Image Processing • Performance Evaluation • Radar Signal Processing • Remote Sensing • Segmentation • Sensor Array and Multi-channel Processing • Shape Representation • Signal Processing Education • Sonar Signal Processing and Localization • Speech, Audio and Music Processing • Statistic Learning & Pattern Recognition • Text processing • Time-Frequency/Time-Scale Analysis • Video Analysis and Event Recognition • Video Compression & Streaming • Video Surveillance and Monitoring • Distributed Source Coding • Document Recognition • DSP Implementation and Embedded Systems • Face and Gesture • Hardware Implementation for Signal Processing • Higher Order Spectral Analysis • Illumination and Reflectance Modeling • Image and Video Retrieval Paper Submission Authors are invited to submit papers through the conference Submission System by May 04, 2024 Submissions must be original and should not have been published previously or be under consideration for publication while being evaluated for this conference. The proceedings of the conference will be published by Computer Science Conference Proceedings in Computer Science & Information Technology (CS & IT) series (Confirmed). Selected papers from IPPR 2024, after further revisions, will be published in the special issue of the following journal. • Signal & Image Processing : An International Journal (SIPIJ) - WJCI Indexed • International Journal of VLSI Design & Communication Systems (VLSICS) • International Journal of Embedded Systems and Applications (IJESA) • International Journal on Organic Electronics (IJOE) • Information Technology in Industry (ITII) Important Dates • Submission Deadline : May 04, 2024 • Authors Notification :June 11, 2024 • Registration & Camera – Ready Paper Due : June 15, 2024 Contact Us: Here's where you can reach us: ippr@csit2024.org (or) ipprconf@yahoo.com Paper Submission Link: https://csit2024.org/submission/index.php","date_start":"2024-06-22","date_end":"2024-06-23","important_dates":{"abstract":"","full":"2024-05-04","notification":"","final":""},"topics":["Engineering & Technology","Other","Image Processing","Signal Processing"],"location":{"virtual":"","full":["Sydney","Australia","Australia"],"name":"","street":"","city":"Sydney","state":"Australia","ZIP":"","country":"Australia"},"organizers":["IPPR 2024"],"societies":[],"indexes":[],"emails":["ippr@csit2024.org","ipprconf@yahoo.com"]}