{"name":"9th International Conference on Software Engineering","series":"","short":"SOEN 2024","website":"https://ccsit2024.org/soen/index","content":"9th International Conference on Software Engineering (SOEN 2024) September 21-22, 2024, Copenhagen, Denmark https://ccsit2024.org/soen/index Scope & Topics 9th International Conference on Software Engineering (SOEN 2024) will provide an excellent international forum for sharing knowledge and results in theory, methodology and applications of Software Engineering and Applications. The goal of this Conference is to bring together researchers and practitioners from academia and industry to focus on understanding Modern software engineering concepts and establishing new collaborations in these areas. Authors are solicited to contribute to the conference by submitting articles that illustrate research results, projects, surveying works and industrial experiences that describe significant advances in the following areas, but are not limited to. Topics of interest include, but are not limited to, the following • Advanced Topics in Software Engineering • Knowledge-based Systems and Formal Methods • Languages and Formal Methods • Managing Software Projects • Multimedia and Visual Software Engineering • Quality Management • Search Engines and Information Retrieval • Software Engineering Decision Making • Software Engineering Practice • Software Maintenance and Testing • The Software Process • Web Engineering Paper Submission Authors are invited to submit papers through the conference Submission System by August 10, 2024\\. Submissions must be original and should not have been published previously or be under consideration for publication while being evaluated for this conference. The proceedings of the conference will be published by Computer Science Conference Proceedings in Computer Science & Information Technology (CS & IT) series (Confirmed). Selected papers from SOEN 2024, after further revisions, will be published in the special issues of the following journals. • International Journal of Computer Science & Information Technology (IJCSIT) - INSPEC, WJCI Indexed • International Journal of Software Engineering & Applications (IJSEA) • Information Technology in Industry (ITII) Contact Us Here's where you can reach us : soen@ccsit2024.org (or) soenconf@gmail.com Submission Link: https://ccsit2024.org/submission/index.php","date_start":"2024-09-21","date_end":"2024-09-22","important_dates":{"abstract":"","full":"2024-08-10","notification":"","final":""},"topics":["Engineering & Technology","Computer/Informatics","Software Engineering","Computer Engineering"],"location":{"virtual":"","full":["Copenhagen","Denmark"],"name":"","street":"","city":"Copenhagen","state":"","ZIP":"","country":"Denmark"},"organizers":["SOEN"],"societies":[],"indexes":[],"emails":["soen@ccsit2024.org","soenconf@gmail.com"]}