{"name":"11th International Conference on Artificial Intelligence and Applications","series":"","short":"AIAPP 2024","website":"https://www.cosit2024.org/aiapp/index","content":"11th International Conference on Artificial Intelligence and Applications (AIAPP 2024) April 20 \\~ 21, 2024, Melbourne, Australia https://www.cosit2024.org/aiapp/index Scope & Topics 11th International Conference on Artificial Intelligence and Applications (AIAPP 2024) is a forum for presenting new advances and research results in the fields of Artificial Intelligence. The conference will bring together leading researchers, engineers and scientists in the domain of interest from around the world. The scope of the conference covers all theoretical and practical aspects of the Artificial Intelligence forum for presenting new advances and research results in the fields of Artificial Intelligence. Authors are solicited to contribute to the conference by submitting articles that illustrate research results, projects, surveying works and industrial experiences that describe significant advances in the following areas, but are not limited to Topics of interest include, but are not limited to, the following: • AI Algorithms • Artificial Intelligence Tools & Applications • Automatic Control • Bioinformatics • CAD Design & Testing • Computational Theories of Learning • Computer Vision and Speech Understanding • Data Mining and Machine Learning Tools • Fuzzy Logic • Heuristic and AI Planning Strategies and Tools • Hybrid Intelligent Systems • Information Retrieval • Intelligence • Intelligent System Architectures • Knowledge Representation • Knowledge-based Systems • Mechatronics • Multimedia & Cognitive Informatics • Natural Language Processing • Neural Networks • Parallel Processing • Pattern Recognition • Pervasive Computing and Ambient • Programming Languages • Reasoning and Evolution • Recent Trends and Developments • Robotics • Semantic Web Techniques and Technologies • Soft Computing Theory and Applications • Software and Hardware Architectures Paper Submission Authors are invited to submit papers through the conference Submission System by April 06, 2024\\. Submissions must be original and should not have been published previously or be under consideration for publication while being evaluated for this conference. The proceedings of the conference will be published by Computer Science Conference Proceedings in Computer Science & Information Technology (CS & IT) series (Confirmed). Selected papers from AIAPP 2024, after further revisions, will be published in the special issues of the following journals • International journal of Artificial Intelligence & Applications (IJAIA) • International Journal on Soft Computing, Artificial Intelligence and Applications (IJSCAI) • Machine Learning and Applications: An International Journal (MLAIJ) • International Journal on Soft Computing (IJSC) • Information Technology in Industry (ITII) Important Dates • Submission Deadline : April 06, 2024 • Authors Notification : April 13, 2024 • Registration & Camera-Ready Paper Due : April 15, 2024 Contact Us Here's where you can reach us : aiapp@cosit2024.org or confaiapp@gmail.com","date_start":"2024-04-20","date_end":"2024-04-21","important_dates":{"abstract":"","full":"2024-04-06","notification":"","final":""},"topics":["Engineering & Technology","Computer/Informatics","Artificial Intelligence"],"location":{"virtual":"","full":["Melbourne","Australia"],"name":"","street":"","city":"Melbourne","state":"","ZIP":"","country":"Australia"},"organizers":["AIAPP 2024"],"societies":[],"indexes":[],"emails":["aiapp@cosit2024.org","confaiapp@gmail.com"]}