{"name":"5th International conference on Advanced Natural Language Processing (AdNLP 2024)","series":"","short":"","website":"https://icaita2024.org/adnlp/index","content":"5th International conference on Advanced Natural Language Processing (AdNLP 2024) May 25 \\~ 26, 2024, Vancouver, Canada https://icaita2024.org/adnlp/index Scope & Topics 5th International conference on Advanced Natural Language Processing (AdNLP 2024) will provide an excellent international forum for sharing knowledge and results in theory, methodology and applications of Natural Language Computing and its advances. Authors are solicited to contribute to the conference by submitting articles that illustrate research results, projects, surveying works and industrial experiences that describe significant advances in NLP. Topics of interest include, but are not limited to, the following • Chunking/Shallow Parsing • Dialog Systems • Discourse • Information Extraction • Information Retrieval • Lexical Semantics • Linguistic Resources • Machine Translation • NLP and AI • NLP and Computational Linguistics • NLP and Information Retrieval • NLP and Machine Learning • Ontology • Paraphrasing/Entailment/Generation • Parsing/Grammatical Formalisms • Phonology, Morphology • POS Tagging • Question Answering • Semantic Processing • Speech Recognition and Synthesis • Spoken Language Processing • Statistical and Knowledge based Methods • Text Mining Paper Submission Authors are invited to submit papers through the conference Submission System by May 04, 2024\\. Submissions must be original and should not have been published previously or be under consideration for publication while being evaluated for this conference. The proceedings of the conference will be published by Computer Science Conference Proceedings in Computer Science & Information Technology (CS & IT) series (Confirmed). Selected papers from AdNLP 2024, after further revisions, will be published in the special issue of the following journals. • International Journal on Natural Language Computing (IJNLC) • International Journal on Information Theory (IJIT) • International Journal on Computational Science & Applications (IJCSA) • Machine Learning and Applications: An International Journal (MLAIJ) • International Journal of Web & Semantic Technology (IJWesT) • Information Technology in Industry (ITII) Contact Us Here's where you can reach us: adnlp@icaita2024.org (or) adnlpconference@gmail.com For more details, please visit: https://icaita2024.org/adnlp/index Paper Submission Link: https://icaita2024.org/submission/index.php","date_start":"2024-05-25","date_end":"2024-05-26","important_dates":{"abstract":"","full":"2024-05-04","notification":"","final":""},"topics":["Engineering & Technology","Computer/Informatics","Natural Language Processing","Machine Learning"],"location":{"virtual":"","full":["Vancouver","Canada"],"name":"","street":"","city":"Vancouver","state":"","ZIP":"","country":"Canada"},"organizers":["AdNLP 2024"],"societies":[],"indexes":[],"emails":["adnlp@icaita2024.org","adnlpconference@gmail.com"]}