{"name":"6th International Conference on Machine Learning & Applications","series":"","short":"CMLA 2024","website":"https://cseit2024.org/cmla/index","content":"6th International Conference on Machine Learning & Applications (CMLA 2024) July 27 \\~ 28, 2024, London, United Kingdom https://cseit2024.org/cmla/index Scope & Topics 6th International Conference on Machine Learning & Applications (CMLA 2024) will provide an excellent international forum for sharing knowledge and results in theory, methodology and applications of on Machine Learning & Applications. Authors are solicited to contribute to the conference by submitting articles that illustrate research results, projects, surveying works and industrial experiences that describe significant advances in the following areas, but are not limited to. Topics of interest include, but are not limited to, the following • Bayesian Network • Computer Vision • Data Mining • Deep Learning • Learning in knowledge-intensive systems • Learning Methods and analysis • Learning Problems • Machine Learning Algorithms • Neural Networks • Predictive Learning • Reinforcement Learning • Supervised Machine Learning • Unsupervised Machine Learning Paper Submission Authors are invited to submit papers through the conference Submission System by July 20, 2024\\. Submissions must be original and should not have been published previously or be under consideration for publication while being evaluated for this conference. The proceedings of the conference will be published by Computer Science Conference Proceedings in Computer Science & Information Technology (CS & IT) series (Confirmed). Selected papers from CMLA 2024, after further revisions, will be published in the special issue of the following journals. • Machine Learning and Applications: An International Journal (MLAIJ) • International Journal of Artificial Intelligence & Applications (IJAIA) • Advances in Vision Computing: An International Journal (AVC) Contact Us Here's where you can reach us: cmla@cseit2024.org (or) cmlaconference@gmail.com For more details, please visit: https://cseit2024.org/cmla/index Paper Submission Link: https://cseit2024.org/submission/index.php","date_start":"2024-07-27","date_end":"2024-07-28","important_dates":{"abstract":"","full":"2024-07-20","notification":"","final":""},"topics":["Engineering & Technology","Computer/Informatics","Machine Learning","Data Mining"],"location":{"virtual":"","full":["London","United Kingdom"],"name":"","street":"","city":"London","state":"","ZIP":"","country":"United Kingdom"},"organizers":["CMLA 2024"],"societies":[],"indexes":[],"emails":["cmla@cseit2024.org","cmlaconference@gmail.com"]}