{"name":"13th International Conference on Soft Computing, Artificial Intelligence and Applications","series":"","short":"SCAI 2024","website":"https://iccsea2024.org/scai/index","content":"13th International Conference on Soft Computing, Artificial Intelligence and Applications (SCAI 2024) November 16 \\~ 17, 2024, Zurich, Switzerland https://iccsea2024.org/scai/index Scope 13th International Conference on Soft Computing, Artificial Intelligence and Applications (SCAI 2024) will provide an excellent international forum for sharing knowledge and results in theory, methodology and applications of artificial intelligence, soft computing. The conference looks for significant contributions to all major fields of the artificial intelligence, soft computing in theoretical and practical aspects. The aim of the conference is to provide a platform to the researchers and practitioners from both academia as well as industry to meet and share cutting-edge development in the field. Authors are solicited to contribute to the conference by submitting articles that illustrate research results, projects, surveying works and industrial experiences that describe significant advances in the following areas, but are not limited to. Topics of interest include, but are not limited to, the following • Algorithms and Bioinformatics • AI Algorithms • Artificial Intelligence • Artificial Intelligence Tools & Applications • Automatic Control • Bioinformatics • Biomedical Engineering • CAD Design & Testing • Computational Theories of Learning • Computer Vision and Speech Understanding • Data Mining and Machine Learning Tools • Data Visualization • E-commerce, e-medicine • Evolutionary Computingn • Fuzzy Logic • Fuzzy Systems • Heuristic and AI Planning Strategies and Tools • Hybrid Intelligent Systems • Image Processing • Information Retrieval • Intelligent System Architectures • Knowledge Representation • Knowledge-based Systems • Machine Learning • Mechatronics • Morphic Computing • Multimedia & Cognitive Informatics • Nano & Micro-systems • Natural Language Processing • Neural Networks • Parallel Processing • Pattern Recognition • Pervasive Computing and Ambient Intelligence • Probabilistic Reasoning • Programming Languages • Reactive Distributed AI • Reasoning and Evolution • Recent Trends and Developments • Robotics • Rough Sets • Semantic Web Techniques and Technologies • Signal or Image Processing • Soft Computing • Soft Computing Theory and Applications • Software & Hardware Architectures • Software Agents • Symbolic Machine Learning • Telecommunications • Vision Recognition • Wavelet • Web Intelligence Applications & Search Paper Submission Authors are invited to submit papers through the conference Submission System by October 26, 2024\\. Submissions must be original and should not have been published previously or be under consideration for publication while being evaluated for this conference. The proceedings of the conference will be published by Computer Science Conference Proceedings in Computer Science & Information Technology (CS & IT) series (Confirmed). Selected papers from SCAI 2024, after further revisions, will be published in the special issue of the following journal. • International Journal of Artificial Intelligence & Applications (IJAIA) • International Journal of Fuzzy Logic Systems (IJFLS) • International Journal on Soft Computing, Artificial Intelligence and Applications (IJSCAI) • International Journal on Soft Computing (IJSC) • Information Technology in Industry (ITII) Important Dates • Submission Deadline : October 26, 2024 • Authors Notification : November 09, 2024 • Registration & camera - Ready Paper Due : November 12, 2024 Contact Us Here's where you can reach us : scai@iccsea2024.org (or) scai\\_conference@yahoo.com","date_start":"2024-11-16","date_end":"2024-11-17","important_dates":{"abstract":"","full":"2024-10-26","notification":"","final":""},"topics":["Engineering & Technology","Computer/Informatics","Artificial Intelligence","Machine Learning"],"location":{"virtual":"","full":["Zurich","Switzerland","Zurich","Switzerland Switzerland"],"name":"","street":"","city":"","state":"","ZIP":"","country":""},"organizers":["SCAI 2024"],"societies":[],"indexes":[],"emails":["scai@iccsea2024.org","_conference@yahoo.com"]}